Workbook

Sheet Balance sheet
B2: Coffee Life - Balance sheet
B4: Consolidated Balance Sheets - $'000 | C4: 43465 | D4: 43830 | E4: 43921
B5: Current assets:
B6: Cash and cash equivalents | C6: 432 | D6: 500 | E6: 516
B7: Accounts receivable, net | C7: 3108 | D7: 3579 | E7: 2050
B8: Inventory | C8: 1790 | D8: 2114 | E8: 1550
B9: Prepaid Expenses and other current assets | C9: 560 | D9: 470 | E9: 310
B10: Total current assets | C10: =SUM(C6:C9) -> 5890 | D10: =SUM(D6:D9) -> 6663 | E10: =SUM(E6:E9) -> 4426
B11: Property, plant and equipment, net | C11: 10340 | D11: 12075 | E11: 14115
B12: Other long-term assets | C12: 450 | D12: 479 | E12: 479
B13: Intangible assets | C13: 1040 | D13: 800 | E13: 740
B14: Goodwill | C14: 3300 | D14: 3300 | E14: 3300
B15: TOTAL ASSETS | C15: =SUM(C10:C14) -> 21020 | D15: =SUM(D10:D14) -> 23317 | E15: =SUM(E10:E14) -> 23060
B16: Current liabilities:
B17: Accounts payable | C17: 1180 | D17: 1315 | E17: 1570
B18: Accrued liabilities | C18: 1710 | D18: 1911 | E18: 2045
B19: Deferred Revenue, Current | C19: 735 | D19: 890 | E19: 900
B20: Short-term debt | C20: 1605 | D20: 1833 | E20: 1750
B21: Total current liabilities | C21: =SUM(C17:C20) -> 5230 | D21: =SUM(D17:D20) -> 5949 | E21: =SUM(E17:E20) -> 6265
B22: Long-term debt | C22: 7500 | D22: 8000 | E22: 7000
B23: Other long-term liabilities | C23: 1500 | D23: 1500 | E23: 1500
B24: Total liabilities | C24: =SUM(C21:C23) -> 14230 | D24: =SUM(D21:D23) -> 15449 | E24: =SUM(E21:E23) -> 14765
B25: Shareholders' equity:
B26: Common stock and Additional paid-in capital | C26: 1100 | D26: 1100 | E26: 1100
B27: Retained Earnings | C27: 5690 | D27: =C27+'Income statement'!C24+'Cash flow statement'!C29 -> 6768 | E27: =D27+'Income statement'!D24+'Cash flow statement'!D29 -> 7195
B28: Total shareholders' equity | C28: =SUM(C26:C27) -> 6790 | D28: =SUM(D26:D27) -> 7868 | E28: =SUM(E26:E27) -> 8295
B29: TOTAL LIABILITIES AND EQUITY | C29: =C24+C28 -> 21020 | D29: =D24+D28 -> 23317 | E29: =E24+E28 -> 23060
B31: Check accounting equation | C31: =C15-C29 -> 0 | D31: =D15-D29 -> 0 | E31: =E15-E29 -> 0

Sheet Income statement
B2: Coffee Life - Income statement
B4: Consolidated Income Statement - $'000, shares in '000 | C4: 43830 | D4: 43921
B6: Net Sales | C6: 22350 | D6: 6553
B7: Cost of sales | C7: 9899 | D7: 2883
B8: Gross profit | C8: =C6-C7 -> 12451 | D8: =D6-D7 -> 3670
B10: Sales and marketing expenses | C10: 2895 | D10: 786
B11: New product development | C11: 679 | D11: 315
B12: Store operating expenses | C12: 2450 | D12: 655
B13: Depreciation and amortization expenses | C13: 1378 | D13: 520
B14: General and administrative expenses | C14: 987 | D14: 305
B15: Other operating expenses | C15: 569 | D15: 128
B16: Total operating expenses | C16: =SUM(C10:C15) -> 8958 | D16: =SUM(D10:D15) -> 2709
B17: Operating income | C17: =C8-C16 -> 3493 | D17: =D8-D16 -> 961
B18: Operating income margin | C18: =C17/C6 -> 0.15628635 | D18: =D17/D6 -> 0.14665039
B20: Interest expense | C20: 630 | D20: 190
B21: Interest income and other | C21: 25 | D21: 207
B22: Income before income taxes | C22: =C17-C20+C21 -> 2888 | D22: =D17-D20+D21 -> 978
B23: Provision for income taxes | C23: 560 | D23: 201
B24: Net Income | C24: =C22-C23 -> 2328 | D24: =D22-D23 -> 777
B25: Net income margin | C25: =C24/C6 -> 0.10416107 | D25: =D24/D6 -> 0.11857165
B27: Weighted average shares outstanding:
B28: Basic | C28: 1200 | D28: 1200
B29: EPS | C29: =C24/C28 -> 1.94 | D29: =D24/D28 -> 0.6475

Sheet Cash flow statement
B2: Coffee Life - Cash flow statement
B4: Consolidated Cash Flow Statement - $'000 | C4: 43830 | D4: 43921
B6: Net Income | C6: ='Income statement'!C24 -> 2328 | D6: ='Income statement'!D24 -> 777
B7: Adjustments:
B8: Depreciation and amortization | C8: ='Income statement'!C13 -> 1378 | D8: ='Income statement'!D13 -> 520
B9: Other non-cash adjustments | C9: 0 | D9: -200
B10: Changes in operating assets and liabilities:
B11: Accounts receivable | C11: ='Balance sheet'!C7-'Balance sheet'!D7 -> -471 | D11: ='Balance sheet'!D7-'Balance sheet'!E7 -> 1529
B12: Inventories | C12: ='Balance sheet'!C8-'Balance sheet'!D8 -> -324 | D12: ='Balance sheet'!D8-'Balance sheet'!E8 -> 564
B13: Accounts payable | C13: ='Balance sheet'!D17-'Balance sheet'!C17 -> 135 | D13: ='Balance sheet'!E17-'Balance sheet'!D17 -> 255
B14: Other operating assets and liabilities | C14: =('Balance sheet'!C9-'Balance sheet'!D9)+('Balance sheet'!D18-'Balance sheet'!C18)+('Balance sheet'!D19-'Balance sheet'!C19) -> 446 | D14: =('Balance sheet'!D9-'Balance sheet'!E9)+('Balance sheet'!E18-'Balance sheet'!D18)+('Balance sheet'!E19-'Balance sheet'!D19) -> 304
B15: Net cash flow from operations (CFO) | C15: =SUM(C6:C14) -> 3492 | D15: =SUM(D6:D14) -> 3749
B17: Purchases of property | C17: ='Balance sheet'!C11-'Balance sheet'!D11+'Balance sheet'!C13-'Balance sheet'!D13-'Income statement'!C13 -> -2873 | D17: -3500
B18: Sales of property | C18: 0 | D18: 1200
B19: Net proceeds from other investments | C19: ='Balance sheet'!C12-'Balance sheet'!D12 -> -29 | D19: 0
B20: Acquisitions, net of cash acquired | C20: 0 | D20: 0
B21: Other | C21: 0 | D21: 0
B22: Net cash flow from investing activities (CFI) | C22: =SUM(C17:C21) -> -2902 | D22: =SUM(D17:D21) -> -2300
B24: Proceeds from ST borrowings | C24: ='Balance sheet'!D20-'Balance sheet'!C20+1000 -> 1228 | D24: ='Balance sheet'!E20-'Balance sheet'!D20+1200 -> 1117
B25: Repayments of ST borrowings | C25: -1000 | D25: -1200
B26: Proceeds from LT borrowings | C26: ='Balance sheet'!D22-'Balance sheet'!C22+3500 -> 4000 | D26: 0
B27: Repayments of LT borrowings | C27: -3500 | D27: ='Balance sheet'!E22-'Balance sheet'!D22 -> -1000
B28: Proceeds from issuance of common stock | C28: 0 | D28: 0
B29: Cash dividends paid | C29: -1250 | D29: -350
B30: Repurchase of common stock | C30: 0 | D30: 0
B31: Other | C31: 0 | D31: 0
B32: Net cash flow from financing activities (CFI) | C32: =SUM(C24:C31) -> -522 | D32: =SUM(D24:D31) -> -1433
B33: Change in cash (CFO+CFI+CFF) | C33: =C15+C22+C32 -> 68 | D33: =D15+D22+D32 -> 16
B35: Cash summary
B36: Beginning of period | C36: ='Balance sheet'!C6 -> 432 | D36: ='Balance sheet'!D6 -> 500
B37: End of period | C37: ='Balance sheet'!D6 -> 500 | D37: ='Balance sheet'!E6 -> 516
B38: Total change in cash on the balance sheet | C38: =C37-C36 -> 68 | D38: =D37-D36 -> 16

Sheet Connections
B2: Connections between the statements
B4: Beginning Balance sheet | C4: Ending Balance sheet | F4: Income Statement | I4: Cash flow statement
B6: Cash | C6: Cash | F6: Revenue | I6: Net Income
B7: + | C7: + | F7: - | I7: +
B8: Other current assets | C8: Other current assets | F8: Cost of revenue | I8: Adjustments
B9: + | C9: + | F9: = | I9: =
B10: LT assets | C10: LT assets | F10: Gross profit | I10: Cash inflow/outflow from operations
B11: = | C11: = | F11: - | I11: +
B12: Total Assets | C12: Total Assets | F12: Operating expenses | I12: Cash inflow/outflow from investing
F13: = | I13: +
B14: Current liabilities | C14: Current liabilities | F14: Operating profit | I14: Cash inflow/outflow from financing
B15: + | C15: + | F15: - | I15: =
B16: Long term liabilities | C16: Long term liabilities | F16: Non-operating expense/(income) | I16: Net change in cash
B17: = | C17: = | F17: = | I17: +
B18: Total liabilities | C18: Total liabilities | F18: Pre-tax income | I18: Beginning cash
F19: - | I19: =
B20: Common stock | C20: Common stock | F20: Taxes | I20: Ending cash
B21: + | C21: + | F21: =
B22: Retained Earnings | C22: Retained Earnings | F22: Net Income
B23: = | C23: =
B24: Total Equity | C24: Total Equity
B26: Assets = Liabilities + Equity | C26: Assets = Liabilities + Equity
B29: Beginning Retained earnings
B30: +
B31: Net Income
B32: -
B33: Dividends
B34: =
B35: Ending Retained earnings
B38: Explanations of the connections:
B39: The net income is the end of the IS and the beginning of the CF statement
B40: The net income also affects the Retained earnings account on the BS
B41: The cash on the beginning BS is the beginning cash on the CF statement
B42: The change in cash from the CF statement plus the beginning cash is equal to the ending cash on the BS
