Workbook

Sheet Valuation summary
B2: Summary various scenarios
B4: Scenario | C4: Share price
B5: Base scenario | C5: ='Valuation - base'!C91 -> 251.55499 | E5: BASE
B6: Lower growth, higher costs | C6: ='Valuation - lower margins'!C91 -> 154.33614 | E6: Price pressure, less services, more regulation, geopolitical
B7: Higher growth, higher profit | C7: ='Valuation - new product'!C91 -> 330.15228 | E7: New and more services - healthcare, iCloud for business, games, original content revenue

Sheet Valuation - base - in class
B2: IS and BS forecast, Free Cash Flows and Apple valuation
B3: BASE - estimated value as of November 2025
B5: Assumptions | C5: Actual | D5: Forecast | E5: Forecast | F5: Forecast | G5: Forecast | H5: Forecast | I5: Forecast | J5: Forecast
B6: Income statement | C6: 2025 | D6: 2026 | E6: 2027 | F6: 2028 | G6: 2029 | H6: 2030 | I6: 2031 | J6: 2032
B7: Sales growth | D7: ='Revenue forecast'!D27 -> 0.17067308 | E7: ='Revenue forecast'!E27 -> 0.11967146 | F7: ='Revenue forecast'!F27 -> 0.07918684 | G7: ='Revenue forecast'!G27 -> 0.07 | H7: ='Revenue forecast'!H27 -> 0.06 | I7: ='Revenue forecast'!I27 -> 0.05 | J7: ='Revenue forecast'!J27 -> 0.04 | L7: See the tab revenue forecast
B8: Cost of sales as % sales | C8: ='IS common size'!V6 -> 0.53094836 | D8: 0.51 | E8: 0.49 | F8: 0.47 | G8: =F8 -> 0.47 | H8: =G8 -> 0.47 | I8: =H8 -> 0.47 | J8: =I8 -> 0.47 | L8: Going down sligthly as a result of higher % of services as % of sales
B9: Ops expenses as % of sales | C9: ='IS common size'!V8 -> 0.14922109 | D9: =C9 -> 0.14922109 | E9: =D9 -> 0.14922109 | F9: =E9 -> 0.14922109 | G9: =F9 -> 0.14922109 | H9: =G9 -> 0.14922109 | I9: =H9 -> 0.14922109 | J9: =I9 -> 0.14922109 | L9: Stable
B10: Interest income | C10: 0.03 | D10: =C10 -> 0.03 | E10: 0.04 | F10: =E10 -> 0.04 | G10: =F10 -> 0.04 | H10: =G10 -> 0.04 | I10: =H10 -> 0.04 | J10: =I10 -> 0.04 | L10: Increasing at the interest rates increase
B11: Interest expense | C11: 0.05 | D11: =C11 -> 0.05 | E11: 0.05 | F11: =E11 -> 0.05 | G11: =F11 -> 0.05 | H11: =G11 -> 0.05 | I11: =H11 -> 0.05 | J11: =I11 -> 0.05 | L11: Increasing at the interest rates increase
B12: Tax rate as % of pretax income (going down) | C12: 0.2 | D12: =C12 -> 0.2 | E12: =D12 -> 0.2 | F12: =E12 -> 0.2 | G12: =F12 -> 0.2 | H12: =G12 -> 0.2 | I12: =H12 -> 0.2 | J12: =I12 -> 0.2 | L12: Based on the new tax rules
B13: Balance sheet
B14: Cash - stable in $ | C14: =C47 -> 35.934 | D14: =C14 -> 35.934 | E14: =D14 -> 35.934 | F14: =E14 -> 35.934 | G14: =F14 -> 35.934 | H14: =G14 -> 35.934 | I14: =H14 -> 35.934 | J14: =I14 -> 35.934 | L14: Stable
B15: ST debt - stable | C15: =C58 -> 20.329 | D15: =C15 -> 20.329 | E15: =D15 -> 20.329 | F15: =E15 -> 20.329 | G15: =F15 -> 20.329 | H15: =G15 -> 20.329 | I15: =H15 -> 20.329 | J15: =I15 -> 20.329 | L15: Stable
B16: LT debt - stable | C16: =C59 -> 78.328 | D16: =C16 -> 78.328 | E16: =D16 -> 78.328 | F16: =E16 -> 78.328 | G16: =F16 -> 78.328 | H16: =G16 -> 78.328 | I16: =H16 -> 78.328 | J16: =I16 -> 78.328 | L16: Stable
B17: AR as % of sales | C17: 0.058721746 | D17: =C17 -> 0.058721746 | E17: =D17 -> 0.058721746 | F17: =E17 -> 0.058721746 | G17: =F17 -> 0.058721746 | H17: =G17 -> 0.058721746 | I17: =H17 -> 0.058721746 | J17: =I17 -> 0.058721746 | L17: Stable
B18: Inventory as % of COGS | C18: 0.023950365 | D18: =C18 -> 0.023950365 | E18: =D18 -> 0.023950365 | F18: =E18 -> 0.023950365 | G18: =F18 -> 0.023950365 | H18: =G18 -> 0.023950365 | I18: =H18 -> 0.023950365 | J18: =I18 -> 0.023950365 | L18: Stable
B19: Goodwill + intangibles+other in $ | C19: =C53 -> 83.727 | D19: =C19 -> 83.727 | E19: =D19 -> 83.727 | F19: =E19 -> 83.727 | G19: =F19 -> 83.727 | H19: =G19 -> 83.727 | I19: =H19 -> 83.727 | J19: =I19 -> 83.727 | L19: Stable
B20: Other current assets as % of sales | C20: 0.11871482 | D20: =C20 -> 0.11871482 | E20: =D20 -> 0.11871482 | F20: =E20 -> 0.11871482 | G20: =F20 -> 0.11871482 | H20: =G20 -> 0.11871482 | I20: =H20 -> 0.11871482 | J20: =I20 -> 0.11871482 | L20: Stable
B21: AP as % of COGS | C21: 0.2494471 | D21: =C21 -> 0.2494471 | E21: =D21 -> 0.2494471 | F21: =E21 -> 0.2494471 | G21: =F21 -> 0.2494471 | H21: =G21 -> 0.2494471 | I21: =H21 -> 0.2494471 | J21: =I21 -> 0.2494471 | L21: Stable
B22: Accrued expenses as % of COGS | C22: 0.29091349 | D22: =C22 -> 0.29091349 | E22: =D22 -> 0.29091349 | F22: =E22 -> 0.29091349 | G22: =F22 -> 0.29091349 | H22: =G22 -> 0.29091349 | I22: =H22 -> 0.29091349 | J22: =I22 -> 0.29091349 | L22: Stable
B23: Non-current liabilities - no change | C23: =C60 -> 41.549 | D23: =C23 -> 41.549 | E23: =D23 -> 41.549 | F23: =E23 -> 41.549 | G23: =F23 -> 41.549 | H23: =G23 -> 41.549 | I23: =H23 -> 41.549 | J23: =I23 -> 41.549 | L23: Stable
B24: Other:
B25: Dividends in $ - increase of 5% per year | C25: 0.05 | D25: =C25 -> 0.05 | E25: =D25 -> 0.05 | F25: =E25 -> 0.05 | G25: =F25 -> 0.05 | H25: =G25 -> 0.05 | I25: =H25 -> 0.05 | J25: =I25 -> 0.05
B26: Share repurchases in $ - 80% of net income | C26: 0.8 | D26: 0.8 | E26: =D26 -> 0.8 | F26: =E26 -> 0.8 | G26: =F26 -> 0.8 | H26: =G26 -> 0.8 | I26: =H26 -> 0.8 | J26: =I26 -> 0.8
B27: Additional share repurchases/dividends to use foreign cash ($'B) | D27: 20 | E27: 20 | F27: 10 | G27: 10 | L27: Extra share repurchases
B28: CapEx as % of next year sales | C28: 0.03 | D28: 0.05 | E28: 0.07 | F28: =E28 -> 0.07 | G28: =F28 -> 0.07 | H28: =G28 -> 0.07 | I28: =H28 -> 0.07 | J28: =I28 -> 0.07 | L28: 3% is historical rate, just a bit gorwing because of potential data center needs
B29: Depreciation as % of current year CapEx | C29: 0.8 | D29: =C29 -> 0.8 | E29: =D29 -> 0.8 | F29: =E29 -> 0.8 | G29: =F29 -> 0.8 | H29: =G29 -> 0.8 | I29: =H29 -> 0.8 | J29: =I29 -> 0.8 | L29: Approximately the historical rate
B30: Growth rate - terminal | C30: 0.035
C32: Actual | D32: Forecast | E32: Forecast | F32: Forecast | G32: Forecast | H32: Forecast | I32: Forecast | J32: Forecast
B33: Income statement forecast | C33: =C6 -> 2025 | D33: =D6 -> 2026 | E33: =E6 -> 2027 | F33: =F6 -> 2028 | G33: =G6 -> 2029 | H33: =H6 -> 2030 | I33: =I6 -> 2031 | J33: =J6 -> 2032
B34: Net sales | C34: =IS!V4 -> 416.161 | L34: See the tab revenue forecast
B35: Cost of sales | C35: =IS!V5 -> -220.96
B36: Gross margin | C36: =SUM(C34:C35) -> 195.201
B37: Total operating expenses | C37: =IS!V7 -> -62.1
B38: Operating income | C38: =SUM(C36:C37) -> 133.101
B39: Interest income
B40: Interest expense
B41: Income before provision for income taxes | C41: =IS!V12 -> 132.729
B42: Provision for income taxes | C42: =IS!V13 -> -20.719
B43: Net income | C43: =SUM(C41:C42) -> 112.01
C45: Actual | D45: Forecast | E45: Forecast | F45: Forecast | G45: Forecast | H45: Forecast | I45: Forecast | J45: Forecast
B46: Balance sheet forecast | C46: =C6 -> 2025 | D46: =D33 -> 2026 | E46: =E33 -> 2027 | F46: =F33 -> 2028 | G46: =G33 -> 2029 | H46: =H33 -> 2030 | I46: =I33 -> 2031 | J46: =J33 -> 2032
B47: Cash and cash equivalents | C47: =BS!V6 -> 35.934
B48: Marketable securities - ST and LT | C48: =BS!V7+BS!V15 -> 96.486 | L48: This is a plug
B49: Accounts receivable, less allowances | C49: =BS!V8 -> 39.777
B50: Inventories | C50: =BS!V9 -> 5.718
B51: Other current assets | C51: =BS!V14+BS!V11 -> 47.765
B52: Property, plant and equipment, net | C52: =BS!V16 -> 49.834 | L52: Prior PPE + CapEx - Depreciation
B53: Goodwill + intangbles + other | C53: =BS!V19 -> 83.727
B54: Total assets | C54: =SUM(C47:C53) -> 359.241
B56: Accounts payable | C56: =BS!V23 -> 69.86
B57: Accrued expenses | C57: =BS!V24+BS!V26 -> 75.442
B58: ST debt | C58: =BS!V27+BS!V28 -> 20.329
B59: Long-term debt | C59: =BS!V29 -> 78.328
B60: Non-current liabilities | C60: =BS!V30 -> 41.549
B61: Total liabilities | C61: =SUM(C56:C60) -> 285.508
B62: Total shareholders' equity | C62: =BS!V33 -> 73.733 | L62: Prior equity + NI - Dividends - buybacks
B63: Total liabilities and equity | C63: =SUM(C61:C62) -> 359.241
B65: Other
B66: CapEx
B67: Depreciation
B68: Dividends | C68: 15
B69: Share repurchases
D71: Forecast | E71: Forecast | F71: Forecast | G71: Forecast | H71: Forecast | I71: Forecast | J71: Forecast
B72: Free cash flow | D72: =D46 -> 2026 | E72: =E46 -> 2027 | F72: =F46 -> 2028 | G72: =G46 -> 2029 | H72: =H46 -> 2030 | I72: =I46 -> 2031 | J72: =J46 -> 2032
B73: EBIT * (1-tax rate)
B74: Depreciation
B75: CapEx
B76: WC calculation
B77: (Increase)/decrease in AR
B78: (Increase)/decrease in Inventory
B79: (Increase)/decrease in other current assets
B80: Increase/(decrease) in AP
B81: Increase/(decrease) in Accrued expenses
B82: Free Cash Flows
B83: Terminal Value
B84: Total Free Cash Flow
... B88: Subtract Debt
B89: Apple market value | E89: `
B90: Number of shares in B | C90: ='cost of capital'!C12 -> 14.8
B91: Share price

Sheet Valuation - base
B2: IS and BS forecast, Free Cash Flows and Apple valuation
B3: BASE - estimated value as of November 2025
B5: Assumptions | C5: Actual | D5: Forecast | E5: Forecast | F5: Forecast | G5: Forecast | H5: Forecast | I5: Forecast | J5: Forecast
B6: Income statement | C6: 2025 | D6: 2026 | E6: 2027 | F6: 2028 | G6: 2029 | H6: 2030 | I6: 2031 | J6: 2032
B7: Sales growth | D7: ='Revenue forecast'!D27 -> 0.17067308 | E7: ='Revenue forecast'!E27 -> 0.11967146 | F7: ='Revenue forecast'!F27 -> 0.07918684 | G7: ='Revenue forecast'!G27 -> 0.07 | H7: ='Revenue forecast'!H27 -> 0.06 | I7: ='Revenue forecast'!I27 -> 0.05 | J7: ='Revenue forecast'!J27 -> 0.04 | L7: See the tab revenue forecast
B8: Cost of sales as % sales | C8: ='IS common size'!V6 -> 0.53094836 | D8: 0.51 | E8: 0.49 | F8: 0.47 | G8: =F8 -> 0.47 | H8: =G8 -> 0.47 | I8: =H8 -> 0.47 | J8: =I8 -> 0.47 | L8: Going down sligthly as a result of higher % of services as % of sales
B9: Ops expenses as % of sales | C9: ='IS common size'!V8 -> 0.14922109 | D9: =C9 -> 0.14922109 | E9: =D9 -> 0.14922109 | F9: =E9 -> 0.14922109 | G9: =F9 -> 0.14922109 | H9: =G9 -> 0.14922109 | I9: =H9 -> 0.14922109 | J9: =I9 -> 0.14922109 | L9: Stable
B10: Interest income | C10: 0.03 | D10: =C10 -> 0.03 | E10: 0.04 | F10: =E10 -> 0.04 | G10: =F10 -> 0.04 | H10: =G10 -> 0.04 | I10: =H10 -> 0.04 | J10: =I10 -> 0.04 | L10: Increasing at the interest rates increase
B11: Interest expense | C11: 0.05 | D11: =C11 -> 0.05 | E11: 0.05 | F11: =E11 -> 0.05 | G11: =F11 -> 0.05 | H11: =G11 -> 0.05 | I11: =H11 -> 0.05 | J11: =I11 -> 0.05 | L11: Increasing at the interest rates increase
B12: Tax rate as % of pretax income (going down) | C12: 0.2 | D12: =C12 -> 0.2 | E12: =D12 -> 0.2 | F12: =E12 -> 0.2 | G12: =F12 -> 0.2 | H12: =G12 -> 0.2 | I12: =H12 -> 0.2 | J12: =I12 -> 0.2 | L12: Based on the new tax rules
B13: Balance sheet
B14: Cash - stable in $ | C14: =C47 -> 35.934 | D14: =C14 -> 35.934 | E14: =D14 -> 35.934 | F14: =E14 -> 35.934 | G14: =F14 -> 35.934 | H14: =G14 -> 35.934 | I14: =H14 -> 35.934 | J14: =I14 -> 35.934 | L14: Stable
B15: ST debt - stable | C15: =C58 -> 20.329 | D15: =C15 -> 20.329 | E15: =D15 -> 20.329 | F15: =E15 -> 20.329 | G15: =F15 -> 20.329 | H15: =G15 -> 20.329 | I15: =H15 -> 20.329 | J15: =I15 -> 20.329 | L15: Stable
B16: LT debt - stable | C16: =C59 -> 78.328 | D16: =C16 -> 78.328 | E16: =D16 -> 78.328 | F16: =E16 -> 78.328 | G16: =F16 -> 78.328 | H16: =G16 -> 78.328 | I16: =H16 -> 78.328 | J16: =I16 -> 78.328 | L16: Stable
B17: AR as % of sales | C17: 0.058721746 | D17: =C17 -> 0.058721746 | E17: =D17 -> 0.058721746 | F17: =E17 -> 0.058721746 | G17: =F17 -> 0.058721746 | H17: =G17 -> 0.058721746 | I17: =H17 -> 0.058721746 | J17: =I17 -> 0.058721746 | L17: Stable
B18: Inventory as % of COGS | C18: 0.023950365 | D18: =C18 -> 0.023950365 | E18: =D18 -> 0.023950365 | F18: =E18 -> 0.023950365 | G18: =F18 -> 0.023950365 | H18: =G18 -> 0.023950365 | I18: =H18 -> 0.023950365 | J18: =I18 -> 0.023950365 | L18: Stable
B19: Goodwill + intangibles+other in $ | C19: =C53 -> 83.727 | D19: =C19 -> 83.727 | E19: =D19 -> 83.727 | F19: =E19 -> 83.727 | G19: =F19 -> 83.727 | H19: =G19 -> 83.727 | I19: =H19 -> 83.727 | J19: =I19 -> 83.727 | L19: Stable
B20: Other current assets as % of sales | C20: 0.11871482 | D20: =C20 -> 0.11871482 | E20: =D20 -> 0.11871482 | F20: =E20 -> 0.11871482 | G20: =F20 -> 0.11871482 | H20: =G20 -> 0.11871482 | I20: =H20 -> 0.11871482 | J20: =I20 -> 0.11871482 | L20: Stable
B21: AP as % of COGS | C21: 0.2494471 | D21: =C21 -> 0.2494471 | E21: =D21 -> 0.2494471 | F21: =E21 -> 0.2494471 | G21: =F21 -> 0.2494471 | H21: =G21 -> 0.2494471 | I21: =H21 -> 0.2494471 | J21: =I21 -> 0.2494471 | L21: Stable
B22: Accrued expenses as % of COGS | C22: 0.29091349 | D22: =C22 -> 0.29091349 | E22: =D22 -> 0.29091349 | F22: =E22 -> 0.29091349 | G22: =F22 -> 0.29091349 | H22: =G22 -> 0.29091349 | I22: =H22 -> 0.29091349 | J22: =I22 -> 0.29091349 | L22: Stable
B23: Non-current liabilities - no change | C23: =C60 -> 41.549 | D23: =C23 -> 41.549 | E23: =D23 -> 41.549 | F23: =E23 -> 41.549 | G23: =F23 -> 41.549 | H23: =G23 -> 41.549 | I23: =H23 -> 41.549 | J23: =I23 -> 41.549 | L23: Stable
B24: Other:
B25: Dividends in $ - increase of 5% per year | C25: 0.05 | D25: =C25 -> 0.05 | E25: =D25 -> 0.05 | F25: =E25 -> 0.05 | G25: =F25 -> 0.05 | H25: =G25 -> 0.05 | I25: =H25 -> 0.05 | J25: =I25 -> 0.05
B26: Share repurchases in $ - 80% of net income | C26: 0.8 | D26: 0.8 | E26: =D26 -> 0.8 | F26: =E26 -> 0.8 | G26: =F26 -> 0.8 | H26: =G26 -> 0.8 | I26: =H26 -> 0.8 | J26: =I26 -> 0.8
B27: Additional share repurchases/dividends to use foreign cash ($'B) | D27: 20 | E27: 20 | F27: 10 | G27: 10 | L27: Extra share repurchases
B28: CapEx as % of next year sales | C28: 0.03 | D28: 0.05 | E28: 0.07 | F28: =E28 -> 0.07 | G28: =F28 -> 0.07 | H28: =G28 -> 0.07 | I28: =H28 -> 0.07 | J28: =I28 -> 0.07 | L28: 3% is historical rate, just a bit gorwing because of potential data center needs
B29: Depreciation as % of current year CapEx | C29: 0.8 | D29: =C29 -> 0.8 | E29: =D29 -> 0.8 | F29: =E29 -> 0.8 | G29: =F29 -> 0.8 | H29: =G29 -> 0.8 | I29: =H29 -> 0.8 | J29: =I29 -> 0.8 | L29: Approximately the historical rate
B30: Growth rate - terminal | C30: 0.035
C32: Actual | D32: Forecast | E32: Forecast | F32: Forecast | G32: Forecast | H32: Forecast | I32: Forecast | J32: Forecast
B33: Income statement forecast | C33: =C6 -> 2025 | D33: =D6 -> 2026 | E33: =E6 -> 2027 | F33: =F6 -> 2028 | G33: =G6 -> 2029 | H33: =H6 -> 2030 | I33: =I6 -> 2031 | J33: =J6 -> 2032
B34: Net sales | C34: =IS!V4 -> 416.161 | D34: ='Revenue forecast'!D22 -> 487 | E34: ='Revenue forecast'!E22 -> 545.28 | F34: ='Revenue forecast'!F22 -> 588.459 | G34: ='Revenue forecast'!G22 -> 629.65113 | H34: ='Revenue forecast'!H22 -> 667.4302 | I34: ='Revenue forecast'!I22 -> 700.80171 | J34: ='Revenue forecast'!J22 -> 728.83378 | L34: See the tab revenue forecast
B35: Cost of sales | C35: =IS!V5 -> -220.96 | D35: =-D34*D8 -> -248.37 | E35: =-E34*E8 -> -267.1872 | F35: =-F34*F8 -> -276.57573 | G35: =-G34*G8 -> -295.93603 | H35: =-H34*H8 -> -313.69219 | I35: =-I34*I8 -> -329.3768 | J35: =-J34*J8 -> -342.55187
B36: Gross margin | C36: =SUM(C34:C35) -> 195.201 | D36: =SUM(D34:D35) -> 238.63 | E36: =SUM(E34:E35) -> 278.0928 | F36: =SUM(F34:F35) -> 311.88327 | G36: =SUM(G34:G35) -> 333.7151 | H36: =SUM(H34:H35) -> 353.738 | I36: =SUM(I34:I35) -> 371.42491 | J36: =SUM(J34:J35) -> 386.2819
B37: Total operating expenses | C37: =IS!V7 -> -62.1 | D37: =-D34*D9 -> -72.670673 | E37: =-E34*E9 -> -81.367279 | F37: =-F34*F9 -> -87.810496 | G37: =-G34*G9 -> -93.957231 | H37: =-H34*H9 -> -99.594665 | I37: =-I34*I9 -> -104.5744 | J37: =-J34*J9 -> -108.75737
B38: Operating income | C38: =SUM(C36:C37) -> 133.101 | D38: =SUM(D36:D37) -> 165.95933 | E38: =SUM(E36:E37) -> 196.72552 | F38: =SUM(F36:F37) -> 224.07277 | G38: =SUM(G36:G37) -> 239.75787 | H38: =SUM(H36:H37) -> 254.14334 | I38: =SUM(I36:I37) -> 266.85051 | J38: =SUM(J36:J37) -> 277.52453
B39: Interest income | D39: =D10*C48 -> 2.89458 | E39: =E10*D48 -> 2.8527106 | F39: =F10*E48 -> 2.2824597 | G39: =G10*F48 -> 2.1398552 | H39: =H10*G48 -> 2.2609205 | I39: =I10*H48 -> 2.8107626 | J39: =J10*I48 -> 3.3956528
B40: Interest expense | D40: =-D11*(C58+C59) -> -4.93285 | E40: =-E11*(D58+D59) -> -4.93285 | F40: =-F11*(E58+E59) -> -4.93285 | G40: =-G11*(F58+F59) -> -4.93285 | H40: =-H11*(G58+G59) -> -4.93285 | I40: =-I11*(H58+H59) -> -4.93285 | J40: =-J11*(I58+I59) -> -4.93285
B41: Income before provision for income taxes | C41: =IS!V12 -> 132.729 | D41: =SUM(D38:D40) -> 163.92106 | E41: =SUM(E38:E40) -> 194.64538 | F41: =SUM(F38:F40) -> 221.42238 | G41: =SUM(G38:G40) -> 236.96487 | H41: =SUM(H38:H40) -> 251.47141 | I41: =SUM(I38:I40) -> 264.72842 | J41: =SUM(J38:J40) -> 275.98733
B42: Provision for income taxes | C42: =IS!V13 -> -20.719 | D42: =-D41*D12 -> -32.784211 | E42: =-E41*E12 -> -38.929076 | F42: =-F41*F12 -> -44.284477 | G42: =-G41*G12 -> -47.392975 | H42: =-H41*H12 -> -50.294282 | I42: =-I41*I12 -> -52.945684 | J42: =-J41*J12 -> -55.197466
B43: Net income | C43: =SUM(C41:C42) -> 112.01 | D43: =SUM(D41:D42) -> 131.13685 | E43: =SUM(E41:E42) -> 155.71631 | F43: =SUM(F41:F42) -> 177.13791 | G43: =SUM(G41:G42) -> 189.5719 | H43: =SUM(H41:H42) -> 201.17713 | I43: =SUM(I41:I42) -> 211.78274 | J43: =SUM(J41:J42) -> 220.78986
C45: Actual | D45: Forecast | E45: Forecast | F45: Forecast | G45: Forecast | H45: Forecast | I45: Forecast | J45: Forecast
B46: Balance sheet forecast | C46: =C6 -> 2025 | D46: =D33 -> 2026 | E46: =E33 -> 2027 | F46: =F33 -> 2028 | G46: =G33 -> 2029 | H46: =H33 -> 2030 | I46: =I33 -> 2031 | J46: =J33 -> 2032
B47: Cash and cash equivalents | C47: =BS!V6 -> 35.934 | D47: =D14 -> 35.934 | E47: =D47 -> 35.934 | F47: =E47 -> 35.934 | G47: =F47 -> 35.934 | H47: =G47 -> 35.934 | I47: =H47 -> 35.934 | J47: =I47 -> 35.934
B48: Marketable securities - ST and LT | C48: =BS!V7+BS!V15 -> 96.486 | D48: =D63-D47-SUM(D49:D53) -> 71.317765 | E48: =E63-E47-SUM(E49:E53) -> 57.061491 | F48: =F63-F47-SUM(F49:F53) -> 53.496381 | G48: =G63-G47-SUM(G49:G53) -> 56.523011 | H48: =H63-H47-SUM(H49:H53) -> 70.269065 | I48: =I63-I47-SUM(I49:I53) -> 84.89132 | J48: =J63-J47-SUM(J49:J53) -> 99.96139 | L48: This is a plug
B49: Accounts receivable, less allowances | C49: =BS!V8 -> 39.777 | D49: =D17*D34 -> 28.59749 | E49: =E17*E34 -> 32.019793 | F49: =F17*F34 -> 34.55534 | G49: =G17*G34 -> 36.974213 | H49: =H17*H34 -> 39.192666 | I49: =I17*I34 -> 41.1523 | J49: =J17*J34 -> 42.798392
B50: Inventories | C50: =BS!V9 -> 5.718 | D50: =-D18*D35 -> 5.9485522 | E50: =-E18*E35 -> 6.3992311 | F50: =-F18*F35 -> 6.6240898 | G50: =-G18*G35 -> 7.0877761 | H50: =-H18*H35 -> 7.5130426 | I50: =-I18*I35 -> 7.8886948 | J50: =-J18*J35 -> 8.2042426
B51: Other current assets | C51: =BS!V14+BS!V11 -> 47.765 | D51: =D20*D34 -> 57.814119 | E51: =E20*E34 -> 64.732819 | F51: =F20*F34 -> 69.858807 | G51: =G20*G34 -> 74.748923 | H51: =H20*H34 -> 79.233859 | I51: =I20*I34 -> 83.195552 | J51: =J20*J34 -> 86.523374
B52: Property, plant and equipment, net | C52: =BS!V16 -> 49.834 | D52: =C52+D66-D67 -> 55.2868 | E52: =D52+E66-E67 -> 63.525226 | F52: =E52+F66-F67 -> 72.340342 | G52: =F52+G66-G67 -> 81.684365 | H52: =G52+H66-H67 -> 91.495588 | I52: =H52+I66-I67 -> 101.30681 | J52: =I52+J66-J67 -> 111.11804 | L52: Prior PPE + CapEx - Depreciation
B53: Goodwill + intangbles + other | C53: =BS!V19 -> 83.727 | D53: =D19 -> 83.727 | E53: =E19 -> 83.727 | F53: =F19 -> 83.727 | G53: =G19 -> 83.727 | H53: =H19 -> 83.727 | I53: =I19 -> 83.727 | J53: =J19 -> 83.727
B54: Total assets | C54: =SUM(C47:C53) -> 359.241 | D54: =SUM(D47:D53) -> 338.62573 | E54: =SUM(E47:E53) -> 343.39956 | F54: =SUM(F47:F53) -> 356.53596 | G54: =SUM(G47:G53) -> 376.67929 | H54: =SUM(H47:H53) -> 407.36522 | I54: =SUM(I47:I53) -> 438.09568 | J54: =SUM(J47:J53) -> 468.26643
B56: Accounts payable | C56: =BS!V23 -> 69.86 | D56: =-D21*D35 -> 61.955175 | E56: =-E21*E35 -> 66.649071 | F56: =-F21*F35 -> 68.991012 | G56: =-G21*G35 -> 73.820383 | H56: =-H21*H35 -> 78.249606 | I56: =-I21*I35 -> 82.162087 | J56: =-J21*J35 -> 85.44857
B57: Accrued expenses | C57: =BS!V24+BS!V26 -> 75.442 | D57: =-D22*D35 -> 72.254183 | E57: =-E22*E35 -> 77.72836 | F57: =-F22*F35 -> 80.45961 | G57: =-G22*G35 -> 86.091783 | H57: =-H22*H35 -> 91.25729 | I57: =-I22*I35 -> 95.820154 | J57: =-J22*J35 -> 99.65296
B58: ST debt | C58: =BS!V27+BS!V28 -> 20.329 | D58: =D15 -> 20.329 | E58: =E15 -> 20.329 | F58: =F15 -> 20.329 | G58: =G15 -> 20.329 | H58: =H15 -> 20.329 | I58: =I15 -> 20.329 | J58: =J15 -> 20.329
B59: Long-term debt | C59: =BS!V29 -> 78.328 | D59: =D16 -> 78.328 | E59: =E16 -> 78.328 | F59: =F16 -> 78.328 | G59: =G16 -> 78.328 | H59: =H16 -> 78.328 | I59: =I16 -> 78.328 | J59: =J16 -> 78.328
B60: Non-current liabilities | C60: =BS!V30 -> 41.549 | D60: =D23 -> 41.549 | E60: =E23 -> 41.549 | F60: =F23 -> 41.549 | G60: =G23 -> 41.549 | H60: =H23 -> 41.549 | I60: =I23 -> 41.549 | J60: =J23 -> 41.549
B61: Total liabilities | C61: =SUM(C56:C60) -> 285.508 | D61: =SUM(D56:D60) -> 274.41536 | E61: =SUM(E56:E60) -> 284.58343 | F61: =SUM(F56:F60) -> 289.65662 | G61: =SUM(G56:G60) -> 300.11817 | H61: =SUM(H56:H60) -> 309.7129 | I61: =SUM(I56:I60) -> 318.18824 | J61: =SUM(J56:J60) -> 325.30753
B62: Total shareholders' equity | C62: =BS!V33 -> 73.733 | D62: =C62+D43-D68-D69 -> 64.210369 | E62: =D62+E43-E68-E69 -> 58.81613 | F62: =E62+F43-F68-F69 -> 66.879337 | G62: =F62+G43-G68-G69 -> 76.561123 | H62: =G62+H43-H68-H69 -> 97.652325 | I62: =H62+I43-I68-I69 -> 119.90744 | J62: =I62+J43-J68-J69 -> 142.9589 | L62: Prior equity + NI - Dividends - buybacks
B63: Total liabilities and equity | C63: =SUM(C61:C62) -> 359.241 | D63: =D62+D61 -> 338.62573 | E63: =E62+E61 -> 343.39956 | F63: =F62+F61 -> 356.53596 | G63: =G62+G61 -> 376.67929 | H63: =H62+H61 -> 407.36522 | I63: =I62+I61 -> 438.09568 | J63: =J62+J61 -> 468.26643
B65: Other
B66: CapEx | D66: =D28*E34 -> 27.264 | E66: =E28*F34 -> 41.19213 | F66: =F28*G34 -> 44.075579 | G66: =G28*H34 -> 46.720114 | H66: =H28*I34 -> 49.05612 | I66: =H66 -> 49.05612 | J66: =I66 -> 49.05612
B67: Depreciation | D67: =D66*D29 -> 21.8112 | E67: =E66*E29 -> 32.953704 | F67: =F66*F29 -> 35.260463 | G67: =G66*G29 -> 37.376091 | H67: =H66*H29 -> 39.244896 | I67: =H67 -> 39.244896 | J67: =I67 -> 39.244896
B68: Dividends | C68: 15 | D68: =C68*(1+D25) -> 15.75 | E68: =D68*(1+E25) -> 16.5375 | F68: =E68*(1+F25) -> 17.364375 | G68: =F68*(1+G25) -> 18.232594 | H68: =G68*(1+H25) -> 19.144223 | I68: =H68*(1+I25) -> 20.101435 | J68: =I68*(1+J25) -> 21.106506
B69: Share repurchases | D69: =D26*D43+D27 -> 124.90948 | E69: =E26*E43+E27 -> 144.57304 | F69: =F26*F43+F27 -> 151.71033 | G69: =G26*G43+G27 -> 161.65752 | H69: =H26*H43+H27 -> 160.9417 | I69: =I26*I43+I27 -> 169.42619 | J69: =J26*J43+J27 -> 176.63189
D71: Forecast | E71: Forecast | F71: Forecast | G71: Forecast | H71: Forecast | I71: Forecast | J71: Forecast
B72: Free cash flow | D72: =D46 -> 2026 | E72: =E46 -> 2027 | F72: =F46 -> 2028 | G72: =G46 -> 2029 | H72: =H46 -> 2030 | I72: =I46 -> 2031 | J72: =J46 -> 2032
B73: EBIT * (1-tax rate) | D73: =D38*(1-D12) -> 132.76746 | E73: =E38*(1-E12) -> 157.38042 | F73: =F38*(1-F12) -> 179.25822 | G73: =G38*(1-G12) -> 191.80629 | H73: =H38*(1-H12) -> 203.31467 | I73: =I38*(1-I12) -> 213.48041 | J73: =J38*(1-J12) -> 222.01962
B74: Depreciation | D74: =D67 -> 21.8112 | E74: =E67 -> 32.953704 | F74: =F67 -> 35.260463 | G74: =G67 -> 37.376091 | H74: =H67 -> 39.244896 | I74: =I67 -> 39.244896 | J74: =J67 -> 39.244896
B75: CapEx | D75: =-D66 -> -27.264 | E75: =-E66 -> -41.19213 | F75: =-F66 -> -44.075579 | G75: =-G66 -> -46.720114 | H75: =-H66 -> -49.05612 | I75: =-I66 -> -49.05612 | J75: =-J66 -> -49.05612
B76: WC calculation
B77: (Increase)/decrease in AR | D77: =C49-D49 -> 11.17951 | E77: =D49-E49 -> -3.4223033 | F77: =E49-F49 -> -2.5355463 | G77: =F49-G49 -> -2.4188738 | H77: =G49-H49 -> -2.2184528 | I77: =H49-I49 -> -1.9596333 | J77: =I49-J49 -> -1.646092
B78: (Increase)/decrease in Inventory | D78: =C50-D50 -> -0.23055224 | E78: =D50-E50 -> -0.45067882 | F78: =E50-F50 -> -0.22485872 | G78: =F50-G50 -> -0.46368628 | H78: =G50-H50 -> -0.42526656 | I78: =H50-I50 -> -0.37565213 | J78: =I50-J50 -> -0.31554779
B79: (Increase)/decrease in other current assets | D79: =C51-D51 -> -10.049119 | E79: =D51-E51 -> -6.9187 | F79: =E51-F51 -> -5.1259874 | G79: =F51-G51 -> -4.8901165 | H79: =G51-H51 -> -4.4849354 | I79: =H51-I51 -> -3.9616929 | J79: =I51-J51 -> -3.3278221
B80: Increase/(decrease) in AP | D80: =D56-C56 -> -7.904825 | E80: =E56-D56 -> 4.6938959 | F80: =F56-E56 -> 2.3419415 | G80: =G56-F56 -> 4.8293709 | H80: =H56-G56 -> 4.429223 | I80: =I56-H56 -> 3.9124803 | J80: =J56-I56 -> 3.2864835
B81: Increase/(decrease) in Accrued expenses | D81: =D57-C57 -> -3.1878171 | E81: =E57-D57 -> 5.4741773 | F81: =F57-E57 -> 2.73125 | G81: =G57-F57 -> 5.6321727 | H81: =H57-G57 -> 5.165507 | I81: =I57-H57 -> 4.5628645 | J81: =J57-I57 -> 3.8328062
B82: Free Cash Flows | D82: =SUM(D73:D81) -> 117.12186 | E82: =SUM(E73:E81) -> 148.51838 | F82: =SUM(F73:F81) -> 167.6299 | G82: =SUM(G73:G81) -> 185.15114 | H82: =SUM(H73:H81) -> 195.96952 | I82: =SUM(I73:I81) -> 205.84755 | J82: =SUM(J73:J81) -> 214.03823
B83: Terminal Value | J83: =J82*(1+C30)/('cost of capital'!C22-'Valuation - base'!C30) -> 4825.8265
B84: Total Free Cash Flow | D84: =SUM(D82:D83) -> 117.12186 | E84: =SUM(E82:E83) -> 148.51838 | F84: =SUM(F82:F83) -> 167.6299 | G84: =SUM(G82:G83) -> 185.15114 | H84: =SUM(H82:H83) -> 195.96952 | I84: =SUM(I82:I83) -> 205.84755 | J84: =SUM(J82:J83) -> 5039.8647
B86: PV of the Total Free Cash Flow | C86: =NPV('cost of capital'!C22,D84:J84) -> 3689.2509
B87: Add cash and MS | C87: =C47+C48 -> 132.42
B88: Subtract Debt | C88: =-(C59+C58) -> -98.657
B89: Apple market value | C89: =SUM(C86:C88) -> 3723.0139 | E89: `
B90: Number of shares in B | C90: ='cost of capital'!C12 -> 14.8
B91: Share price | C91: =C89/C90 -> 251.55499

Sheet Forecast vs Actuals 2025
B2: Forecast versus actuals - 2025
B4: Income statement forecast | C4: Forecast - April 2025 | D4: Actuals - September 2025 | E4: Difference Actual - Forecast | G4: Comments
B5: Net sales | C5: 430.05 | D5: 416.161 | E5: =D5-C5 -> -13.889 | G5: A bit lower revenue than I projected :-(
B6: Cost of sales | C6: -223.626 | D6: -220.96 | E6: =D6-C6 -> 2.666 | G6: Very close
B7: Gross margin | C7: 206.424 | D7: 195.201 | E7: =D7-C7 -> -11.223 | G7: Because of the revenue miss
B8: Total operating expenses | C8: -55.9065 | D8: -62.1 | E8: =D8-C8 -> -6.1935 | G8: Lower revenue and higher ops expenses is why the ops income is off
B9: Operating income | C9: 150.5175 | D9: 133.101 | E9: =D9-C9 -> -17.4165
B10: Interest income
B11: Interest expense
B12: Income before provision for income taxes | C12: 148.9775 | D12: 132.729 | E12: =D12-C12 -> -16.2485
B13: Provision for income taxes | C13: -29.7955 | D13: -20.719 | E13: =D13-C13 -> 9.0765
B14: Net income | C14: 119.182 | D14: 112.01 | E14: =D14-C14 -> -7.172
B16: Balance sheet forecast | C16: =C4 -> Forecast - April 2025 | D16: =D4 -> Actuals - September 2025 | E16: Difference Actual - Forecast
B17: Cash and cash equivalents | C17: 30 | D17: 35.934 | E17: =D17-C17 -> 5.934 | G17: This is very close
B18: Marketable securities - ST and LT | C18: 103.3306 | D18: 96.486 | E18: =D18-C18 -> -6.8445983 | G18: And this one
B19: Accounts receivable, less allowances | C19: 25.253287 | D19: 39.777 | E19: =D19-C19 -> 14.523713 | G19: Probably just timing
B20: Inventories | C20: 5.3559244 | D20: 5.718 | E20: =D20-C20 -> 0.3620756
B21: Other current assets | C21: 51.05331 | D21: 47.765 | E21: =D21-C21 -> -3.2883102
B22: Property, plant and equipment, net | C22: 48.850156 | D22: 49.834 | E22: =D22-C22 -> 0.983844
B23: Goodwill + intangibles + other | C23: 75 | D23: 83.727 | E23: =D23-C23 -> 8.727
B24: Total assets | C24: 338.84328 | D24: 359.241 | E24: =D24-C24 -> 20.397724
B26: Accounts payable | C26: 55.782856 | D26: 69.86 | E26: =D26-C26 -> 14.077144 | G26: Basically slower collections and slower payments
B27: Accrued expenses | C27: 65.05582 | D27: 75.442 | E27: =D27-C27 -> 10.38618
B28: ST debt | C28: 21 | D28: 20.329 | E28: =D28-C28 -> -0.671
B29: Long-term debt | C29: 86 | D29: 78.328 | E29: =D29-C29 -> -7.672
B30: Non-current liabilities | C30: 54 | D30: 41.549 | E30: =D30-C30 -> -12.451
B31: Total liabilities | C31: 281.83868 | D31: 285.508 | E31: =D31-C31 -> 3.6693244
B32: Total shareholders' equity | C32: 57.0046 | D32: 73.733 | E32: =D32-C32 -> 16.7284 | G32: I expected higher share repurchases
B33: Total liabilities and equity | C33: 338.84328 | D33: 359.241 | E33: =D33-C33 -> 20.397724
B35: Other
B36: Dividends | C36: 15.54 | D36: 15 | E36: =D36-C36 -> -0.54
B37: Share repurchases | C37: 103 | D37: 91 | E37: =D37-C37 -> -12

Sheet Revenue forecast
B2: Apple revenue forecast as of November 2025
C4: Actual | D4: Forecast | E4: Forecast | F4: Forecast | G4: Forecast | H4: Forecast | I4: Forecast | J4: Forecast
B5: Volume by product | C5: 2025 | D5: 2026 | E5: 2027 | F5: 2028 | G5: 2029 | H5: 2030 | I5: 2031 | J5: 2032
B6: iPhone (in M) | D6: 260 | E6: 270 | F6: 270 | L6: From JPM projections
B7: iPad (in M) | D7: 70 | E7: 60 | F7: 60 | L7: From JPM projections
B9: Price by product | C9: =C5 -> 2025 | D9: =D5 -> 2026 | E9: =E5 -> 2027 | F9: =F5 -> 2028 | G9: =G5 -> 2029 | H9: =H5 -> 2030 | I9: =I5 -> 2031 | J9: =J5 -> 2032
B10: iPhone (in $) - blended | D10: 950 | E10: 1050 | F10: 1100 | L10: From JPM projections
B11: iPad (in $) - blended | D11: 480 | E11: 470 | F11: 450 | L11: From JPM projections
B13: Other products growth | C13: =C5 -> 2025 | D13: =D5 -> 2026 | E13: =E5 -> 2027 | F13: =F5 -> 2028 | G13: =G5 -> 2029 | H13: =H5 -> 2030 | I13: =I5 -> 2031 | J13: =J5 -> 2032
B14: Mac, iWatch, iPods | C14: 0.05 | D14: 0.08 | E14: 0.1 | F14: 0.1 | L14: From JPM projections
B15: Services | C15: 0.14 | D15: 0.2 | E15: 0.15 | F15: 0.15 | L15: From JPM projections
B17: Total revenue in $'B | C17: =C13 -> 2025 | D17: =D13 -> 2026 | E17: =E13 -> 2027 | F17: =F13 -> 2028 | G17: =G13 -> 2029 | H17: =H13 -> 2030 | I17: =I13 -> 2031 | J17: =J13 -> 2032
B18: iPhone | C18: 209 | D18: =D6*D10/1000 -> 247 | E18: =E6*E10/1000 -> 283.5 | F18: =F6*F10/1000 -> 297
B19: iPad | C19: 28 | D19: =D7*D11/1000 -> 33.6 | E19: =E7*E11/1000 -> 28.2 | F19: =F7*F11/1000 -> 27
B20: Other products | C20: 70 | D20: =C20*(1+D14) -> 75.6 | E20: =D20*(1+E14) -> 83.16 | F20: =E20*(1+F14) -> 91.476
B21: Services | C21: 109 | D21: =C21*(1+D15) -> 130.8 | E21: =D21*(1+E15) -> 150.42 | F21: =E21*(1+F15) -> 172.983
B22: Total | C22: =SUM(C18:C21) -> 416 | D22: =SUM(D18:D21) -> 487 | E22: =SUM(E18:E21) -> 545.28 | F22: =SUM(F18:F21) -> 588.459 | G22: =F22*(1+G27) -> 629.65113 | H22: =G22*(1+H27) -> 667.4302 | I22: =H22*(1+I27) -> 700.80171 | J22: =I22*(1+J27) -> 728.83378
C25: Calculated | D25: Calculated | E25: Calculated | F25: Calculated | G25: Estimate | H25: Estimate | I25: Estimate | J25: Estimate
C26: =C17 -> 2025 | D26: =D17 -> 2026 | E26: =E17 -> 2027 | F26: =F17 -> 2028 | G26: =G17 -> 2029 | H26: =H17 -> 2030 | I26: =I17 -> 2031 | J26: =J17 -> 2032
B27: Total revenue growth rate | D27: =D22/C22-1 -> 0.17067308 | E27: =E22/D22-1 -> 0.11967146 | F27: =F22/E22-1 -> 0.07918684 | G27: 0.07 | H27: 0.06 | I27: 0.05 | J27: 0.04

Sheet Valuation - new product
B2: IS and BS forecast, Free Cash Flows and Apple valuation
B3: BASE - estimated value as of November 2025
B5: Assumptions | C5: Actual | D5: Forecast | E5: Forecast | F5: Forecast | G5: Forecast | H5: Forecast | I5: Forecast | J5: Forecast
B6: Income statement | C6: 2025 | D6: 2026 | E6: 2027 | F6: 2028 | G6: 2029 | H6: 2030 | I6: 2031 | J6: 2032
B7: Sales growth | D7: ='Revenue forecast'!D27 -> 0.17067308 | E7: 0.15 | F7: 0.2 | G7: 0.15 | H7: 0.1 | I7: ='Revenue forecast'!I27 -> 0.05 | J7: ='Revenue forecast'!J27 -> 0.04 | L7: New product and higher revenue
B8: Cost of sales as % sales | C8: ='IS common size'!V6 -> 0.53094836 | D8: 0.5 | E8: 0.48 | F8: 0.46 | G8: 0.45 | H8: =G8 -> 0.45 | I8: =H8 -> 0.45 | J8: =I8 -> 0.45 | L8: Higher margins mainly because of the new product
B9: Ops expenses as % of sales | C9: ='IS common size'!V8 -> 0.14922109 | D9: =C9 -> 0.14922109 | E9: =D9 -> 0.14922109 | F9: =E9 -> 0.14922109 | G9: =F9 -> 0.14922109 | H9: =G9 -> 0.14922109 | I9: =H9 -> 0.14922109 | J9: =I9 -> 0.14922109 | L9: Stable
B10: Interest income | C10: 0.03 | D10: =C10 -> 0.03 | E10: 0.04 | F10: =E10 -> 0.04 | G10: =F10 -> 0.04 | H10: =G10 -> 0.04 | I10: =H10 -> 0.04 | J10: =I10 -> 0.04 | L10: Increasing at the interest rates increase
B11: Interest expense | C11: 0.05 | D11: =C11 -> 0.05 | E11: 0.05 | F11: =E11 -> 0.05 | G11: =F11 -> 0.05 | H11: =G11 -> 0.05 | I11: =H11 -> 0.05 | J11: =I11 -> 0.05 | L11: Increasing at the interest rates increase
B12: Tax rate as % of pretax income (going down) | C12: 0.2 | D12: =C12 -> 0.2 | E12: =D12 -> 0.2 | F12: =E12 -> 0.2 | G12: =F12 -> 0.2 | H12: =G12 -> 0.2 | I12: =H12 -> 0.2 | J12: =I12 -> 0.2 | L12: Based on the new tax rules
B13: Balance sheet
B14: Cash - stable in $ | C14: =C47 -> 35.934 | D14: =C14 -> 35.934 | E14: =D14 -> 35.934 | F14: =E14 -> 35.934 | G14: =F14 -> 35.934 | H14: =G14 -> 35.934 | I14: =H14 -> 35.934 | J14: =I14 -> 35.934 | L14: Stable
B15: ST debt - stable | C15: =C58 -> 20.329 | D15: =C15 -> 20.329 | E15: =D15 -> 20.329 | F15: =E15 -> 20.329 | G15: =F15 -> 20.329 | H15: =G15 -> 20.329 | I15: =H15 -> 20.329 | J15: =I15 -> 20.329 | L15: Stable
B16: LT debt - stable | C16: =C59 -> 78.328 | D16: =C16 -> 78.328 | E16: =D16 -> 78.328 | F16: =E16 -> 78.328 | G16: =F16 -> 78.328 | H16: =G16 -> 78.328 | I16: =H16 -> 78.328 | J16: =I16 -> 78.328 | L16: Stable
B17: AR as % of sales | C17: 0.058721746 | D17: =C17 -> 0.058721746 | E17: =D17 -> 0.058721746 | F17: =E17 -> 0.058721746 | G17: =F17 -> 0.058721746 | H17: =G17 -> 0.058721746 | I17: =H17 -> 0.058721746 | J17: =I17 -> 0.058721746 | L17: Stable
B18: Inventory as % of COGS | C18: 0.023950365 | D18: =C18 -> 0.023950365 | E18: =D18 -> 0.023950365 | F18: =E18 -> 0.023950365 | G18: =F18 -> 0.023950365 | H18: =G18 -> 0.023950365 | I18: =H18 -> 0.023950365 | J18: =I18 -> 0.023950365 | L18: Stable
B19: Goodwill + intangibles+other in $ | C19: =C53 -> 83.727 | D19: =C19 -> 83.727 | E19: =D19 -> 83.727 | F19: =E19 -> 83.727 | G19: =F19 -> 83.727 | H19: =G19 -> 83.727 | I19: =H19 -> 83.727 | J19: =I19 -> 83.727 | L19: Stable
B20: Other current assets as % of sales | C20: 0.11871482 | D20: =C20 -> 0.11871482 | E20: =D20 -> 0.11871482 | F20: =E20 -> 0.11871482 | G20: =F20 -> 0.11871482 | H20: =G20 -> 0.11871482 | I20: =H20 -> 0.11871482 | J20: =I20 -> 0.11871482 | L20: Stable
B21: AP as % of COGS | C21: 0.2494471 | D21: =C21 -> 0.2494471 | E21: =D21 -> 0.2494471 | F21: =E21 -> 0.2494471 | G21: =F21 -> 0.2494471 | H21: =G21 -> 0.2494471 | I21: =H21 -> 0.2494471 | J21: =I21 -> 0.2494471 | L21: Stable
B22: Accrued expenses as % of COGS | C22: 0.29091349 | D22: =C22 -> 0.29091349 | E22: =D22 -> 0.29091349 | F22: =E22 -> 0.29091349 | G22: =F22 -> 0.29091349 | H22: =G22 -> 0.29091349 | I22: =H22 -> 0.29091349 | J22: =I22 -> 0.29091349 | L22: Stable
B23: Non-current liabilities - no change | C23: =C60 -> 41.549 | D23: =C23 -> 41.549 | E23: =D23 -> 41.549 | F23: =E23 -> 41.549 | G23: =F23 -> 41.549 | H23: =G23 -> 41.549 | I23: =H23 -> 41.549 | J23: =I23 -> 41.549 | L23: Stable
B24: Other:
B25: Dividends in $ - increase of 5% per year | C25: 0.05 | D25: =C25 -> 0.05 | E25: =D25 -> 0.05 | F25: =E25 -> 0.05 | G25: =F25 -> 0.05 | H25: =G25 -> 0.05 | I25: =H25 -> 0.05 | J25: =I25 -> 0.05
B26: Share repurchases in $ - 80% of net income | C26: 0.8 | D26: 0.8 | E26: =D26 -> 0.8 | F26: =E26 -> 0.8 | G26: =F26 -> 0.8 | H26: =G26 -> 0.8 | I26: =H26 -> 0.8 | J26: =I26 -> 0.8
B27: Additional share repurchases/dividends to use foreign cash ($'B) | D27: 20 | E27: 20 | F27: 10 | G27: 10 | L27: Extra share repurchases
B28: CapEx as % of next year sales | C28: 0.03 | D28: 0.05 | E28: 0.07 | F28: =E28 -> 0.07 | G28: =F28 -> 0.07 | H28: =G28 -> 0.07 | I28: =H28 -> 0.07 | J28: =I28 -> 0.07 | L28: 3% is historical rate, just a bit gorwing because of potential data center needs
B29: Depreciation as % of current year CapEx | C29: 0.8 | D29: =C29 -> 0.8 | E29: =D29 -> 0.8 | F29: =E29 -> 0.8 | G29: =F29 -> 0.8 | H29: =G29 -> 0.8 | I29: =H29 -> 0.8 | J29: =I29 -> 0.8 | L29: Approximately the historical rate
B30: Growth rate - terminal | C30: 0.035
C32: Actual | D32: Forecast | E32: Forecast | F32: Forecast | G32: Forecast | H32: Forecast | I32: Forecast | J32: Forecast
B33: Income statement forecast | C33: =C6 -> 2025 | D33: =D6 -> 2026 | E33: =E6 -> 2027 | F33: =F6 -> 2028 | G33: =G6 -> 2029 | H33: =H6 -> 2030 | I33: =I6 -> 2031 | J33: =J6 -> 2032
B34: Net sales | C34: =IS!V4 -> 416.161 | D34: =C34*(1+D7) -> 487.18848 | E34: =D34*(1+E7) -> 560.26675 | F34: =E34*(1+F7) -> 672.3201 | G34: =F34*(1+G7) -> 773.16812 | H34: =G34*(1+H7) -> 850.48493 | I34: =H34*(1+I7) -> 893.00917 | J34: =I34*(1+J7) -> 928.72954 | L34: See the tab revenue forecast
B35: Cost of sales | C35: =IS!V5 -> -220.96 | D35: =-D34*D8 -> -243.59424 | E35: =-E34*E8 -> -268.92804 | F35: =-F34*F8 -> -309.26725 | G35: =-G34*G8 -> -347.92565 | H35: =-H34*H8 -> -382.71822 | I35: =-I34*I8 -> -401.85413 | J35: =-J34*J8 -> -417.92829
B36: Gross margin | C36: =SUM(C34:C35) -> 195.201 | D36: =SUM(D34:D35) -> 243.59424 | E36: =SUM(E34:E35) -> 291.33871 | F36: =SUM(F34:F35) -> 363.05285 | G36: =SUM(G34:G35) -> 425.24246 | H36: =SUM(H34:H35) -> 467.76671 | I36: =SUM(I34:I35) -> 491.15505 | J36: =SUM(J34:J35) -> 510.80125
B37: Total operating expenses | C37: =IS!V7 -> -62.1 | D37: =-D34*D9 -> -72.698798 | E37: =-E34*E9 -> -83.603618 | F37: =-F34*F9 -> -100.32434 | G37: =-G34*G9 -> -115.37299 | H37: =-H34*H9 -> -126.91029 | I37: =-I34*I9 -> -133.25581 | J37: =-J34*J9 -> -138.58604
B38: Operating income | C38: =SUM(C36:C37) -> 133.101 | D38: =SUM(D36:D37) -> 170.89544 | E38: =SUM(E36:E37) -> 207.73509 | F38: =SUM(F36:F37) -> 262.72851 | G38: =SUM(G36:G37) -> 309.86947 | H38: =SUM(H36:H37) -> 340.85642 | I38: =SUM(I36:I37) -> 357.89924 | J38: =SUM(J36:J37) -> 372.21521
B39: Interest income | D39: =D10*C48 -> 2.89458 | E39: =E10*D48 -> 2.7783193 | F39: =F10*E48 -> 2.2606706 | G39: =G10*F48 -> 2.4354506 | H39: =H10*G48 -> 2.8798354 | I39: =I10*H48 -> 3.9522594 | J39: =J10*I48 -> 5.0258611
B40: Interest expense | D40: =-D11*(C58+C59) -> -4.93285 | E40: =-E11*(D58+D59) -> -4.93285 | F40: =-F11*(E58+E59) -> -4.93285 | G40: =-G11*(F58+F59) -> -4.93285 | H40: =-H11*(G58+G59) -> -4.93285 | I40: =-I11*(H58+H59) -> -4.93285 | J40: =-J11*(I58+I59) -> -4.93285
B41: Income before provision for income taxes | C41: =IS!V12 -> 132.729 | D41: =SUM(D38:D40) -> 168.85717 | E41: =SUM(E38:E40) -> 205.58056 | F41: =SUM(F38:F40) -> 260.05633 | G41: =SUM(G38:G40) -> 307.37207 | H41: =SUM(H38:H40) -> 338.8034 | I41: =SUM(I38:I40) -> 356.91865 | J41: =SUM(J38:J40) -> 372.30822
B42: Provision for income taxes | C42: =IS!V13 -> -20.719 | D42: =-D41*D12 -> -33.771434 | E42: =-E41*E12 -> -41.116112 | F42: =-F41*F12 -> -52.011267 | G42: =-G41*G12 -> -61.474414 | H42: =-H41*H12 -> -67.760681 | I42: =-I41*I12 -> -71.38373 | J42: =-J41*J12 -> -74.461644
B43: Net income | C43: =SUM(C41:C42) -> 112.01 | D43: =SUM(D41:D42) -> 135.08574 | E43: =SUM(E41:E42) -> 164.46445 | F43: =SUM(F41:F42) -> 208.04507 | G43: =SUM(G41:G42) -> 245.89766 | H43: =SUM(H41:H42) -> 271.04272 | I43: =SUM(I41:I42) -> 285.53492 | J43: =SUM(J41:J42) -> 297.84658
C45: Actual | D45: Forecast | E45: Forecast | F45: Forecast | G45: Forecast | H45: Forecast | I45: Forecast | J45: Forecast
B46: Balance sheet forecast | C46: =C6 -> 2025 | D46: =D33 -> 2026 | E46: =E33 -> 2027 | F46: =F33 -> 2028 | G46: =G33 -> 2029 | H46: =H33 -> 2030 | I46: =I33 -> 2031 | J46: =J33 -> 2032
B47: Cash and cash equivalents | C47: =BS!V6 -> 35.934 | D47: =D14 -> 35.934 | E47: =D47 -> 35.934 | F47: =E47 -> 35.934 | G47: =F47 -> 35.934 | H47: =G47 -> 35.934 | I47: =H47 -> 35.934 | J47: =I47 -> 35.934
B48: Marketable securities - ST and LT | C48: =BS!V7+BS!V15 -> 96.486 | D48: =D63-D47-SUM(D49:D53) -> 69.457981 | E48: =E63-E47-SUM(E49:E53) -> 56.516765 | F48: =F63-F47-SUM(F49:F53) -> 60.886266 | G48: =G63-G47-SUM(G49:G53) -> 71.995885 | H48: =H63-H47-SUM(H49:H53) -> 98.806484 | I48: =I63-I47-SUM(I49:I53) -> 125.64653 | J48: =J63-J47-SUM(J49:J53) -> 153.56997 | L48: This is a plug
B49: Accounts receivable, less allowances | C49: =BS!V8 -> 39.777 | D49: =D17*D34 -> 28.608558 | E49: =E17*E34 -> 32.899842 | F49: =F17*F34 -> 39.47981 | G49: =G17*G34 -> 45.401781 | H49: =H17*H34 -> 49.94196 | I49: =I17*I34 -> 52.439057 | J49: =J17*J34 -> 54.53662
B50: Inventories | C50: =BS!V9 -> 5.718 | D50: =-D18*D35 -> 5.834171 | E50: =-E18*E35 -> 6.4409248 | F50: =-F18*F35 -> 7.4070635 | G50: =-G18*G35 -> 8.3329465 | H50: =-H18*H35 -> 9.1662411 | I50: =-I18*I35 -> 9.6245532 | J50: =-J18*J35 -> 10.009535
B51: Other current assets | C51: =BS!V14+BS!V11 -> 47.765 | D51: =D20*D34 -> 57.836495 | E51: =E20*E34 -> 66.511969 | F51: =F20*F34 -> 79.814363 | G51: =G20*G34 -> 91.786517 | H51: =H20*H34 -> 100.96517 | I51: =I20*I34 -> 106.01343 | J51: =J20*J34 -> 110.25396
B52: Property, plant and equipment, net | C52: =BS!V16 -> 49.834 | D52: =C52+D66-D67 -> 55.436668 | E52: =D52+E66-E67 -> 64.849149 | F52: =E52+F66-F67 -> 75.673503 | G52: =F52+G66-G67 -> 87.580291 | H52: =G52+H66-H67 -> 100.08242 | I52: =H52+I66-I67 -> 112.58455 | J52: =I52+J66-J67 -> 125.08668 | L52: Prior PPE + CapEx - Depreciation
B53: Goodwill + intangbles + other | C53: =BS!V19 -> 83.727 | D53: =D19 -> 83.727 | E53: =E19 -> 83.727 | F53: =F19 -> 83.727 | G53: =G19 -> 83.727 | H53: =H19 -> 83.727 | I53: =I19 -> 83.727 | J53: =J19 -> 83.727
B54: Total assets | C54: =SUM(C47:C53) -> 359.241 | D54: =SUM(D47:D53) -> 336.83487 | E54: =SUM(E47:E53) -> 346.87965 | F54: =SUM(F47:F53) -> 382.922 | G54: =SUM(G47:G53) -> 424.75842 | H54: =SUM(H47:H53) -> 478.62327 | I54: =SUM(I47:I53) -> 525.96911 | J54: =SUM(J47:J53) -> 573.11777
B56: Accounts payable | C56: =BS!V23 -> 69.86 | D56: =-D21*D35 -> 60.763875 | E56: =-E21*E35 -> 67.083318 | F56: =-F21*F35 -> 77.145816 | G56: =-G21*G35 -> 86.789043 | H56: =-H21*H35 -> 95.467947 | I56: =-I21*I35 -> 100.24134 | J56: =-J21*J35 -> 104.251
B57: Accrued expenses | C57: =BS!V24+BS!V26 -> 75.442 | D57: =-D22*D35 -> 70.86485 | E57: =-E22*E35 -> 78.234794 | F57: =-F22*F35 -> 89.970013 | G57: =-G22*G35 -> 101.21626 | H57: =-H22*H35 -> 111.33789 | I57: =-I22*I35 -> 116.90479 | J57: =-J22*J35 -> 121.58098
B58: ST debt | C58: =BS!V27+BS!V28 -> 20.329 | D58: =D15 -> 20.329 | E58: =E15 -> 20.329 | F58: =F15 -> 20.329 | G58: =G15 -> 20.329 | H58: =H15 -> 20.329 | I58: =I15 -> 20.329 | J58: =J15 -> 20.329
B59: Long-term debt | C59: =BS!V29 -> 78.328 | D59: =D16 -> 78.328 | E59: =E16 -> 78.328 | F59: =F16 -> 78.328 | G59: =G16 -> 78.328 | H59: =H16 -> 78.328 | I59: =I16 -> 78.328 | J59: =J16 -> 78.328
B60: Non-current liabilities | C60: =BS!V30 -> 41.549 | D60: =D23 -> 41.549 | E60: =E23 -> 41.549 | F60: =F23 -> 41.549 | G60: =G23 -> 41.549 | H60: =H23 -> 41.549 | I60: =I23 -> 41.549 | J60: =J23 -> 41.549
B61: Total liabilities | C61: =SUM(C56:C60) -> 285.508 | D61: =SUM(D56:D60) -> 271.83472 | E61: =SUM(E56:E60) -> 285.52411 | F61: =SUM(F56:F60) -> 307.32183 | G61: =SUM(G56:G60) -> 328.21131 | H61: =SUM(H56:H60) -> 347.01184 | I61: =SUM(I56:I60) -> 357.35213 | J61: =SUM(J56:J60) -> 366.03798
B62: Total shareholders' equity | C62: =BS!V33 -> 73.733 | D62: =C62+D43-D68-D69 -> 65.000147 | E62: =D62+E43-E68-E69 -> 61.355537 | F62: =E62+F43-F68-F69 -> 75.600176 | G62: =F62+G43-G68-G69 -> 96.547113 | H62: =G62+H43-H68-H69 -> 131.61143 | I62: =H62+I43-I68-I69 -> 168.61698 | J62: =I62+J43-J68-J69 -> 207.07979 | L62: Prior equity + NI - Dividends - buybacks
B63: Total liabilities and equity | C63: =SUM(C61:C62) -> 359.241 | D63: =D62+D61 -> 336.83487 | E63: =E62+E61 -> 346.87965 | F63: =F62+F61 -> 382.922 | G63: =G62+G61 -> 424.75842 | H63: =H62+H61 -> 478.62327 | I63: =I62+I61 -> 525.96911 | J63: =J62+J61 -> 573.11777
B65: Other
B66: CapEx | D66: =D28*E34 -> 28.013338 | E66: =E28*F34 -> 47.062407 | F66: =F28*G34 -> 54.121768 | G66: =G28*H34 -> 59.533945 | H66: =H28*I34 -> 62.510642 | I66: =H66 -> 62.510642 | J66: =I66 -> 62.510642
B67: Depreciation | D67: =D66*D29 -> 22.41067 | E67: =E66*E29 -> 37.649926 | F67: =F66*F29 -> 43.297414 | G67: =G66*G29 -> 47.627156 | H67: =H66*H29 -> 50.008514 | I67: =H67 -> 50.008514 | J67: =I67 -> 50.008514
B68: Dividends | C68: 15 | D68: =C68*(1+D25) -> 15.75 | E68: =D68*(1+E25) -> 16.5375 | F68: =E68*(1+F25) -> 17.364375 | G68: =F68*(1+G25) -> 18.232594 | H68: =G68*(1+H25) -> 19.144223 | I68: =H68*(1+I25) -> 20.101435 | J68: =I68*(1+J25) -> 21.106506
B69: Share repurchases | D69: =D26*D43+D27 -> 128.06859 | E69: =E26*E43+E27 -> 151.57156 | F69: =F26*F43+F27 -> 176.43605 | G69: =G26*G43+G27 -> 206.71813 | H69: =H26*H43+H27 -> 216.83418 | I69: =I26*I43+I27 -> 228.42793 | J69: =J26*J43+J27 -> 238.27726
D71: Forecast | E71: Forecast | F71: Forecast | G71: Forecast | H71: Forecast | I71: Forecast | J71: Forecast
B72: Free cash flow | D72: =D46 -> 2026 | E72: =E46 -> 2027 | F72: =F46 -> 2028 | G72: =G46 -> 2029 | H72: =H46 -> 2030 | I72: =I46 -> 2031 | J72: =J46 -> 2032
B73: EBIT * (1-tax rate) | D73: =D38*(1-D12) -> 136.71635 | E73: =E38*(1-E12) -> 166.18807 | F73: =F38*(1-F12) -> 210.18281 | G73: =G38*(1-G12) -> 247.89558 | H73: =H38*(1-H12) -> 272.68513 | I73: =I38*(1-I12) -> 286.31939 | J73: =J38*(1-J12) -> 297.77217
B74: Depreciation | D74: =D67 -> 22.41067 | E74: =E67 -> 37.649926 | F74: =F67 -> 43.297414 | G74: =G67 -> 47.627156 | H74: =H67 -> 50.008514 | I74: =I67 -> 50.008514 | J74: =J67 -> 50.008514
B75: CapEx | D75: =-D66 -> -28.013338 | E75: =-E66 -> -47.062407 | F75: =-F66 -> -54.121768 | G75: =-G66 -> -59.533945 | H75: =-H66 -> -62.510642 | I75: =-I66 -> -62.510642 | J75: =-J66 -> -62.510642
B76: WC calculation
B77: (Increase)/decrease in AR | D77: =C49-D49 -> 11.168442 | E77: =D49-E49 -> -4.2912837 | F77: =E49-F49 -> -6.5799683 | G77: =F49-G49 -> -5.9219715 | H77: =G49-H49 -> -4.5401781 | I77: =H49-I49 -> -2.497098 | J77: =I49-J49 -> -2.0975623
B78: (Increase)/decrease in Inventory | D78: =C50-D50 -> -0.11617103 | E78: =D50-E50 -> -0.60675379 | F78: =E50-F50 -> -0.96613872 | G78: =F50-G50 -> -0.92588294 | H78: =G50-H50 -> -0.83329465 | I78: =H50-I50 -> -0.45831206 | J78: =I50-J50 -> -0.38498213
B79: (Increase)/decrease in other current assets | D79: =C51-D51 -> -10.071495 | E79: =D51-E51 -> -8.6754742 | F79: =E51-F51 -> -13.302394 | G79: =F51-G51 -> -11.972154 | H79: =G51-H51 -> -9.1786517 | I79: =H51-I51 -> -5.0482584 | J79: =I51-J51 -> -4.2405371
B80: Increase/(decrease) in AP | D80: =D56-C56 -> -9.0961246 | E80: =E56-D56 -> 6.319443 | F80: =F56-E56 -> 10.062498 | G80: =G56-F56 -> 9.643227 | H80: =H56-G56 -> 8.6789043 | I80: =I56-H56 -> 4.7733974 | J80: =J56-I56 -> 4.0096538
B81: Increase/(decrease) in Accrued expenses | D81: =D57-C57 -> -4.5771504 | E81: =E57-D57 -> 7.3699444 | F81: =F57-E57 -> 11.735219 | G81: =G57-F57 -> 11.246252 | H81: =H57-G57 -> 10.121626 | I81: =I57-H57 -> 5.5668946 | J81: =J57-I57 -> 4.6761914
B82: Free Cash Flows | D82: =SUM(D73:D81) -> 118.42119 | E82: =SUM(E73:E81) -> 156.89147 | F82: =SUM(F73:F81) -> 200.30767 | G82: =SUM(G73:G81) -> 238.05826 | H82: =SUM(H73:H81) -> 264.43141 | I82: =SUM(I73:I81) -> 276.15389 | J82: =SUM(J73:J81) -> 287.2328
B83: Terminal Value | J83: =J82*(1+C30)/('cost of capital'!C22-'Valuation - new product'!C30) -> 6476.1126
B84: Total Free Cash Flow | D84: =SUM(D82:D83) -> 118.42119 | E84: =SUM(E82:E83) -> 156.89147 | F84: =SUM(F82:F83) -> 200.30767 | G84: =SUM(G82:G83) -> 238.05826 | H84: =SUM(H82:H83) -> 264.43141 | I84: =SUM(I82:I83) -> 276.15389 | J84: =SUM(J82:J83) -> 6763.3454
B86: PV of the Total Free Cash Flow | C86: =NPV('cost of capital'!C22,D84:J84) -> 4852.4908
B87: Add cash and MS | C87: =C47+C48 -> 132.42
B88: Subtract Debt | C88: =-(C59+C58) -> -98.657
B89: Apple market value | C89: =SUM(C86:C88) -> 4886.2538 | E89: `
B90: Number of shares in B | C90: ='cost of capital'!C12 -> 14.8
B91: Share price | C91: =C89/C90 -> 330.15228

Sheet Valuation - lower margins
B2: IS and BS forecast, Free Cash Flows and Apple valuation
B3: BASE - estimated value as of November 2025
B5: Assumptions | C5: Actual | D5: Forecast | E5: Forecast | F5: Forecast | G5: Forecast | H5: Forecast | I5: Forecast | J5: Forecast
B6: Income statement | C6: 2025 | D6: 2026 | E6: 2027 | F6: 2028 | G6: 2029 | H6: 2030 | I6: 2031 | J6: 2032
B7: Sales growth | D7: ='Revenue forecast'!D27 -> 0.17067308 | E7: 0.1 | F7: 0.05 | G7: 0.04 | H7: 0.03 | I7: 0.03 | J7: 0.03 | L7: Less demand, competitive pressure
B8: Cost of sales as % sales | C8: ='IS common size'!V6 -> 0.53094836 | D8: 0.51 | E8: 0.52 | F8: 0.55 | G8: 0.6 | H8: =G8 -> 0.6 | I8: =H8 -> 0.6 | J8: =I8 -> 0.6 | L8: Higher costs - maybe tariffs
B9: Ops expenses as % of sales | C9: ='IS common size'!V8 -> 0.14922109 | D9: =C9 -> 0.14922109 | E9: =D9 -> 0.14922109 | F9: =E9 -> 0.14922109 | G9: =F9 -> 0.14922109 | H9: =G9 -> 0.14922109 | I9: =H9 -> 0.14922109 | J9: =I9 -> 0.14922109 | L9: Stable
B10: Interest income | C10: 0.03 | D10: =C10 -> 0.03 | E10: 0.04 | F10: =E10 -> 0.04 | G10: =F10 -> 0.04 | H10: =G10 -> 0.04 | I10: =H10 -> 0.04 | J10: =I10 -> 0.04 | L10: Increasing at the interest rates increase
B11: Interest expense | C11: 0.05 | D11: =C11 -> 0.05 | E11: 0.05 | F11: =E11 -> 0.05 | G11: =F11 -> 0.05 | H11: =G11 -> 0.05 | I11: =H11 -> 0.05 | J11: =I11 -> 0.05 | L11: Increasing at the interest rates increase
B12: Tax rate as % of pretax income (going down) | C12: 0.2 | D12: =C12 -> 0.2 | E12: =D12 -> 0.2 | F12: =E12 -> 0.2 | G12: =F12 -> 0.2 | H12: =G12 -> 0.2 | I12: =H12 -> 0.2 | J12: =I12 -> 0.2 | L12: Based on the new tax rules
B13: Balance sheet
B14: Cash - stable in $ | C14: =C47 -> 35.934 | D14: =C14 -> 35.934 | E14: =D14 -> 35.934 | F14: =E14 -> 35.934 | G14: =F14 -> 35.934 | H14: =G14 -> 35.934 | I14: =H14 -> 35.934 | J14: =I14 -> 35.934 | L14: Stable
B15: ST debt - stable | C15: =C58 -> 20.329 | D15: =C15 -> 20.329 | E15: =D15 -> 20.329 | F15: =E15 -> 20.329 | G15: =F15 -> 20.329 | H15: =G15 -> 20.329 | I15: =H15 -> 20.329 | J15: =I15 -> 20.329 | L15: Stable
B16: LT debt - stable | C16: =C59 -> 78.328 | D16: =C16 -> 78.328 | E16: =D16 -> 78.328 | F16: =E16 -> 78.328 | G16: =F16 -> 78.328 | H16: =G16 -> 78.328 | I16: =H16 -> 78.328 | J16: =I16 -> 78.328 | L16: Stable
B17: AR as % of sales | C17: 0.058721746 | D17: =C17 -> 0.058721746 | E17: =D17 -> 0.058721746 | F17: =E17 -> 0.058721746 | G17: =F17 -> 0.058721746 | H17: =G17 -> 0.058721746 | I17: =H17 -> 0.058721746 | J17: =I17 -> 0.058721746 | L17: Stable
B18: Inventory as % of COGS | C18: 0.023950365 | D18: =C18 -> 0.023950365 | E18: =D18 -> 0.023950365 | F18: =E18 -> 0.023950365 | G18: =F18 -> 0.023950365 | H18: =G18 -> 0.023950365 | I18: =H18 -> 0.023950365 | J18: =I18 -> 0.023950365 | L18: Stable
B19: Goodwill + intangibles+other in $ | C19: =C53 -> 83.727 | D19: =C19 -> 83.727 | E19: =D19 -> 83.727 | F19: =E19 -> 83.727 | G19: =F19 -> 83.727 | H19: =G19 -> 83.727 | I19: =H19 -> 83.727 | J19: =I19 -> 83.727 | L19: Stable
B20: Other current assets as % of sales | C20: 0.11871482 | D20: =C20 -> 0.11871482 | E20: =D20 -> 0.11871482 | F20: =E20 -> 0.11871482 | G20: =F20 -> 0.11871482 | H20: =G20 -> 0.11871482 | I20: =H20 -> 0.11871482 | J20: =I20 -> 0.11871482 | L20: Stable
B21: AP as % of COGS | C21: 0.2494471 | D21: =C21 -> 0.2494471 | E21: =D21 -> 0.2494471 | F21: =E21 -> 0.2494471 | G21: =F21 -> 0.2494471 | H21: =G21 -> 0.2494471 | I21: =H21 -> 0.2494471 | J21: =I21 -> 0.2494471 | L21: Stable
B22: Accrued expenses as % of COGS | C22: 0.29091349 | D22: =C22 -> 0.29091349 | E22: =D22 -> 0.29091349 | F22: =E22 -> 0.29091349 | G22: =F22 -> 0.29091349 | H22: =G22 -> 0.29091349 | I22: =H22 -> 0.29091349 | J22: =I22 -> 0.29091349 | L22: Stable
B23: Non-current liabilities - no change | C23: =C60 -> 41.549 | D23: =C23 -> 41.549 | E23: =D23 -> 41.549 | F23: =E23 -> 41.549 | G23: =F23 -> 41.549 | H23: =G23 -> 41.549 | I23: =H23 -> 41.549 | J23: =I23 -> 41.549 | L23: Stable
B24: Other:
B25: Dividends in $ - increase of 5% per year | C25: 0.05 | D25: =C25 -> 0.05 | E25: =D25 -> 0.05 | F25: =E25 -> 0.05 | G25: =F25 -> 0.05 | H25: =G25 -> 0.05 | I25: =H25 -> 0.05 | J25: =I25 -> 0.05
B26: Share repurchases in $ - 80% of net income | C26: 0.8 | D26: 0.8 | E26: =D26 -> 0.8 | F26: =E26 -> 0.8 | G26: =F26 -> 0.8 | H26: =G26 -> 0.8 | I26: =H26 -> 0.8 | J26: =I26 -> 0.8
B27: Additional share repurchases/dividends to use foreign cash ($'B) | D27: 20 | E27: 20 | F27: 10 | G27: 10 | L27: Extra share repurchases
B28: CapEx as % of next year sales | C28: 0.03 | D28: 0.05 | E28: 0.07 | F28: =E28 -> 0.07 | G28: =F28 -> 0.07 | H28: =G28 -> 0.07 | I28: =H28 -> 0.07 | J28: =I28 -> 0.07 | L28: 3% is historical rate, just a bit gorwing because of potential data center needs
B29: Depreciation as % of current year CapEx | C29: 0.8 | D29: =C29 -> 0.8 | E29: =D29 -> 0.8 | F29: =E29 -> 0.8 | G29: =F29 -> 0.8 | H29: =G29 -> 0.8 | I29: =H29 -> 0.8 | J29: =I29 -> 0.8 | L29: Approximately the historical rate
B30: Growth rate - terminal | C30: 0.035
C32: Actual | D32: Forecast | E32: Forecast | F32: Forecast | G32: Forecast | H32: Forecast | I32: Forecast | J32: Forecast
B33: Income statement forecast | C33: =C6 -> 2025 | D33: =D6 -> 2026 | E33: =E6 -> 2027 | F33: =F6 -> 2028 | G33: =G6 -> 2029 | H33: =H6 -> 2030 | I33: =I6 -> 2031 | J33: =J6 -> 2032
B34: Net sales | C34: =IS!V4 -> 416.161 | D34: =C34*(1+D7) -> 487.18848 | E34: =D34*(1+E7) -> 535.90733 | F34: =E34*(1+F7) -> 562.70269 | G34: =F34*(1+G7) -> 585.2108 | H34: =G34*(1+H7) -> 602.76712 | I34: =H34*(1+I7) -> 620.85014 | J34: =I34*(1+J7) -> 639.47564 | L34: See the tab revenue forecast
B35: Cost of sales | C35: =IS!V5 -> -220.96 | D35: =-D34*D8 -> -248.46612 | E35: =-E34*E8 -> -278.67181 | F35: =-F34*F8 -> -309.48648 | G35: =-G34*G8 -> -351.12648 | H35: =-H34*H8 -> -361.66027 | I35: =-I34*I8 -> -372.51008 | J35: =-J34*J8 -> -383.68539
B36: Gross margin | C36: =SUM(C34:C35) -> 195.201 | D36: =SUM(D34:D35) -> 238.72235 | E36: =SUM(E34:E35) -> 257.23552 | F36: =SUM(F34:F35) -> 253.21621 | G36: =SUM(G34:G35) -> 234.08432 | H36: =SUM(H34:H35) -> 241.10685 | I36: =SUM(I34:I35) -> 248.34006 | J36: =SUM(J34:J35) -> 255.79026
B37: Total operating expenses | C37: =IS!V7 -> -62.1 | D37: =-D34*D9 -> -72.698798 | E37: =-E34*E9 -> -79.968678 | F37: =-F34*F9 -> -83.967112 | G37: =-G34*G9 -> -87.325796 | H37: =-H34*H9 -> -89.94557 | I37: =-I34*I9 -> -92.643937 | J37: =-J34*J9 -> -95.423255
B38: Operating income | C38: =SUM(C36:C37) -> 133.101 | D38: =SUM(D36:D37) -> 166.02356 | E38: =SUM(E36:E37) -> 177.26684 | F38: =SUM(F36:F37) -> 169.2491 | G38: =SUM(G36:G37) -> 146.75852 | H38: =SUM(H36:H37) -> 151.16128 | I38: =SUM(I36:I37) -> 155.69612 | J38: =SUM(J36:J37) -> 160.367
B39: Interest income | D39: =D10*C48 -> 2.89458 | E39: =E10*D48 -> 2.8575186 | F39: =F10*E48 -> 2.4802915 | G39: =G10*F48 -> 2.5718377 | H39: =H10*G48 -> 2.7295108 | I39: =I10*H48 -> 2.6623816 | J39: =J10*I48 -> 2.5883468
B40: Interest expense | D40: =-D11*(C58+C59) -> -4.93285 | E40: =-E11*(D58+D59) -> -4.93285 | F40: =-F11*(E58+E59) -> -4.93285 | G40: =-G11*(F58+F59) -> -4.93285 | H40: =-H11*(G58+G59) -> -4.93285 | I40: =-I11*(H58+H59) -> -4.93285 | J40: =-J11*(I58+I59) -> -4.93285
B41: Income before provision for income taxes | C41: =IS!V12 -> 132.729 | D41: =SUM(D38:D40) -> 163.98529 | E41: =SUM(E38:E40) -> 175.19151 | F41: =SUM(F38:F40) -> 166.79654 | G41: =SUM(G38:G40) -> 144.39751 | H41: =SUM(H38:H40) -> 148.95794 | I41: =SUM(I38:I40) -> 153.42565 | J41: =SUM(J38:J40) -> 158.0225
B42: Provision for income taxes | C42: =IS!V13 -> -20.719 | D42: =-D41*D12 -> -32.797057 | E42: =-E41*E12 -> -35.038301 | F42: =-F41*F12 -> -33.359308 | G42: =-G41*G12 -> -28.879502 | H42: =-H41*H12 -> -29.791588 | I42: =-I41*I12 -> -30.68513 | J42: =-J41*J12 -> -31.6045
B43: Net income | C43: =SUM(C41:C42) -> 112.01 | D43: =SUM(D41:D42) -> 131.18823 | E43: =SUM(E41:E42) -> 140.15321 | F43: =SUM(F41:F42) -> 133.43723 | G43: =SUM(G41:G42) -> 115.51801 | H43: =SUM(H41:H42) -> 119.16635 | I43: =SUM(I41:I42) -> 122.74052 | J43: =SUM(J41:J42) -> 126.418
C45: Actual | D45: Forecast | E45: Forecast | F45: Forecast | G45: Forecast | H45: Forecast | I45: Forecast | J45: Forecast
B46: Balance sheet forecast | C46: =C6 -> 2025 | D46: =D33 -> 2026 | E46: =E33 -> 2027 | F46: =F33 -> 2028 | G46: =G33 -> 2029 | H46: =H33 -> 2030 | I46: =I33 -> 2031 | J46: =J33 -> 2032
B47: Cash and cash equivalents | C47: =BS!V6 -> 35.934 | D47: =D14 -> 35.934 | E47: =D47 -> 35.934 | F47: =E47 -> 35.934 | G47: =F47 -> 35.934 | H47: =G47 -> 35.934 | I47: =H47 -> 35.934 | J47: =I47 -> 35.934
B48: Marketable securities - ST and LT | C48: =BS!V7+BS!V15 -> 96.486 | D48: =D63-D47-SUM(D49:D53) -> 71.437965 | E48: =E63-E47-SUM(E49:E53) -> 62.007288 | F48: =F63-F47-SUM(F49:F53) -> 64.295942 | G48: =G63-G47-SUM(G49:G53) -> 68.23777 | H48: =H63-H47-SUM(H49:H53) -> 66.55954 | I48: =I63-I47-SUM(I49:I53) -> 64.708671 | J48: =J63-J47-SUM(J49:J53) -> 62.660057 | L48: This is a plug
B49: Accounts receivable, less allowances | C49: =BS!V8 -> 39.777 | D49: =D17*D34 -> 28.608558 | E49: =E17*E34 -> 31.469414 | F49: =F17*F34 -> 33.042884 | G49: =G17*G34 -> 34.3646 | H49: =H17*H34 -> 35.395538 | I49: =I17*I34 -> 36.457404 | J49: =J17*J34 -> 37.551126
B50: Inventories | C50: =BS!V9 -> 5.718 | D50: =-D18*D35 -> 5.9508544 | E50: =-E18*E35 -> 6.6742917 | F50: =-F18*F35 -> 7.4123143 | G50: =-G18*G35 -> 8.4096075 | H50: =-H18*H35 -> 8.6618957 | I50: =-I18*I35 -> 8.9217526 | J50: =-J18*J35 -> 9.1894052
B51: Other current assets | C51: =BS!V14+BS!V11 -> 47.765 | D51: =D20*D34 -> 57.836495 | E51: =E20*E34 -> 63.620144 | F51: =F20*F34 -> 66.801151 | G51: =G20*G34 -> 69.473197 | H51: =H20*H34 -> 71.557393 | I51: =I20*I34 -> 73.704115 | J51: =J20*J34 -> 75.915239
B52: Property, plant and equipment, net | C52: =BS!V16 -> 49.834 | D52: =C52+D66-D67 -> 55.193073 | E52: =D52+E66-E67 -> 63.070911 | F52: =E52+F66-F67 -> 71.263862 | G52: =F52+G66-G67 -> 79.702602 | H52: =G52+H66-H67 -> 88.394504 | I52: =H52+I66-I67 -> 97.086406 | J52: =I52+J66-J67 -> 105.77831 | L52: Prior PPE + CapEx - Depreciation
B53: Goodwill + intangbles + other | C53: =BS!V19 -> 83.727 | D53: =D19 -> 83.727 | E53: =E19 -> 83.727 | F53: =F19 -> 83.727 | G53: =G19 -> 83.727 | H53: =H19 -> 83.727 | I53: =I19 -> 83.727 | J53: =J19 -> 83.727
B54: Total assets | C54: =SUM(C47:C53) -> 359.241 | D54: =SUM(D47:D53) -> 338.68795 | E54: =SUM(E47:E53) -> 346.50305 | F54: =SUM(F47:F53) -> 362.47715 | G54: =SUM(G47:G53) -> 379.84878 | H54: =SUM(H47:H53) -> 390.22987 | I54: =SUM(I47:I53) -> 400.53935 | J54: =SUM(J47:J53) -> 410.75513
B56: Accounts payable | C56: =BS!V23 -> 69.86 | D56: =-D21*D35 -> 61.979153 | E56: =-E21*E35 -> 69.513873 | F56: =-F21*F35 -> 77.200504 | G56: =-G21*G35 -> 87.58748 | H56: =-H21*H35 -> 90.215105 | I56: =-I21*I35 -> 92.921558 | J56: =-J21*J35 -> 95.709205
B57: Accrued expenses | C57: =BS!V24+BS!V26 -> 75.442 | D57: =-D22*D35 -> 72.282147 | E57: =-E22*E35 -> 81.069388 | F57: =-F22*F35 -> 90.033791 | G57: =-G22*G35 -> 102.14743 | H57: =-H22*H35 -> 105.21185 | I57: =-I22*I35 -> 108.36821 | J57: =-J22*J35 -> 111.61925
B58: ST debt | C58: =BS!V27+BS!V28 -> 20.329 | D58: =D15 -> 20.329 | E58: =E15 -> 20.329 | F58: =F15 -> 20.329 | G58: =G15 -> 20.329 | H58: =H15 -> 20.329 | I58: =I15 -> 20.329 | J58: =J15 -> 20.329
B59: Long-term debt | C59: =BS!V29 -> 78.328 | D59: =D16 -> 78.328 | E59: =E16 -> 78.328 | F59: =F16 -> 78.328 | G59: =G16 -> 78.328 | H59: =H16 -> 78.328 | I59: =I16 -> 78.328 | J59: =J16 -> 78.328
B60: Non-current liabilities | C60: =BS!V30 -> 41.549 | D60: =D23 -> 41.549 | E60: =E23 -> 41.549 | F60: =F23 -> 41.549 | G60: =G23 -> 41.549 | H60: =H23 -> 41.549 | I60: =I23 -> 41.549 | J60: =J23 -> 41.549
B61: Total liabilities | C61: =SUM(C56:C60) -> 285.508 | D61: =SUM(D56:D60) -> 274.4673 | E61: =SUM(E56:E60) -> 290.78926 | F61: =SUM(F56:F60) -> 307.4403 | G61: =SUM(G56:G60) -> 329.94091 | H61: =SUM(H56:H60) -> 335.63296 | I61: =SUM(I56:I60) -> 341.49577 | J61: =SUM(J56:J60) -> 347.53446
B62: Total shareholders' equity | C62: =BS!V33 -> 73.733 | D62: =C62+D43-D68-D69 -> 64.220646 | E62: =D62+E43-E68-E69 -> 55.713787 | F62: =E62+F43-F68-F69 -> 55.036859 | G62: =F62+G43-G68-G69 -> 49.907867 | H62: =G62+H43-H68-H69 -> 54.596914 | I62: =H62+I43-I68-I69 -> 59.043583 | J62: =I62+J43-J68-J69 -> 63.220676 | L62: Prior equity + NI - Dividends - buybacks
B63: Total liabilities and equity | C63: =SUM(C61:C62) -> 359.241 | D63: =D62+D61 -> 338.68795 | E63: =E62+E61 -> 346.50305 | F63: =F62+F61 -> 362.47715 | G63: =G62+G61 -> 379.84878 | H63: =H62+H61 -> 390.22987 | I63: =I62+I61 -> 400.53935 | J63: =J62+J61 -> 410.75513
B65: Other
B66: CapEx | D66: =D28*E34 -> 26.795366 | E66: =E28*F34 -> 39.389188 | F66: =F28*G34 -> 40.964756 | G66: =G28*H34 -> 42.193699 | H66: =H28*I34 -> 43.45951 | I66: =H66 -> 43.45951 | J66: =I66 -> 43.45951
B67: Depreciation | D67: =D66*D29 -> 21.436293 | E67: =E66*E29 -> 31.511351 | F67: =F66*F29 -> 32.771805 | G67: =G66*G29 -> 33.754959 | H67: =H66*H29 -> 34.767608 | I67: =H67 -> 34.767608 | J67: =I67 -> 34.767608
B68: Dividends | C68: 15 | D68: =C68*(1+D25) -> 15.75 | E68: =D68*(1+E25) -> 16.5375 | F68: =E68*(1+F25) -> 17.364375 | G68: =F68*(1+G25) -> 18.232594 | H68: =G68*(1+H25) -> 19.144223 | I68: =H68*(1+I25) -> 20.101435 | J68: =I68*(1+J25) -> 21.106506
B69: Share repurchases | D69: =D26*D43+D27 -> 124.95058 | E69: =E26*E43+E27 -> 132.12256 | F69: =F26*F43+F27 -> 116.74979 | G69: =G26*G43+G27 -> 102.41441 | H69: =H26*H43+H27 -> 95.333082 | I69: =I26*I43+I27 -> 98.192416 | J69: =J26*J43+J27 -> 101.1344
D71: Forecast | E71: Forecast | F71: Forecast | G71: Forecast | H71: Forecast | I71: Forecast | J71: Forecast
B72: Free cash flow | D72: =D46 -> 2026 | E72: =E46 -> 2027 | F72: =F46 -> 2028 | G72: =G46 -> 2029 | H72: =H46 -> 2030 | I72: =I46 -> 2031 | J72: =J46 -> 2032
B73: EBIT * (1-tax rate) | D73: =D38*(1-D12) -> 132.81885 | E73: =E38*(1-E12) -> 141.81347 | F73: =F38*(1-F12) -> 135.39928 | G73: =G38*(1-G12) -> 117.40682 | H73: =H38*(1-H12) -> 120.92902 | I73: =I38*(1-I12) -> 124.55689 | J73: =J38*(1-J12) -> 128.2936
B74: Depreciation | D74: =D67 -> 21.436293 | E74: =E67 -> 31.511351 | F74: =F67 -> 32.771805 | G74: =G67 -> 33.754959 | H74: =H67 -> 34.767608 | I74: =I67 -> 34.767608 | J74: =J67 -> 34.767608
B75: CapEx | D75: =-D66 -> -26.795366 | E75: =-E66 -> -39.389188 | F75: =-F66 -> -40.964756 | G75: =-G66 -> -42.193699 | H75: =-H66 -> -43.45951 | I75: =-I66 -> -43.45951 | J75: =-J66 -> -43.45951
B76: WC calculation
B77: (Increase)/decrease in AR | D77: =C49-D49 -> 11.168442 | E77: =D49-E49 -> -2.8608558 | F77: =E49-F49 -> -1.5734707 | G77: =F49-G49 -> -1.3217154 | H77: =G49-H49 -> -1.030938 | I77: =H49-I49 -> -1.0618661 | J77: =I49-J49 -> -1.0937221
B78: (Increase)/decrease in Inventory | D78: =C50-D50 -> -0.23285445 | E78: =D50-E50 -> -0.72343721 | F78: =E50-F50 -> -0.73802264 | G78: =F50-G50 -> -0.9972932 | H78: =G50-H50 -> -0.25228822 | I78: =H50-I50 -> -0.25985687 | J78: =I50-J50 -> -0.26765258
B79: (Increase)/decrease in other current assets | D79: =C51-D51 -> -10.071495 | E79: =D51-E51 -> -5.7836495 | F79: =E51-F51 -> -3.1810072 | G79: =F51-G51 -> -2.6720461 | H79: =G51-H51 -> -2.0841959 | I79: =H51-I51 -> -2.1467218 | J79: =I51-J51 -> -2.2111235
B80: Increase/(decrease) in AP | D80: =D56-C56 -> -7.8808471 | E80: =E56-D56 -> 7.5347205 | F80: =F56-E56 -> 7.6866302 | G80: =G56-F56 -> 10.386977 | H80: =H56-G56 -> 2.6276244 | I80: =I56-H56 -> 2.7064531 | J80: =J56-I56 -> 2.7876467
B81: Increase/(decrease) in Accrued expenses | D81: =D57-C57 -> -3.1598534 | E81: =E57-D57 -> 8.7872414 | F81: =F57-E57 -> 8.9644035 | G81: =G57-F57 -> 12.113637 | H81: =H57-G57 -> 3.0644229 | I81: =I57-H57 -> 3.1563556 | J81: =J57-I57 -> 3.2510462
B82: Free Cash Flows | D82: =SUM(D73:D81) -> 117.28316 | E82: =SUM(E73:E81) -> 140.88965 | F82: =SUM(F73:F81) -> 138.36486 | G82: =SUM(G73:G81) -> 126.47764 | H82: =SUM(H73:H81) -> 114.56175 | I82: =SUM(I73:I81) -> 118.25936 | J82: =SUM(J73:J81) -> 122.06789
B83: Terminal Value | J83: =J82*(1+C30)/('cost of capital'!C22-'Valuation - lower margins'!C30) -> 2752.2115
B84: Total Free Cash Flow | D84: =SUM(D82:D83) -> 117.28316 | E84: =SUM(E82:E83) -> 140.88965 | F84: =SUM(F82:F83) -> 138.36486 | G84: =SUM(G82:G83) -> 126.47764 | H84: =SUM(H82:H83) -> 114.56175 | I84: =SUM(I82:I83) -> 118.25936 | J84: =SUM(J82:J83) -> 2874.2794
B86: PV of the Total Free Cash Flow | C86: =NPV('cost of capital'!C22,D84:J84) -> 2250.4119
B87: Add cash and MS | C87: =C47+C48 -> 132.42
B88: Subtract Debt | C88: =-(C59+C58) -> -98.657
B89: Apple market value | C89: =SUM(C86:C88) -> 2284.1749 | E89: `
B90: Number of shares in B | C90: ='cost of capital'!C12 -> 14.8
B91: Share price | C91: =C89/C90 -> 154.33614

Sheet Valuation - base - 2026
B2: IS and BS forecast, Free Cash Flows and Apple valuation
B3: BASE - estimated value as of September 2025
B5: Assumptions | C5: ='Valuation - base'!C5 -> Actual | D5: ='Valuation - base'!D5 -> Forecast | E5: ='Valuation - base'!E5 -> Forecast | F5: ='Valuation - base'!F5 -> Forecast | G5: ='Valuation - base'!G5 -> Forecast | H5: ='Valuation - base'!H5 -> Forecast | I5: ='Valuation - base'!I5 -> Forecast | J5: ='Valuation - base'!J5 -> Forecast
B6: Income statement | C6: ='Valuation - base'!C6 -> 2025 | D6: ='Valuation - base'!D6 -> 2026 | E6: ='Valuation - base'!E6 -> 2027 | F6: ='Valuation - base'!F6 -> 2028 | G6: ='Valuation - base'!G6 -> 2029 | H6: ='Valuation - base'!H6 -> 2030 | I6: ='Valuation - base'!I6 -> 2031 | J6: ='Valuation - base'!J6 -> 2032
B7: Sales growth | D7: ='Valuation - base'!D7 -> 0.17067308 | E7: ='Valuation - base'!E7 -> 0.11967146 | F7: ='Valuation - base'!F7 -> 0.07918684 | G7: ='Valuation - base'!G7 -> 0.07 | H7: ='Valuation - base'!H7 -> 0.06 | I7: ='Valuation - base'!I7 -> 0.05 | J7: ='Valuation - base'!J7 -> 0.04 | L7: See the tab revenue forecast
B8: Cost of sales as % sales | C8: ='Valuation - base'!C8 -> 0.53094836 | D8: ='Valuation - base'!D8 -> 0.51 | E8: ='Valuation - base'!E8 -> 0.49 | F8: ='Valuation - base'!F8 -> 0.47 | G8: ='Valuation - base'!G8 -> 0.47 | H8: ='Valuation - base'!H8 -> 0.47 | I8: ='Valuation - base'!I8 -> 0.47 | J8: ='Valuation - base'!J8 -> 0.47 | L8: Going down sligthly as a result of higher % of services as % of sales
B9: Ops expenses as % of sales | C9: ='Valuation - base'!C9 -> 0.14922109 | D9: ='Valuation - base'!D9 -> 0.14922109 | E9: ='Valuation - base'!E9 -> 0.14922109 | F9: ='Valuation - base'!F9 -> 0.14922109 | G9: ='Valuation - base'!G9 -> 0.14922109 | H9: ='Valuation - base'!H9 -> 0.14922109 | I9: ='Valuation - base'!I9 -> 0.14922109 | J9: ='Valuation - base'!J9 -> 0.14922109 | L9: Stable
B10: Interest income | C10: ='Valuation - base'!C10 -> 0.03 | D10: ='Valuation - base'!D10 -> 0.03 | E10: ='Valuation - base'!E10 -> 0.04 | F10: ='Valuation - base'!F10 -> 0.04 | G10: ='Valuation - base'!G10 -> 0.04 | H10: ='Valuation - base'!H10 -> 0.04 | I10: ='Valuation - base'!I10 -> 0.04 | J10: ='Valuation - base'!J10 -> 0.04 | L10: Increasing at the interest rates increase
B11: Interest expense | C11: ='Valuation - base'!C11 -> 0.05 | D11: ='Valuation - base'!D11 -> 0.05 | E11: ='Valuation - base'!E11 -> 0.05 | F11: ='Valuation - base'!F11 -> 0.05 | G11: ='Valuation - base'!G11 -> 0.05 | H11: ='Valuation - base'!H11 -> 0.05 | I11: ='Valuation - base'!I11 -> 0.05 | J11: ='Valuation - base'!J11 -> 0.05 | L11: Increasing at the interest rates increase
B12: Tax rate as % of pretax income (going down) | C12: ='Valuation - base'!C12 -> 0.2 | D12: ='Valuation - base'!D12 -> 0.2 | E12: ='Valuation - base'!E12 -> 0.2 | F12: ='Valuation - base'!F12 -> 0.2 | G12: ='Valuation - base'!G12 -> 0.2 | H12: ='Valuation - base'!H12 -> 0.2 | I12: ='Valuation - base'!I12 -> 0.2 | J12: ='Valuation - base'!J12 -> 0.2 | L12: Based on the new tax rules
B13: Balance sheet
B14: Cash - stable in $ | C14: ='Valuation - base'!C14 -> 35.934 | D14: ='Valuation - base'!D14 -> 35.934 | E14: ='Valuation - base'!E14 -> 35.934 | F14: ='Valuation - base'!F14 -> 35.934 | G14: ='Valuation - base'!G14 -> 35.934 | H14: ='Valuation - base'!H14 -> 35.934 | I14: ='Valuation - base'!I14 -> 35.934 | J14: ='Valuation - base'!J14 -> 35.934 | L14: Stable
B15: ST debt - stable | C15: ='Valuation - base'!C15 -> 20.329 | D15: ='Valuation - base'!D15 -> 20.329 | E15: ='Valuation - base'!E15 -> 20.329 | F15: ='Valuation - base'!F15 -> 20.329 | G15: ='Valuation - base'!G15 -> 20.329 | H15: ='Valuation - base'!H15 -> 20.329 | I15: ='Valuation - base'!I15 -> 20.329 | J15: ='Valuation - base'!J15 -> 20.329 | L15: Stable
B16: LT debt - stable | C16: ='Valuation - base'!C16 -> 78.328 | D16: ='Valuation - base'!D16 -> 78.328 | E16: ='Valuation - base'!E16 -> 78.328 | F16: ='Valuation - base'!F16 -> 78.328 | G16: ='Valuation - base'!G16 -> 78.328 | H16: ='Valuation - base'!H16 -> 78.328 | I16: ='Valuation - base'!I16 -> 78.328 | J16: ='Valuation - base'!J16 -> 78.328 | L16: Stable
B17: AR as % of sales | C17: ='Valuation - base'!C17 -> 0.058721746 | D17: ='Valuation - base'!D17 -> 0.058721746 | E17: ='Valuation - base'!E17 -> 0.058721746 | F17: ='Valuation - base'!F17 -> 0.058721746 | G17: ='Valuation - base'!G17 -> 0.058721746 | H17: ='Valuation - base'!H17 -> 0.058721746 | I17: ='Valuation - base'!I17 -> 0.058721746 | J17: ='Valuation - base'!J17 -> 0.058721746 | L17: Stable
B18: Inventory as % of COGS | C18: ='Valuation - base'!C18 -> 0.023950365 | D18: ='Valuation - base'!D18 -> 0.023950365 | E18: ='Valuation - base'!E18 -> 0.023950365 | F18: ='Valuation - base'!F18 -> 0.023950365 | G18: ='Valuation - base'!G18 -> 0.023950365 | H18: ='Valuation - base'!H18 -> 0.023950365 | I18: ='Valuation - base'!I18 -> 0.023950365 | J18: ='Valuation - base'!J18 -> 0.023950365 | L18: Stable
B19: Goodwill + intangibles+other in $ | C19: ='Valuation - base'!C19 -> 83.727 | D19: ='Valuation - base'!D19 -> 83.727 | E19: ='Valuation - base'!E19 -> 83.727 | F19: ='Valuation - base'!F19 -> 83.727 | G19: ='Valuation - base'!G19 -> 83.727 | H19: ='Valuation - base'!H19 -> 83.727 | I19: ='Valuation - base'!I19 -> 83.727 | J19: ='Valuation - base'!J19 -> 83.727 | L19: Stable
B20: Other current assets as % of sales | C20: ='Valuation - base'!C20 -> 0.11871482 | D20: ='Valuation - base'!D20 -> 0.11871482 | E20: ='Valuation - base'!E20 -> 0.11871482 | F20: ='Valuation - base'!F20 -> 0.11871482 | G20: ='Valuation - base'!G20 -> 0.11871482 | H20: ='Valuation - base'!H20 -> 0.11871482 | I20: ='Valuation - base'!I20 -> 0.11871482 | J20: ='Valuation - base'!J20 -> 0.11871482 | L20: Stable
B21: AP as % of COGS | C21: ='Valuation - base'!C21 -> 0.2494471 | D21: ='Valuation - base'!D21 -> 0.2494471 | E21: ='Valuation - base'!E21 -> 0.2494471 | F21: ='Valuation - base'!F21 -> 0.2494471 | G21: ='Valuation - base'!G21 -> 0.2494471 | H21: ='Valuation - base'!H21 -> 0.2494471 | I21: ='Valuation - base'!I21 -> 0.2494471 | J21: ='Valuation - base'!J21 -> 0.2494471 | L21: Stable
B22: Accrued expenses as % of COGS | C22: ='Valuation - base'!C22 -> 0.29091349 | D22: ='Valuation - base'!D22 -> 0.29091349 | E22: ='Valuation - base'!E22 -> 0.29091349 | F22: ='Valuation - base'!F22 -> 0.29091349 | G22: ='Valuation - base'!G22 -> 0.29091349 | H22: ='Valuation - base'!H22 -> 0.29091349 | I22: ='Valuation - base'!I22 -> 0.29091349 | J22: ='Valuation - base'!J22 -> 0.29091349 | L22: Stable
B23: Non-current liabilities - no change | C23: ='Valuation - base'!C23 -> 41.549 | D23: ='Valuation - base'!D23 -> 41.549 | E23: ='Valuation - base'!E23 -> 41.549 | F23: ='Valuation - base'!F23 -> 41.549 | G23: ='Valuation - base'!G23 -> 41.549 | H23: ='Valuation - base'!H23 -> 41.549 | I23: ='Valuation - base'!I23 -> 41.549 | J23: ='Valuation - base'!J23 -> 41.549 | L23: Stable
B24: Other:
B25: Dividends in $ - increase of 5% per year | C25: ='Valuation - base'!C25 -> 0.05 | D25: ='Valuation - base'!D25 -> 0.05 | E25: ='Valuation - base'!E25 -> 0.05 | F25: ='Valuation - base'!F25 -> 0.05 | G25: ='Valuation - base'!G25 -> 0.05 | H25: ='Valuation - base'!H25 -> 0.05 | I25: ='Valuation - base'!I25 -> 0.05 | J25: ='Valuation - base'!J25 -> 0.05
B26: Share repurchases in $ - 70% of net income | C26: ='Valuation - base'!C26 -> 0.8 | D26: ='Valuation - base'!D26 -> 0.8 | E26: ='Valuation - base'!E26 -> 0.8 | F26: ='Valuation - base'!F26 -> 0.8 | G26: ='Valuation - base'!G26 -> 0.8 | H26: ='Valuation - base'!H26 -> 0.8 | I26: ='Valuation - base'!I26 -> 0.8 | J26: ='Valuation - base'!J26 -> 0.8
B27: Additional share repurchases/dividends to use foreign cash ($'B) | D27: ='Valuation - base'!D27 -> 20 | E27: ='Valuation - base'!E27 -> 20 | F27: ='Valuation - base'!F27 -> 10 | G27: ='Valuation - base'!G27 -> 10 | L27: Extra share repurchases
B28: CapEx as % of next year sales | C28: ='Valuation - base'!C28 -> 0.03 | D28: ='Valuation - base'!D28 -> 0.05 | E28: ='Valuation - base'!E28 -> 0.07 | F28: ='Valuation - base'!F28 -> 0.07 | G28: ='Valuation - base'!G28 -> 0.07 | H28: ='Valuation - base'!H28 -> 0.07 | I28: ='Valuation - base'!I28 -> 0.07 | J28: ='Valuation - base'!J28 -> 0.07 | L28: Approximately the historical rate, stable business
B29: Depreciation as % of current year CapEx | C29: ='Valuation - base'!C29 -> 0.8 | D29: ='Valuation - base'!D29 -> 0.8 | E29: ='Valuation - base'!E29 -> 0.8 | F29: ='Valuation - base'!F29 -> 0.8 | G29: ='Valuation - base'!G29 -> 0.8 | H29: ='Valuation - base'!H29 -> 0.8 | I29: ='Valuation - base'!I29 -> 0.8 | J29: ='Valuation - base'!J29 -> 0.8 | L29: Approximately the historical rate
B30: Growth rate - terminal | C30: ='Valuation - base'!C30 -> 0.035
C32: ='Valuation - base'!C32 -> Actual | D32: ='Valuation - base'!D32 -> Forecast | E32: ='Valuation - base'!E32 -> Forecast | F32: ='Valuation - base'!F32 -> Forecast | G32: ='Valuation - base'!G32 -> Forecast | H32: ='Valuation - base'!H32 -> Forecast | I32: ='Valuation - base'!I32 -> Forecast | J32: ='Valuation - base'!J32 -> Forecast
B33: Income statement forecast | C33: ='Valuation - base'!C33 -> 2025 | D33: ='Valuation - base'!D33 -> 2026 | E33: ='Valuation - base'!E33 -> 2027 | F33: ='Valuation - base'!F33 -> 2028 | G33: ='Valuation - base'!G33 -> 2029 | H33: ='Valuation - base'!H33 -> 2030 | I33: ='Valuation - base'!I33 -> 2031 | J33: ='Valuation - base'!J33 -> 2032
B34: Net sales | C34: ='Valuation - base'!C34 -> 416.161 | D34: ='Valuation - base'!D34 -> 487 | E34: ='Valuation - base'!E34 -> 545.28 | F34: ='Valuation - base'!F34 -> 588.459 | G34: ='Valuation - base'!G34 -> 629.65113 | H34: ='Valuation - base'!H34 -> 667.4302 | I34: ='Valuation - base'!I34 -> 700.80171 | J34: ='Valuation - base'!J34 -> 728.83378 | L34: See the tab revenue forecast
B35: Cost of sales | C35: ='Valuation - base'!C35 -> -220.96 | D35: ='Valuation - base'!D35 -> -248.37 | E35: ='Valuation - base'!E35 -> -267.1872 | F35: ='Valuation - base'!F35 -> -276.57573 | G35: ='Valuation - base'!G35 -> -295.93603 | H35: ='Valuation - base'!H35 -> -313.69219 | I35: ='Valuation - base'!I35 -> -329.3768 | J35: ='Valuation - base'!J35 -> -342.55187
B36: Gross margin | C36: ='Valuation - base'!C36 -> 195.201 | D36: ='Valuation - base'!D36 -> 238.63 | E36: ='Valuation - base'!E36 -> 278.0928 | F36: ='Valuation - base'!F36 -> 311.88327 | G36: ='Valuation - base'!G36 -> 333.7151 | H36: ='Valuation - base'!H36 -> 353.738 | I36: ='Valuation - base'!I36 -> 371.42491 | J36: ='Valuation - base'!J36 -> 386.2819
B37: Total operating expenses | C37: ='Valuation - base'!C37 -> -62.1 | D37: ='Valuation - base'!D37 -> -72.670673 | E37: ='Valuation - base'!E37 -> -81.367279 | F37: ='Valuation - base'!F37 -> -87.810496 | G37: ='Valuation - base'!G37 -> -93.957231 | H37: ='Valuation - base'!H37 -> -99.594665 | I37: ='Valuation - base'!I37 -> -104.5744 | J37: ='Valuation - base'!J37 -> -108.75737
B38: Operating income | C38: ='Valuation - base'!C38 -> 133.101 | D38: ='Valuation - base'!D38 -> 165.95933 | E38: ='Valuation - base'!E38 -> 196.72552 | F38: ='Valuation - base'!F38 -> 224.07277 | G38: ='Valuation - base'!G38 -> 239.75787 | H38: ='Valuation - base'!H38 -> 254.14334 | I38: ='Valuation - base'!I38 -> 266.85051 | J38: ='Valuation - base'!J38 -> 277.52453
B39: Interest income | C39: ='Valuation - base'!C39 -> 0 | D39: ='Valuation - base'!D39 -> 2.89458 | E39: ='Valuation - base'!E39 -> 2.8527106 | F39: ='Valuation - base'!F39 -> 2.2824597 | G39: ='Valuation - base'!G39 -> 2.1398552 | H39: ='Valuation - base'!H39 -> 2.2609205 | I39: ='Valuation - base'!I39 -> 2.8107626 | J39: ='Valuation - base'!J39 -> 3.3956528
B40: Interest expense | C40: ='Valuation - base'!C40 -> 0 | D40: ='Valuation - base'!D40 -> -4.93285 | E40: ='Valuation - base'!E40 -> -4.93285 | F40: ='Valuation - base'!F40 -> -4.93285 | G40: ='Valuation - base'!G40 -> -4.93285 | H40: ='Valuation - base'!H40 -> -4.93285 | I40: ='Valuation - base'!I40 -> -4.93285 | J40: ='Valuation - base'!J40 -> -4.93285
B41: Income before provision for income taxes | C41: ='Valuation - base'!C41 -> 132.729 | D41: ='Valuation - base'!D41 -> 163.92106 | E41: ='Valuation - base'!E41 -> 194.64538 | F41: ='Valuation - base'!F41 -> 221.42238 | G41: ='Valuation - base'!G41 -> 236.96487 | H41: ='Valuation - base'!H41 -> 251.47141 | I41: ='Valuation - base'!I41 -> 264.72842 | J41: ='Valuation - base'!J41 -> 275.98733
B42: Provision for income taxes | C42: ='Valuation - base'!C42 -> -20.719 | D42: ='Valuation - base'!D42 -> -32.784211 | E42: ='Valuation - base'!E42 -> -38.929076 | F42: ='Valuation - base'!F42 -> -44.284477 | G42: ='Valuation - base'!G42 -> -47.392975 | H42: ='Valuation - base'!H42 -> -50.294282 | I42: ='Valuation - base'!I42 -> -52.945684 | J42: ='Valuation - base'!J42 -> -55.197466
B43: Net income | C43: ='Valuation - base'!C43 -> 112.01 | D43: ='Valuation - base'!D43 -> 131.13685 | E43: ='Valuation - base'!E43 -> 155.71631 | F43: ='Valuation - base'!F43 -> 177.13791 | G43: ='Valuation - base'!G43 -> 189.5719 | H43: ='Valuation - base'!H43 -> 201.17713 | I43: ='Valuation - base'!I43 -> 211.78274 | J43: ='Valuation - base'!J43 -> 220.78986
C45: ='Valuation - base'!C45 -> Actual | D45: ='Valuation - base'!D45 -> Forecast | E45: ='Valuation - base'!E45 -> Forecast | F45: ='Valuation - base'!F45 -> Forecast | G45: ='Valuation - base'!G45 -> Forecast | H45: ='Valuation - base'!H45 -> Forecast | I45: ='Valuation - base'!I45 -> Forecast | J45: ='Valuation - base'!J45 -> Forecast
B46: Balance sheet forecast | C46: ='Valuation - base'!C46 -> 2025 | D46: ='Valuation - base'!D46 -> 2026 | E46: ='Valuation - base'!E46 -> 2027 | F46: ='Valuation - base'!F46 -> 2028 | G46: ='Valuation - base'!G46 -> 2029 | H46: ='Valuation - base'!H46 -> 2030 | I46: ='Valuation - base'!I46 -> 2031 | J46: ='Valuation - base'!J46 -> 2032
B47: Cash and cash equivalents | C47: ='Valuation - base'!C47 -> 35.934 | D47: ='Valuation - base'!D47 -> 35.934 | E47: ='Valuation - base'!E47 -> 35.934 | F47: ='Valuation - base'!F47 -> 35.934 | G47: ='Valuation - base'!G47 -> 35.934 | H47: ='Valuation - base'!H47 -> 35.934 | I47: ='Valuation - base'!I47 -> 35.934 | J47: ='Valuation - base'!J47 -> 35.934
B48: Marketable securities - ST and LT | C48: ='Valuation - base'!C48 -> 96.486 | D48: ='Valuation - base'!D48 -> 71.317765 | E48: ='Valuation - base'!E48 -> 57.061491 | F48: ='Valuation - base'!F48 -> 53.496381 | G48: ='Valuation - base'!G48 -> 56.523011 | H48: ='Valuation - base'!H48 -> 70.269065 | I48: ='Valuation - base'!I48 -> 84.89132 | J48: ='Valuation - base'!J48 -> 99.96139 | L48: This is a plug
B49: Accounts receivable, less allowances | C49: ='Valuation - base'!C49 -> 39.777 | D49: ='Valuation - base'!D49 -> 28.59749 | E49: ='Valuation - base'!E49 -> 32.019793 | F49: ='Valuation - base'!F49 -> 34.55534 | G49: ='Valuation - base'!G49 -> 36.974213 | H49: ='Valuation - base'!H49 -> 39.192666 | I49: ='Valuation - base'!I49 -> 41.1523 | J49: ='Valuation - base'!J49 -> 42.798392
B50: Inventories | C50: ='Valuation - base'!C50 -> 5.718 | D50: ='Valuation - base'!D50 -> 5.9485522 | E50: ='Valuation - base'!E50 -> 6.3992311 | F50: ='Valuation - base'!F50 -> 6.6240898 | G50: ='Valuation - base'!G50 -> 7.0877761 | H50: ='Valuation - base'!H50 -> 7.5130426 | I50: ='Valuation - base'!I50 -> 7.8886948 | J50: ='Valuation - base'!J50 -> 8.2042426
B51: Other current assets | C51: ='Valuation - base'!C51 -> 47.765 | D51: ='Valuation - base'!D51 -> 57.814119 | E51: ='Valuation - base'!E51 -> 64.732819 | F51: ='Valuation - base'!F51 -> 69.858807 | G51: ='Valuation - base'!G51 -> 74.748923 | H51: ='Valuation - base'!H51 -> 79.233859 | I51: ='Valuation - base'!I51 -> 83.195552 | J51: ='Valuation - base'!J51 -> 86.523374
B52: Property, plant and equipment, net | C52: ='Valuation - base'!C52 -> 49.834 | D52: ='Valuation - base'!D52 -> 55.2868 | E52: ='Valuation - base'!E52 -> 63.525226 | F52: ='Valuation - base'!F52 -> 72.340342 | G52: ='Valuation - base'!G52 -> 81.684365 | H52: ='Valuation - base'!H52 -> 91.495588 | I52: ='Valuation - base'!I52 -> 101.30681 | J52: ='Valuation - base'!J52 -> 111.11804 | L52: Prior PPE + CapEx - Depreciation
B53: Goodwill + intangbles + other | C53: ='Valuation - base'!C53 -> 83.727 | D53: ='Valuation - base'!D53 -> 83.727 | E53: ='Valuation - base'!E53 -> 83.727 | F53: ='Valuation - base'!F53 -> 83.727 | G53: ='Valuation - base'!G53 -> 83.727 | H53: ='Valuation - base'!H53 -> 83.727 | I53: ='Valuation - base'!I53 -> 83.727 | J53: ='Valuation - base'!J53 -> 83.727
B54: Total assets | C54: ='Valuation - base'!C54 -> 359.241 | D54: ='Valuation - base'!D54 -> 338.62573 | E54: ='Valuation - base'!E54 -> 343.39956 | F54: ='Valuation - base'!F54 -> 356.53596 | G54: ='Valuation - base'!G54 -> 376.67929 | H54: ='Valuation - base'!H54 -> 407.36522 | I54: ='Valuation - base'!I54 -> 438.09568 | J54: ='Valuation - base'!J54 -> 468.26643
B56: Accounts payable | C56: ='Valuation - base'!C56 -> 69.86 | D56: ='Valuation - base'!D56 -> 61.955175 | E56: ='Valuation - base'!E56 -> 66.649071 | F56: ='Valuation - base'!F56 -> 68.991012 | G56: ='Valuation - base'!G56 -> 73.820383 | H56: ='Valuation - base'!H56 -> 78.249606 | I56: ='Valuation - base'!I56 -> 82.162087 | J56: ='Valuation - base'!J56 -> 85.44857
B57: Accrued expenses | C57: ='Valuation - base'!C57 -> 75.442 | D57: ='Valuation - base'!D57 -> 72.254183 | E57: ='Valuation - base'!E57 -> 77.72836 | F57: ='Valuation - base'!F57 -> 80.45961 | G57: ='Valuation - base'!G57 -> 86.091783 | H57: ='Valuation - base'!H57 -> 91.25729 | I57: ='Valuation - base'!I57 -> 95.820154 | J57: ='Valuation - base'!J57 -> 99.65296
B58: ST debt | C58: ='Valuation - base'!C58 -> 20.329 | D58: ='Valuation - base'!D58 -> 20.329 | E58: ='Valuation - base'!E58 -> 20.329 | F58: ='Valuation - base'!F58 -> 20.329 | G58: ='Valuation - base'!G58 -> 20.329 | H58: ='Valuation - base'!H58 -> 20.329 | I58: ='Valuation - base'!I58 -> 20.329 | J58: ='Valuation - base'!J58 -> 20.329
B59: Long-term debt | C59: ='Valuation - base'!C59 -> 78.328 | D59: ='Valuation - base'!D59 -> 78.328 | E59: ='Valuation - base'!E59 -> 78.328 | F59: ='Valuation - base'!F59 -> 78.328 | G59: ='Valuation - base'!G59 -> 78.328 | H59: ='Valuation - base'!H59 -> 78.328 | I59: ='Valuation - base'!I59 -> 78.328 | J59: ='Valuation - base'!J59 -> 78.328
B60: Non-current liabilities | C60: ='Valuation - base'!C60 -> 41.549 | D60: ='Valuation - base'!D60 -> 41.549 | E60: ='Valuation - base'!E60 -> 41.549 | F60: ='Valuation - base'!F60 -> 41.549 | G60: ='Valuation - base'!G60 -> 41.549 | H60: ='Valuation - base'!H60 -> 41.549 | I60: ='Valuation - base'!I60 -> 41.549 | J60: ='Valuation - base'!J60 -> 41.549
B61: Total liabilities | C61: ='Valuation - base'!C61 -> 285.508 | D61: ='Valuation - base'!D61 -> 274.41536 | E61: ='Valuation - base'!E61 -> 284.58343 | F61: ='Valuation - base'!F61 -> 289.65662 | G61: ='Valuation - base'!G61 -> 300.11817 | H61: ='Valuation - base'!H61 -> 309.7129 | I61: ='Valuation - base'!I61 -> 318.18824 | J61: ='Valuation - base'!J61 -> 325.30753
B62: Total shareholders' equity | C62: ='Valuation - base'!C62 -> 73.733 | D62: ='Valuation - base'!D62 -> 64.210369 | E62: ='Valuation - base'!E62 -> 58.81613 | F62: ='Valuation - base'!F62 -> 66.879337 | G62: ='Valuation - base'!G62 -> 76.561123 | H62: ='Valuation - base'!H62 -> 97.652325 | I62: ='Valuation - base'!I62 -> 119.90744 | J62: ='Valuation - base'!J62 -> 142.9589 | L62: Prior equity + NI - Dividends - buybacks
B63: Total liabilities and equity | C63: ='Valuation - base'!C63 -> 359.241 | D63: ='Valuation - base'!D63 -> 338.62573 | E63: ='Valuation - base'!E63 -> 343.39956 | F63: ='Valuation - base'!F63 -> 356.53596 | G63: ='Valuation - base'!G63 -> 376.67929 | H63: ='Valuation - base'!H63 -> 407.36522 | I63: ='Valuation - base'!I63 -> 438.09568 | J63: ='Valuation - base'!J63 -> 468.26643
B65: Other
B66: CapEx | D66: ='Valuation - base'!D66 -> 27.264 | E66: ='Valuation - base'!E66 -> 41.19213 | F66: ='Valuation - base'!F66 -> 44.075579 | G66: ='Valuation - base'!G66 -> 46.720114 | H66: ='Valuation - base'!H66 -> 49.05612 | I66: ='Valuation - base'!I66 -> 49.05612 | J66: ='Valuation - base'!J66 -> 49.05612
B67: Depreciation | D67: ='Valuation - base'!D67 -> 21.8112 | E67: ='Valuation - base'!E67 -> 32.953704 | F67: ='Valuation - base'!F67 -> 35.260463 | G67: ='Valuation - base'!G67 -> 37.376091 | H67: ='Valuation - base'!H67 -> 39.244896 | I67: ='Valuation - base'!I67 -> 39.244896 | J67: ='Valuation - base'!J67 -> 39.244896
B68: Dividends | C68: ='Valuation - base'!C68 -> 15 | D68: ='Valuation - base'!D68 -> 15.75 | E68: ='Valuation - base'!E68 -> 16.5375 | F68: ='Valuation - base'!F68 -> 17.364375 | G68: ='Valuation - base'!G68 -> 18.232594 | H68: ='Valuation - base'!H68 -> 19.144223 | I68: ='Valuation - base'!I68 -> 20.101435 | J68: ='Valuation - base'!J68 -> 21.106506
B69: Share repurchases | D69: ='Valuation - base'!D69 -> 124.90948 | E69: ='Valuation - base'!E69 -> 144.57304 | F69: ='Valuation - base'!F69 -> 151.71033 | G69: ='Valuation - base'!G69 -> 161.65752 | H69: ='Valuation - base'!H69 -> 160.9417 | I69: ='Valuation - base'!I69 -> 169.42619 | J69: ='Valuation - base'!J69 -> 176.63189
D71: ='Valuation - base'!D71 -> Forecast | E71: ='Valuation - base'!E71 -> Forecast | F71: ='Valuation - base'!F71 -> Forecast | G71: ='Valuation - base'!G71 -> Forecast | H71: ='Valuation - base'!H71 -> Forecast | I71: ='Valuation - base'!I71 -> Forecast | J71: ='Valuation - base'!J71 -> Forecast
B72: Free cash flow | D72: ='Valuation - base'!D72 -> 2026 | E72: ='Valuation - base'!E72 -> 2027 | F72: ='Valuation - base'!F72 -> 2028 | G72: ='Valuation - base'!G72 -> 2029 | H72: ='Valuation - base'!H72 -> 2030 | I72: ='Valuation - base'!I72 -> 2031 | J72: ='Valuation - base'!J72 -> 2032
B73: EBIT * (1-tax rate) | D73: ='Valuation - base'!D73 -> 132.76746 | E73: ='Valuation - base'!E73 -> 157.38042 | F73: ='Valuation - base'!F73 -> 179.25822 | G73: ='Valuation - base'!G73 -> 191.80629 | H73: ='Valuation - base'!H73 -> 203.31467 | I73: ='Valuation - base'!I73 -> 213.48041 | J73: ='Valuation - base'!J73 -> 222.01962
B74: Depreciation | D74: ='Valuation - base'!D74 -> 21.8112 | E74: ='Valuation - base'!E74 -> 32.953704 | F74: ='Valuation - base'!F74 -> 35.260463 | G74: ='Valuation - base'!G74 -> 37.376091 | H74: ='Valuation - base'!H74 -> 39.244896 | I74: ='Valuation - base'!I74 -> 39.244896 | J74: ='Valuation - base'!J74 -> 39.244896
B75: CapEx | D75: ='Valuation - base'!D75 -> -27.264 | E75: ='Valuation - base'!E75 -> -41.19213 | F75: ='Valuation - base'!F75 -> -44.075579 | G75: ='Valuation - base'!G75 -> -46.720114 | H75: ='Valuation - base'!H75 -> -49.05612 | I75: ='Valuation - base'!I75 -> -49.05612 | J75: ='Valuation - base'!J75 -> -49.05612
B76: WC calculation
B77: (Increase)/decrease in AR | D77: ='Valuation - base'!D77 -> 11.17951 | E77: ='Valuation - base'!E77 -> -3.4223033 | F77: ='Valuation - base'!F77 -> -2.5355463 | G77: ='Valuation - base'!G77 -> -2.4188738 | H77: ='Valuation - base'!H77 -> -2.2184528 | I77: ='Valuation - base'!I77 -> -1.9596333 | J77: ='Valuation - base'!J77 -> -1.646092
B78: (Increase)/decrease in Inventory | D78: ='Valuation - base'!D78 -> -0.23055224 | E78: ='Valuation - base'!E78 -> -0.45067882 | F78: ='Valuation - base'!F78 -> -0.22485872 | G78: ='Valuation - base'!G78 -> -0.46368628 | H78: ='Valuation - base'!H78 -> -0.42526656 | I78: ='Valuation - base'!I78 -> -0.37565213 | J78: ='Valuation - base'!J78 -> -0.31554779
B79: (Increase)/decrease in other current assets | D79: ='Valuation - base'!D79 -> -10.049119 | E79: ='Valuation - base'!E79 -> -6.9187 | F79: ='Valuation - base'!F79 -> -5.1259874 | G79: ='Valuation - base'!G79 -> -4.8901165 | H79: ='Valuation - base'!H79 -> -4.4849354 | I79: ='Valuation - base'!I79 -> -3.9616929 | J79: ='Valuation - base'!J79 -> -3.3278221
B80: Increase/(decrease) in AP | D80: ='Valuation - base'!D80 -> -7.904825 | E80: ='Valuation - base'!E80 -> 4.6938959 | F80: ='Valuation - base'!F80 -> 2.3419415 | G80: ='Valuation - base'!G80 -> 4.8293709 | H80: ='Valuation - base'!H80 -> 4.429223 | I80: ='Valuation - base'!I80 -> 3.9124803 | J80: ='Valuation - base'!J80 -> 3.2864835
B81: Increase/(decrease) in Accrued expenses | D81: ='Valuation - base'!D81 -> -3.1878171 | E81: ='Valuation - base'!E81 -> 5.4741773 | F81: ='Valuation - base'!F81 -> 2.73125 | G81: ='Valuation - base'!G81 -> 5.6321727 | H81: ='Valuation - base'!H81 -> 5.165507 | I81: ='Valuation - base'!I81 -> 4.5628645 | J81: ='Valuation - base'!J81 -> 3.8328062
B82: Free Cash Flows | D82: ='Valuation - base'!D82 -> 117.12186 | E82: ='Valuation - base'!E82 -> 148.51838 | F82: ='Valuation - base'!F82 -> 167.6299 | G82: ='Valuation - base'!G82 -> 185.15114 | H82: ='Valuation - base'!H82 -> 195.96952 | I82: ='Valuation - base'!I82 -> 205.84755 | J82: ='Valuation - base'!J82 -> 214.03823
B83: Terminal Value | J83: ='Valuation - base'!J83 -> 4825.8265
B84: Total Free Cash Flow | D84: ='Valuation - base'!D84 -> 117.12186 | E84: ='Valuation - base'!E84 -> 148.51838 | F84: ='Valuation - base'!F84 -> 167.6299 | G84: ='Valuation - base'!G84 -> 185.15114 | H84: ='Valuation - base'!H84 -> 195.96952 | I84: ='Valuation - base'!I84 -> 205.84755 | J84: ='Valuation - base'!J84 -> 5039.8647
B86: PV of the Total Free Cash Flow | C86: =NPV('cost of capital'!C22,E84:J84) -> 3870.6079
B87: Add cash and MS | C87: =D47+D48 -> 107.25177
B88: Subtract Debt | C88: =-(D59+D58) -> -98.657
B89: Apple market value | C89: =SUM(C86:C88) -> 3879.2026 | E89: `
B90: Number of shares in B | C90: =C95 -> 14.300362
B91: Share price | C91: =C89/C90 -> 271.26604
B93: Beginning shares outstanding | C93: ='cost of capital'!C12 -> 14.8
B94: Shares repurchased | C94: =D69/250 -> 0.49963791 | E94: Assume average price of $250 per share
B95: Ending shares outstanding | C95: =C93-C94 -> 14.300362

Sheet cost of capital
B2: Cost of capital
B3: Assumes that the weight of debt in the capital structure will remain stable going forward
B5: Inputs | E5: Comment
B6: Cost of debt | C6: 0.03 | E6: From Apple 10K (approximate)
B7: Tax rate | C7: 0.21 | E7: Interest payments are in the US
B8: 10y UST | C8: 0.025 | E8: Estimate - long-term
B9: Market risk premium | C9: 0.06 | E9: Estimate - long-term
B10: Beta Apple | C10: 1.1 | E10: From Yahoo Finance
B11: Beta Apple - assuming similar leverage | C11: 1.1 | E11: Estimate - similar leverage going forward
B12: Shares Sept 2023 | C12: 14.8 | E12: Yahoo Finance
B14: Debt value Sept 2025 | C14: 100 | E14: From 2025 BS
B15: Equity value November 2025 | C15: 4000 | E15: Market cap approximation
B16: Gross debt weight November 2025 | C16: =C14/(C14+C15) -> 0.024390244 | E16: Used market cap and current gross debt
B17: Permanent debt weight - estimate | C17: 0.15 | E17: Estimate
B19: Cost of capital calculation
B20: Cost of equity | C20: =C8+C9*C11 -> 0.091 | E20: CAPM
B21: After-tax cost of debt | C21: =C6*(1-C7) -> 0.0237
B22: WACC | C22: =C21*C17+(1-C17)*C20 -> 0.080905

Sheet IS
B2: Income Statement - As Reported
C3: Sep '06 | D3: Sep '07 | E3: Sep '08 | F3: Sep '09 | G3: Sep '10 | H3: Sep '11 | I3: Sep '12 | J3: Sep '13 | K3: Sep '14 | L3: Sep '15 | M3: Sep '16 | N3: Sep '17 | O3: Sep '18 | P3: Sep '19 | Q3: Sep '20 | R3: Sep '21 | S3: Sep '22 | T3: Sep '23 | U3: Sep '24 | V3: Sep '25
B4: Net sales | C4: 19.315 | D4: 24.006 | E4: 37.491 | F4: 42.905 | G4: 65.225 | H4: 108.249 | I4: 156.508 | J4: 170.91 | K4: 182.795 | L4: 233.715 | M4: 215.639 | N4: 229.234 | O4: 265.595 | P4: 260.174 | Q4: 274.515 | R4: 365.817 | S4: 394 | T4: 383 | U4: 391 | V4: 416.161
B5: Cost of sales | C5: -13.717 | D5: -15.852 | E5: -24.294 | F5: -25.683 | G5: -39.541 | H5: -64.431 | I5: -87.846 | J5: -106.606 | K5: -112.258 | L5: -140.089 | M5: -131.376 | N5: -141.048 | O5: -163.756 | P5: -161.782 | Q5: -169.559 | R5: -212.981 | S5: -224 | T5: -214 | U5: -210 | V5: -220.96
B6: Gross margin | C6: 5.598 | D6: 8.154 | E6: 13.197 | F6: 17.222 | G6: 25.684 | H6: 43.818 | I6: 68.662 | J6: 64.304 | K6: 70.537 | L6: 93.626 | M6: 84.263 | N6: 88.186 | O6: 101.839 | P6: 98.392 | Q6: 104.956 | R6: 152.836 | S6: 171 | T6: 169 | U6: =SUM(U4:U5) -> 181 | V6: 195.201
B7: Total operating expenses | C7: -3.145 | D7: -3.745 | E7: -4.87 | F7: -5.482 | G7: -7.299 | H7: -10.028 | I7: -13.421 | J7: -15.305 | K7: -18.034 | L7: -22.396 | M7: -24.239 | N7: -26.842 | O7: -30.941 | P7: -34.462 | Q7: =SUM(Q8:Q9) -> -38.668 | R7: -43.887 | S7: -51 | T7: -55 | U7: -58 | V7: -62.1
B8: Research and development | C8: -0.712 | D8: -0.782 | E8: -1.109 | F8: -1.333 | G8: -1.782 | H8: -2.429 | I8: -3.381 | J8: -4.475 | K8: -6.041 | L8: -8.067 | M8: -10.045 | N8: -11.581 | O8: -14.236 | P8: -16.217 | Q8: -18.752 | R8: -21.914 | S8: -26 | T8: -30 | U8: -31 | V8: -34.55
B9: Selling, general and administrative | C9: -2.433 | D9: -2.963 | E9: -3.761 | F9: -4.149 | G9: -5.517 | H9: -7.599 | I9: -10.04 | J9: -10.83 | K9: -11.993 | L9: -14.329 | M9: -14.194 | N9: -15.261 | O9: -16.705 | P9: -18.245 | Q9: -19.916 | R9: -21.973 | S9: -25 | T9: -25 | U9: -26 | V9: -27.601
B10: Operating income | C10: 2.453 | D10: 4.409 | E10: 8.327 | F10: 11.74 | G10: 18.385 | H10: 33.79 | I10: 55.241 | J10: 48.999 | K10: 52.503 | L10: 71.23 | M10: 60.024 | N10: 61.344 | O10: 70.898 | P10: 63.93 | Q10: =Q6+Q7 -> 66.288 | R10: 108.949 | S10: 119.4 | T10: 114 | U10: 123.2 | V10: 133.05
B11: Other income / expense, net | C11: 0.365 | D11: 0.599 | E11: 0.62 | F11: 0.326 | G11: 0.155 | H11: 0.415 | I11: 0.522 | J11: 1.156 | K11: 0.98 | L11: 1.285 | M11: 1.348 | N11: 2.745 | O11: 2.005 | P11: 1.807 | Q11: 0.803 | R11: 0.258 | S11: -0.3 | T11: -0.5 | U11: 0.3 | V11: -0.321
B12: Income before provision for income taxes | C12: 2.818 | D12: 5.008 | E12: 8.947 | F12: 12.066 | G12: 18.54 | H12: 34.205 | I12: 55.763 | J12: 50.155 | K12: 53.483 | L12: 72.515 | M12: 61.372 | N12: 64.089 | O12: 72.903 | P12: 65.737 | Q12: =Q10+Q11 -> 67.091 | R12: 109.207 | S12: 119.1 | T12: 114 | U12: =SUM(U10:U11) -> 123.5 | V12: 132.729
B13: Provision for income taxes | C13: -0.829 | D13: -1.512 | E13: -2.828 | F13: -3.831 | G13: -4.527 | H13: -8.283 | I13: -14.03 | J13: -13.118 | K13: -13.973 | L13: -19.121 | M13: -15.685 | N13: -15.738 | O13: -13.372 | P13: -10.481 | Q13: -9.68 | R13: -14.527 | S13: -19.3 | T13: -18 | U13: -30 | V13: -20.719
B14: Net income | C14: 1.989 | D14: 3.496 | E14: 6.119 | F14: 8.235 | G14: 14.013 | H14: 25.922 | I14: 41.733 | J14: 37.037 | K14: 39.51 | L14: 53.394 | M14: 45.687 | N14: 48.351 | O14: 59.531 | P14: 55.256 | Q14: =SUM(Q12:Q13) -> 57.411 | R14: 94.68 | S14: 100 | T14: 97 | U14: 93.7 | V14: 112.01
B16: Interest expense | C16: 0 | D16: 0 | E16: 0 | F16: 0 | G16: 0 | H16: 0 | I16: 0 | J16: 0.136 | K16: 0.384 | L16: 0.733 | M16: 1.46 | N16: 2.3 | O16: 3.24 | P16: 3.6 | Q16: 2.9 | R16: 2.6 | S16: 2.9 | T16: 4 | U16: 4 | V16: 4
B17: Dividends | C17: 0 | D17: 0 | E17: 0 | F17: 0 | G17: 0 | H17: 0 | I17: 2.488 | J17: 10.564 | K17: 11.126 | L17: 11.561 | M17: 12.2 | N17: 12.8 | O17: 13.7 | P17: 14.12 | Q17: 14.08 | R17: 14.5 | S17: 14.8 | T17: 15 | U17: 15 | V17: 15

Sheet IS common size
B2: Income Statement - As Reported - common size
C4: Sep '06 | D4: Sep '07 | E4: Sep '08 | F4: Sep '09 | G4: Sep '10 | H4: Sep '11 | I4: Sep '12 | J4: Sep '13 | K4: Sep '14 | L4: Sep '15 | M4: Sep '16 | N4: Sep '17 | O4: Sep '18 | P4: Sep '19 | Q4: =IS!Q3 -> Sep '20 | R4: =IS!R3 -> Sep '21 | S4: =IS!S3 -> Sep '22 | T4: =IS!T3 -> Sep '23 | U4: =IS!U3 -> Sep '24 | V4: =IS!V3 -> Sep '25
B5: Net sales in $'B - 100% | C5: 19.315 | D5: 24.006 | E5: 37.491 | F5: 42.905 | G5: 65.225 | H5: 108.249 | I5: 156.508 | J5: 170.91 | K5: 182.795 | L5: 233.715 | M5: =IS!M4 -> 215.639 | N5: =IS!N4 -> 229.234 | O5: =IS!O4 -> 265.595 | P5: =IS!P4 -> 260.174 | Q5: =IS!Q4 -> 274.515 | R5: =IS!R4 -> 365.817 | S5: =IS!S4 -> 394 | T5: =IS!T4 -> 383 | ... V5: =IS!V4 -> 416.161
B6: Cost of sales | C6: =-IS!C5/IS!C$4 -> 0.71017344 | D6: =-IS!D5/IS!D$4 -> 0.66033492 | E6: =-IS!E5/IS!E$4 -> 0.64799552 | F6: =-IS!F5/IS!F$4 -> 0.59860156 | G6: =-IS!G5/IS!G$4 -> 0.60622461 | H6: =-IS!H5/IS!H$4 -> 0.59521104 | I6: =-IS!I5/IS!I$4 -> 0.5612876 | J6: =-IS!J5/IS!J$4 -> 0.62375519 | ... V6: =-IS!V5/IS!V$4 -> 0.53094836
B7: Gross margin | C7: =IS!C6/IS!C$4 -> 0.28982656 | D7: =IS!D6/IS!D$4 -> 0.33966508 | E7: =IS!E6/IS!E$4 -> 0.35200448 | F7: =IS!F6/IS!F$4 -> 0.40139844 | G7: =IS!G6/IS!G$4 -> 0.39377539 | H7: =IS!H6/IS!H$4 -> 0.40478896 | I7: =IS!I6/IS!I$4 -> 0.4387124 | J7: =IS!J6/IS!J$4 -> 0.37624481 | ... V7: =IS!V6/IS!V$4 -> 0.46905164
B8: Total operating expenses | C8: =-IS!C7/IS!C$4 -> 0.16282682 | D8: =-IS!D7/IS!D$4 -> 0.15600267 | E8: =-IS!E7/IS!E$4 -> 0.12989784 | F8: =-IS!F7/IS!F$4 -> 0.12777066 | G8: =-IS!G7/IS!G$4 -> 0.11190494 | H8: =-IS!H7/IS!H$4 -> 0.092638269 | I8: =-IS!I7/IS!I$4 -> 0.085752805 | J8: =-IS!J7/IS!J$4 -> 0.089550056 | ... V8: =-IS!V7/IS!V$4 -> 0.14922109
B9: Research and development | C9: =-IS!C8/IS!C$4 -> 0.036862542 | D9: =-IS!D8/IS!D$4 -> 0.03257519 | E9: =-IS!E8/IS!E$4 -> 0.029580433 | F9: =-IS!F8/IS!F$4 -> 0.03106864 | G9: =-IS!G8/IS!G$4 -> 0.027320813 | H9: =-IS!H8/IS!H$4 -> 0.022439006 | I9: =-IS!I8/IS!I$4 -> 0.02160273 | J9: =-IS!J8/IS!J$4 -> 0.026183371 | ... V9: =-IS!V8/IS!V$4 -> 0.083020754
B10: Selling, general and administrative | C10: =-IS!C9/IS!C$4 -> 0.12596428 | D10: =-IS!D9/IS!D$4 -> 0.12342748 | E10: =-IS!E9/IS!E$4 -> 0.10031741 | F10: =-IS!F9/IS!F$4 -> 0.096702016 | G10: =-IS!G9/IS!G$4 -> 0.084584132 | H10: =-IS!H9/IS!H$4 -> 0.070199263 | I10: =-IS!I9/IS!I$4 -> 0.064150075 | J10: =-IS!J9/IS!J$4 -> 0.063366684 | ... V10: =-IS!V9/IS!V$4 -> 0.066322889
B11: Operating income | C11: =IS!C10/IS!C$4 -> 0.12699974 | D11: =IS!D10/IS!D$4 -> 0.18366242 | E11: =IS!E10/IS!E$4 -> 0.22210664 | F11: =IS!F10/IS!F$4 -> 0.27362778 | G11: =IS!G10/IS!G$4 -> 0.28187045 | H11: =IS!H10/IS!H$4 -> 0.31215069 | I11: =IS!I10/IS!I$4 -> 0.35295959 | J11: =IS!J10/IS!J$4 -> 0.28669475 | ... V11: =IS!V10/IS!V$4 -> 0.319708
B12: Other income / expense, net | C12: =-IS!C11/IS!C$4 -> -0.01889723 | D12: =-IS!D11/IS!D$4 -> -0.024952095 | E12: =-IS!E11/IS!E$4 -> -0.016537302 | F12: =-IS!F11/IS!F$4 -> -0.007598182 | G12: =-IS!G11/IS!G$4 -> -0.0023763894 | H12: =-IS!H11/IS!H$4 -> -0.0038337537 | I12: =-IS!I11/IS!I$4 -> -0.0033352928 | J12: =-IS!J11/IS!J$4 -> -0.0067637938 | ... V12: =-IS!V11/IS!V$4 -> 0.00077133609
B13: Income before taxes | C13: =IS!C12/IS!C$4 -> 0.14589697 | D13: =IS!D12/IS!D$4 -> 0.20861451 | E13: =IS!E12/IS!E$4 -> 0.23864394 | F13: =IS!F12/IS!F$4 -> 0.28122596 | G13: =IS!G12/IS!G$4 -> 0.28424684 | H13: =IS!H12/IS!H$4 -> 0.31598444 | I13: =IS!I12/IS!I$4 -> 0.35629489 | J13: =IS!J12/IS!J$4 -> 0.29345855 | ... V13: =IS!V12/IS!V$4 -> 0.31893666
B14: Provision for income taxes | C14: =-IS!C13/IS!C$4 -> 0.04292001 | D14: =-IS!D13/IS!D$4 -> 0.062984254 | E14: =-IS!E13/IS!E$4 -> 0.075431437 | F14: =-IS!F13/IS!F$4 -> 0.089290293 | G14: =-IS!G13/IS!G$4 -> 0.069405903 | H14: =-IS!H13/IS!H$4 -> 0.076518028 | I14: =-IS!I13/IS!I$4 -> 0.08964398 | J14: =-IS!J13/IS!J$4 -> 0.076753847 | ... V14: =-IS!V13/IS!V$4 -> 0.04978602
B15: Net income | C15: =IS!C14/IS!C$4 -> 0.10297696 | D15: =IS!D14/IS!D$4 -> 0.14563026 | E15: =IS!E14/IS!E$4 -> 0.1632125 | F15: =IS!F14/IS!F$4 -> 0.19193567 | G15: =IS!G14/IS!G$4 -> 0.21484094 | H15: =IS!H14/IS!H$4 -> 0.23946642 | I15: =IS!I14/IS!I$4 -> 0.26665091 | J15: =IS!J14/IS!J$4 -> 0.2167047 | ... V15: =IS!V14/IS!V$4 -> 0.26915064
B17: Sales growth | D17: =(D5-C5)/C5 -> 0.24286824 | E17: =(E5-D5)/D5 -> 0.56173457 | F17: =(F5-E5)/E5 -> 0.14440799 | G17: =(G5-F5)/F5 -> 0.52021909 | H17: =(H5-G5)/G5 -> 0.65962438 | I17: =(I5-H5)/H5 -> 0.44581474 | J17: =(J5-I5)/I5 -> 0.092020855 | K17: =(K5-J5)/J5 -> 0.069539524 | ... V17: =(V5-U5)/U5 -> 0.064350384
B18: Gross profit growth | D18: =(IS!D6-IS!C6)/IS!C6 -> 0.45659164 | E18: =(IS!E6-IS!D6)/IS!D6 -> 0.61846946 | F18: =(IS!F6-IS!E6)/IS!E6 -> 0.30499356 | G18: =(IS!G6-IS!F6)/IS!F6 -> 0.49134828 | H18: =(IS!H6-IS!G6)/IS!G6 -> 0.70604267 | I18: =(IS!I6-IS!H6)/IS!H6 -> 0.56698161 | J18: =(IS!J6-IS!I6)/IS!I6 -> -0.063470333 | K18: =(IS!K6-IS!J6)/IS!J6 -> 0.096930207 | ... V18: =(IS!V6-IS!U6)/IS!U6 -> 0.078458564
B19: Operating income growth | D19: =(IS!D10-IS!C10)/IS!C10 -> 0.79739095 | E19: =(IS!E10-IS!D10)/IS!D10 -> 0.88863688 | F19: =(IS!F10-IS!E10)/IS!E10 -> 0.4098715 | G19: =(IS!G10-IS!F10)/IS!F10 -> 0.56601363 | H19: =(IS!H10-IS!G10)/IS!G10 -> 0.83791134 | I19: =(IS!I10-IS!H10)/IS!H10 -> 0.63483279 | J19: =(IS!J10-IS!I10)/IS!I10 -> -0.11299578 | K19: =(IS!K10-IS!J10)/IS!J10 -> 0.071511664 | ... V19: =(IS!V10-IS!U10)/IS!U10 -> 0.079951299
B20: Net income growth | D20: =(IS!D14-IS!C14)/IS!C14 -> 0.75766717 | E20: =(IS!E14-IS!D14)/IS!D14 -> 0.75028604 | F20: =(IS!F14-IS!E14)/IS!E14 -> 0.34580814 | G20: =(IS!G14-IS!F14)/IS!F14 -> 0.70163934 | H20: =(IS!H14-IS!G14)/IS!G14 -> 0.84985371 | I20: =(IS!I14-IS!H14)/IS!H14 -> 0.60994522 | J20: =(IS!J14-IS!I14)/IS!I14 -> -0.11252486 | K20: =(IS!K14-IS!J14)/IS!J14 -> 0.066771067 | ... V20: =(IS!V14-IS!U14)/IS!U14 -> 0.19541089

Sheet IS graphs
B2: Income statement - common size - graphs
B4: Income composition
B23: Expenses composition excl cost of sales

Sheet Sales and profit growth
B2: Income Statement - growth measures
D4: Sep '07 | E4: Sep '08 | F4: Sep '09 | G4: Sep '10 | H4: Sep '11 | I4: Sep '12 | J4: Sep '13 | K4: Sep '14 | L4: Sep '15 | M4: Sep '16 | N4: Sep '17 | O4: Sep '18 | P4: Sep '19 | Q4: =IS!Q3 -> Sep '20 | R4: =IS!R3 -> Sep '21 | S4: =IS!S3 -> Sep '22 | T4: =IS!T3 -> Sep '23 | U4: =IS!U3 -> Sep '24 | V4: =IS!V3 -> Sep '25
B5: Sales growth | D5: =(IS!D4-IS!C4)/IS!C4 -> 0.24286824 | E5: =(IS!E4-IS!D4)/IS!D4 -> 0.56173457 | F5: =(IS!F4-IS!E4)/IS!E4 -> 0.14440799 | G5: =(IS!G4-IS!F4)/IS!F4 -> 0.52021909 | H5: =(IS!H4-IS!G4)/IS!G4 -> 0.65962438 | I5: =(IS!I4-IS!H4)/IS!H4 -> 0.44581474 | J5: =(IS!J4-IS!I4)/IS!I4 -> 0.092020855 | K5: =(IS!K4-IS!J4)/IS!J4 -> 0.069539524 | ... V5: =(IS!V4-IS!U4)/IS!U4 -> 0.064350384
B6: Gross profit growth | D6: =(IS!D6-IS!C6)/IS!C6 -> 0.45659164 | E6: =(IS!E6-IS!D6)/IS!D6 -> 0.61846946 | F6: =(IS!F6-IS!E6)/IS!E6 -> 0.30499356 | G6: =(IS!G6-IS!F6)/IS!F6 -> 0.49134828 | H6: =(IS!H6-IS!G6)/IS!G6 -> 0.70604267 | I6: =(IS!I6-IS!H6)/IS!H6 -> 0.56698161 | J6: =(IS!J6-IS!I6)/IS!I6 -> -0.063470333 | K6: =(IS!K6-IS!J6)/IS!J6 -> 0.096930207 | ... V6: =(IS!V6-IS!U6)/IS!U6 -> 0.078458564
B7: Operating income growth | D7: =(IS!D10-IS!C10)/IS!C10 -> 0.79739095 | E7: =(IS!E10-IS!D10)/IS!D10 -> 0.88863688 | F7: =(IS!F10-IS!E10)/IS!E10 -> 0.4098715 | G7: =(IS!G10-IS!F10)/IS!F10 -> 0.56601363 | H7: =(IS!H10-IS!G10)/IS!G10 -> 0.83791134 | I7: =(IS!I10-IS!H10)/IS!H10 -> 0.63483279 | J7: =(IS!J10-IS!I10)/IS!I10 -> -0.11299578 | K7: =(IS!K10-IS!J10)/IS!J10 -> 0.071511664 | ... V7: =(IS!V10-IS!U10)/IS!U10 -> 0.079951299
B8: Net income growth | D8: =(IS!D14-IS!C14)/IS!C14 -> 0.75766717 | E8: =(IS!E14-IS!D14)/IS!D14 -> 0.75028604 | F8: =(IS!F14-IS!E14)/IS!E14 -> 0.34580814 | G8: =(IS!G14-IS!F14)/IS!F14 -> 0.70163934 | H8: =(IS!H14-IS!G14)/IS!G14 -> 0.84985371 | I8: =(IS!I14-IS!H14)/IS!H14 -> 0.60994522 | J8: =(IS!J14-IS!I14)/IS!I14 -> -0.11252486 | K8: =(IS!K14-IS!J14)/IS!J14 -> 0.066771067 | ... V8: =(IS!V14-IS!U14)/IS!U14 -> 0.19541089

Sheet BS
B2: Balance Sheet - As Reported
C3: Sep '06 | D3: Sep '07 | E3: Sep '08 | F3: Sep '09 | G3: Sep '10 | H3: Sep '11 | I3: Sep '12 | J3: Sep '13 | K3: Sep '14 | L3: Sep '15 | M3: Sep '16 | N3: Sep '17 | O3: Sep '18 | P3: Sep '19 | Q3: Sep '20 | R3: Sep '21 | S3: Sep '22 | T3: Sep '23 | U3: Sep '24 | V3: Sep '25
B4: Total assets | C4: 17.205 | D4: 25.347 | E4: 39.572 | F4: 47.501 | G4: 75.183 | H4: 116.371 | I4: 176.064 | J4: 207 | K4: 231.839 | L4: 290.479 | M4: 321.686 | N4: 375.319 | O4: 365.725 | P4: 338.516 | Q4: 323.888 | R4: 351.002 | S4: 352.755 | T4: 353 | U4: 365 | V4: 359.241
B5: Total current assets | C5: 14.509 | D5: 21.956 | E5: 32.311 | F5: 31.555 | G5: 41.678 | H5: 44.988 | I5: 57.653 | J5: 73.286 | K5: 68.531 | L5: 89.378 | M5: 106.869 | N5: 128.645 | O5: 131.339 | P5: 162.819 | Q5: 143.713 | R5: 134.836 | S5: 135.405 | T5: 144 | U5: 153 | V5: 147.957
B6: Cash and cash equivalents | C6: 6.392 | D6: 9.352 | E6: 11.875 | F6: 5.263 | G6: 11.261 | H6: 9.815 | I6: 10.746 | J6: 14.259 | K6: 13.844 | L6: 21.12 | M6: 20.484 | N6: 20.289 | O6: 25.913 | P6: 48.844 | Q6: 38.016 | R6: 34.94 | S6: 23.646 | T6: 30 | U6: 30 | V6: 35.934
B7: Short-term marketable securities | C7: 3.718 | D7: 6.034 | E7: 10.236 | F7: 18.201 | G7: 14.359 | H7: 16.137 | I7: 18.383 | J7: 26.287 | K7: 11.233 | L7: 20.481 | M7: 46.671 | N7: 53.892 | O7: 40.388 | P7: 51.713 | Q7: 52.927 | R7: 27.699 | S7: 24.658 | T7: 32 | U7: 35 | V7: 18.763
B8: Accounts receivable, less allowances | C8: 1.252 | D8: 1.637 | E8: 2.422 | F8: 3.361 | G8: 5.51 | H8: 5.369 | I8: 10.93 | J8: 13.102 | K8: 17.46 | L8: 16.849 | M8: 15.754 | N8: 17.874 | O8: 23.186 | P8: 22.926 | Q8: 16.12 | R8: 26.278 | S8: 28.184 | T8: 30 | U8: 33 | V8: 39.777
B9: Inventories | C9: 0.27 | D9: 0.346 | E9: 0.509 | F9: 0.455 | G9: 1.051 | H9: 0.776 | I9: 0.791 | J9: 1.764 | K9: 2.111 | L9: 2.349 | M9: 2.132 | N9: 4.855 | O9: 3.956 | P9: 4.106 | Q9: 4.061 | R9: 6.58 | S9: 4.946 | T9: 6 | U9: 7 | V9: 5.718
B10: Other current assets | C10: 2.877 | D10: 4.587 | E10: 7.269 | F10: 4.275 | G10: 9.497 | H10: 12.891 | I10: 16.803 | J10: 17.874 | K10: 23.883 | L10: 28.579 | M10: 21.828 | N10: 31.735 | O10: 37.896 | P10: 35.23 | Q10: 11.264 | R10: 14.111 | S10: 21.223 | T10: 15 | U10: 14 | V10: 0
B11: Vendor non-trade receivables | C11: 0 | D11: 0 | E11: 0 | F11: 1.696 | G11: 4.414 | H11: 6.348 | I11: 7.762 | J11: 7.539 | K11: 9.759 | L11: 13.494 | M11: 13.545 | N11: 17.799 | O11: 25.809 | P11: 22.878 | Q11: 21.325 | R11: 25.228 | S11: 33 | T11: 32 | U11: 33 | V11: 33.18
B12: Other current assets excluding vendor non-trade receivables | C12: 2.877 | D12: 4.587 | E12: 7.269 | F12: 2.579 | G12: 5.083 | H12: 6.543 | I12: 9.041 | J12: 10.335 | K12: 14.124 | L12: 15.085 | M12: 8.283 | N12: 13.936 | O12: 12.087 | Q12: 0 | R12: 0 | S12: 0 | T12: 0 | U12: 0 | V12: 0
B13: Deferred tax assets | C13: 0.607 | D13: 0.782 | E13: 1.447 | F13: 1.135 | G13: 1.636 | H13: 2.014 | I13: 2.583 | J13: 3.453 | K13: 4.318 | L13: 5.546 | M13: 0 | N13: 0 | O13: 0 | Q13: 0 | R13: 0 | S13: 0 | T13: 0 | U13: 0 | V13: 0
B14: Other current assets excluding deferred tax assets | C14: 2.27 | D14: 3.805 | E14: 5.822 | F14: 1.444 | G14: 3.447 | H14: 4.529 | I14: 6.458 | J14: 6.882 | K14: 9.806 | L14: 9.539 | M14: 0 | N14: 0 | O14: 0 | Q14: 0 | R14: 0 | S14: 0 | T14: 0 | U14: 0 | V14: 14.585
B15: Long-term marketable securities | C15: 0 | D15: 0 | E15: 2.379 | F15: 10.528 | G15: 25.391 | H15: 55.618 | I15: 92.122 | J15: 106.215 | K15: 130.162 | L15: 164.065 | M15: 170.43 | N15: 194.714 | O15: 170.799 | P15: 105.341 | Q15: 100.887 | R15: 127.877 | S15: 120.805 | T15: 101 | U15: 91 | V15: 77.723
B16: Property, plant and equipment, net | C16: 1.281 | D16: 1.832 | E16: 2.455 | F16: 2.954 | G16: 4.768 | H16: 7.777 | I16: 15.452 | J16: 16.597 | K16: 20.624 | L16: 22.471 | M16: 27.01 | N16: 33.783 | O16: 41.304 | P16: 37.378 | Q16: 36.766 | R16: 39.44 | S16: 42.117 | T16: 44 | U16: 46 | V16: 49.834
B17: Goodwill | C17: 0.038 | D17: 0.038 | E17: 0.207 | F17: 0.206 | G17: 0.741 | H17: 0.896 | I17: 1.135 | J17: 1.577 | K17: 4.616 | L17: 5.116 | M17: 5.414 | N17: 5.717 | O17: 0 | Q17: 0 | R17: 0 | S17: 0 | T17: 0 | U17: 0 | V17: 0
B18: Acquired intangible assets, net | C18: 0.139 | D18: 0.299 | E18: 0.285 | F18: 0.247 | G18: 0.342 | H18: 3.536 | I18: 4.224 | J18: 4.179 | K18: 4.142 | L18: 3.893 | M18: 3.206 | N18: 2.298 | O18: 0 | Q18: 0 | R18: 0 | S18: 0 | T18: 0 | U18: 0 | V18: 0
B19: Other non-current assets | C19: 1.238 | D19: 1.222 | E19: 1.935 | F19: 2.011 | G19: 2.263 | H19: 3.556 | I19: 5.478 | J19: 5.146 | K19: 3.764 | L19: 5.556 | M19: 8.757 | N19: 10.162 | O19: 22.283 | P19: 32.978 | Q19: 42.522 | R19: 48.849 | S19: 54.428 | T19: 65 | U19: 75 | V19: 83.727
B20: Total liabilities and shareholders' equity | C20: 17.205 | D20: 25.347 | E20: 39.572 | F20: 47.501 | G20: 75.183 | H20: 116.371 | I20: 176.064 | J20: 207 | K20: 231.839 | L20: 290.479 | M20: 321.686 | N20: 375.319 | O20: 365.725 | P20: 338.516 | Q20: 323.888 | R20: 351 | S20: 352.755 | T20: 353 | U20: 365 | V20: 359.241
B21: Total liabilities | C21: 7.221 | D21: 10.815 | E21: 18.542 | F21: 15.861 | G21: 27.392 | H21: 39.756 | I21: 57.854 | J21: 83.451 | K21: 120.292 | L21: 171.124 | M21: 193.437 | N21: 241.272 | O21: 258.578 | P21: 248.028 | Q21: 258.549 | R21: 287.912 | S21: 302.083 | T21: 290 | U21: 308 | V21: 285.508
B22: Total current liabilities | C22: 6.443 | D22: 9.28 | E22: 14.092 | F22: 11.506 | G22: 20.722 | H22: 27.97 | I22: 38.542 | J22: 43.658 | K22: 63.448 | L22: 80.61 | M22: 79.006 | N22: 100.814 | O22: 116.866 | P22: 105.718 | Q22: 105.392 | R22: 125.481 | S22: 153.982 | T22: 145 | U22: 176 | V22: 165.631
B23: Accounts payable | C23: 3.39 | D23: 4.97 | E23: 5.52 | F23: 5.601 | G23: 12.015 | H23: 14.632 | I23: 21.175 | J23: 22.367 | K23: 30.196 | L23: 35.49 | M23: 37.294 | N23: 49.049 | O23: 55.888 | P23: 46.236 | Q23: 42.296 | R23: 54.763 | S23: 64.115 | T23: 63 | U23: 69 | V23: 69.86
B24: Accrued expenses | C24: 3.053 | D24: 4.31 | E24: 8.572 | F24: 5.905 | G24: 8.707 | H24: 13.338 | I24: 17.367 | J24: 21.291 | K24: 26.944 | L24: 34.121 | M24: 30.107 | N24: 33.292 | O24: 40.23 | P24: 43.242 | Q24: 42.684 | R24: 47.493 | S24: 60.845 | T24: 59 | U24: 78 | V24: 66.387
B25: Accrued expenses excluding deferred revenue | C25: 0 | D25: 0 | E25: 3.719 | F25: 3.852 | G25: 5.723 | H25: 9.247 | I25: 11.414 | J25: 13.856 | K25: 18.453 | L25: 25.181 | M25: 22.027 | N25: 25.744 | O25: 32.687 | P25: 37.72 | Q25: 0 | R25: 0 | S25: 0 | T25: 0 | U25: 0 | V25: 0
B26: Deferred revenue | C26: 0 | D26: 0 | E26: 4.853 | F26: 2.053 | G26: 2.984 | H26: 4.091 | I26: 5.953 | J26: 7.435 | K26: 8.491 | L26: 8.94 | M26: 8.08 | N26: 7.548 | O26: 7.543 | P26: 5.522 | Q26: 6.643 | R26: 7.6 | S26: 7.912 | T26: 8 | U26: 8 | V26: 9.055
B27: Commercial paper | C27: 0 | D27: 0 | E27: 0 | F27: 0 | G27: 0 | H27: 0 | I27: 0 | J27: 0 | K27: 6.308 | L27: 8.499 | M27: 8.105 | N27: 11.977 | O27: 11.964 | P27: 5.98 | Q27: 4.996 | R27: 6 | S27: 9.982 | T27: 6 | U27: 10 | V27: 7.979
B28: Current portion of long-term debt | C28: 0 | D28: 0 | E28: 0 | F28: 0 | G28: 0 | H28: 0 | I28: 0 | J28: 0 | K28: 0 | L28: 2.5 | M28: 3.5 | N28: 6.496 | O28: 8.784 | P28: 10.26 | Q28: 8.773 | R28: 9.6 | S28: 11.128 | T28: 10 | U28: 11 | V28: 12.35
B29: Long-term debt | C29: 0 | D29: 0 | E29: 0 | F29: 0 | G29: 0 | H29: 0 | I29: 0 | J29: 16.96 | K29: 28.987 | L29: 53.463 | M29: 75.427 | N29: 97.207 | O29: 93.735 | P29: 91.807 | Q29: 98.667 | R29: 109.106 | S29: 98.959 | T29: 95 | U29: 86 | V29: 78.328
B30: Non-current liabilities | C30: 0.778 | D30: 1.535 | E30: 4.45 | F30: 4.355 | G30: 6.67 | H30: 11.786 | I30: 19.312 | J30: 22.833 | K30: 27.857 | L30: 37.051 | M30: 39 | N30: =SUM(N31:N32) -> 43.251 | O30: 47.977 | P30: 50.503 | Q30: 54.49 | R30: 53.325 | S30: 49.142 | T30: 50 | U30: 46 | V30: 41.549
B31: Deferred revenue, non-current | C31: 0 | D31: 0 | E31: 3.029 | F31: 0.853 | G31: 1.139 | H31: 1.686 | I31: 2.648 | J31: 2.625 | K31: 3.031 | L31: 3.624 | M31: 2.9 | N31: 2.836 | O31: 2.797 | Q31: 0 | R31: 0 | S31: 0 | T31: 0 | U31: 0 | V31: 0
B32: Other non-current liabilities | C32: 0 | D32: 0 | E32: 1.421 | F32: 3.502 | G32: 5.531 | H32: 10.1 | I32: 16.664 | J32: 20.208 | K32: 24.826 | L32: 33.427 | M32: 36.074 | N32: 40.415 | O32: 45.18 | Q32: 0 | R32: 0 | S32: 0 | T32: 0 | U32: 0 | V32: 0
B33: Total shareholders' equity | C33: 9.984 | D33: 14.532 | E33: 21.03 | F33: 31.64 | G33: 47.791 | H33: 76.615 | I33: 118.21 | J33: 123.549 | K33: 111.547 | L33: 119.355 | M33: 128.249 | N33: 134.047 | O33: 107.147 | P33: 90.488 | Q33: 65.339 | R33: 63.09 | S33: 50.672 | T33: 62 | U33: 57 | V33: 73.733
B34: Common stock and additional paid-in capital | C34: 4.355 | D34: 5.368 | E34: 7.177 | F34: 8.21 | G34: 10.668 | H34: 13.331 | I34: 16.422 | J34: 19.764 | K34: 23.313 | L34: 27.416 | M34: 31.251 | N34: 35.867 | O34: 40.201 | P34: 45.174 | Q34: 50.779 | R34: 0 | S34: 0 | T34: 74 | U34: 83 | V34: 93.568
B35: Retained earnings | C35: 5.607 | D35: 9.101 | E35: 13.845 | F35: 23.353 | G35: 37.169 | H35: 62.841 | I35: 101.289 | J35: 104.256 | K35: 87.152 | L35: 92.284 | M35: 96.364 | N35: 98.33 | O35: 70.4 | P35: 45.898 | Q35: 14.966 | R35: 5.562 | S35: -3 | T35: 0 | U35: -19 | V35: -14.264
B36: Accumulated other comprehensive income / loss | C36: 0.022 | D36: 0.063 | E36: 0.008 | F36: 0.077 | G36: -0.046 | H36: 0.443 | I36: 0.499 | J36: -0.471 | K36: 1.082 | L36: -0.345 | M36: 0.634 | N36: -0.15 | O36: -3.454 | P36: -0.584 | Q36: -0.406 | R36: 0 | S36: 0 | T36: -11 | U36: -7 | V36: -5.571
B38: Working capital | C38: =C8+C11+C9-C23-C24 -> -4.921 | D38: =D8+D11+D9-D23-D24 -> -7.297 | E38: =E8+E11+E9-E23-E24 -> -11.161 | F38: =F8+F11+F9-F23-F24 -> -5.994 | G38: =G8+G11+G9-G23-G24 -> -9.747 | H38: =H8+H11+H9-H23-H24 -> -15.477 | I38: =I8+I11+I9-I23-I24 -> -19.059 | J38: =J8+J11+J9-J23-J24 -> -21.253 | ... V38: =V8+V11+V9-V23-V24 -> -57.572

Sheet BS common size
B2: Balance Sheet - As Reported - Common size
C3: Sep '06 | D3: Sep '07 | E3: Sep '08 | F3: Sep '09 | G3: Sep '10 | H3: Sep '11 | I3: Sep '12 | J3: Sep '13 | K3: Sep '14 | L3: Sep '15 | M3: Sep '16 | N3: Sep '17 | O3: Sep '18 | P3: Sep '19 | Q3: Sep '20 | R3: Sep '21 | S3: Sep '22 | T3: Sep '23 | U3: Sep '24 | V3: Sep '25
B4: Total assets in $'B - 100% | C4: =BS!C4 -> 17.205 | D4: =BS!D4 -> 25.347 | E4: =BS!E4 -> 39.572 | F4: =BS!F4 -> 47.501 | G4: =BS!G4 -> 75.183 | H4: =BS!H4 -> 116.371 | I4: =BS!I4 -> 176.064 | J4: =BS!J4 -> 207 | ... V4: =BS!V4 -> 359.241
B5: Total current assets | C5: =BS!C5/BS!C$4 -> 0.84330137 | D5: =BS!D5/BS!D$4 -> 0.86621691 | E5: =BS!E5/BS!E$4 -> 0.81651167 | F5: =BS!F5/BS!F$4 -> 0.6643018 | G5: =BS!G5/BS!G$4 -> 0.55435404 | H5: =BS!H5/BS!H$4 -> 0.38659116 | I5: =BS!I5/BS!I$4 -> 0.32745479 | J5: =BS!J5/BS!J$4 -> 0.35403865 | ... V5: =BS!V5/BS!V$4 -> 0.41186
B6: Cash and cash equivalents | C6: =BS!C6/BS!$C$4 -> 0.37151991 | D6: =BS!D6/BS!D$4 -> 0.36895885 | E6: =BS!E6/BS!E$4 -> 0.30008592 | F6: =BS!F6/BS!F$4 -> 0.11079767 | G6: =BS!G6/BS!G$4 -> 0.1497812 | H6: =BS!H6/BS!H$4 -> 0.084342319 | I6: =BS!I6/BS!I$4 -> 0.061034624 | J6: =BS!J6/BS!J$4 -> 0.068884058 | K6: =BS!K6/BS!K$4 -> 0.059713853 | ... V6: =BS!V6/BS!V$4 -> 0.10002756
B7: Short-term marketable securities | C7: =BS!C7/BS!$C$4 -> 0.21609997 | D7: =BS!D7/BS!D$4 -> 0.23805579 | E7: =BS!E7/BS!E$4 -> 0.25866774 | F7: =BS!F7/BS!F$4 -> 0.38317088 | G7: =BS!G7/BS!G$4 -> 0.19098732 | H7: =BS!H7/BS!H$4 -> 0.13866857 | I7: =BS!I7/BS!I$4 -> 0.1044109 | J7: =BS!J7/BS!J$4 -> 0.12699034 | K7: =BS!K7/BS!K$4 -> 0.048451727 | ... V7: =BS!V7/BS!V$4 -> 0.052229562
B8: Accounts receivable, less allowances | C8: =BS!C8/BS!$C$4 -> 0.072769544 | D8: =BS!D8/BS!D$4 -> 0.06458358 | E8: =BS!E8/BS!E$4 -> 0.061204892 | F8: =BS!F8/BS!F$4 -> 0.070756405 | G8: =BS!G8/BS!G$4 -> 0.073287844 | H8: =BS!H8/BS!H$4 -> 0.046136924 | I8: =BS!I8/BS!I$4 -> 0.062079698 | J8: =BS!J8/BS!J$4 -> 0.063294686 | K8: =BS!K8/BS!K$4 -> 0.075310884 | ... V8: =BS!V8/BS!V$4 -> 0.11072511
B9: Inventories | C9: =BS!C9/BS!$C$4 -> 0.015693112 | D9: =BS!D9/BS!D$4 -> 0.013650531 | E9: =BS!E9/BS!E$4 -> 0.01286263 | F9: =BS!F9/BS!F$4 -> 0.0095787457 | G9: =BS!G9/BS!G$4 -> 0.013979224 | H9: =BS!H9/BS!H$4 -> 0.006668328 | I9: =BS!I9/BS!I$4 -> 0.0044926845 | J9: =BS!J9/BS!J$4 -> 0.0085217391 | K9: =BS!K9/BS!K$4 -> 0.0091054568 | ... V9: =BS!V9/BS!V$4 -> 0.015916891
B10: Other current assets | C10: =BS!C10/BS!$C$4 -> 0.16721883 | D10: =BS!D10/BS!D$4 -> 0.18096816 | E10: =BS!E10/BS!E$4 -> 0.18369049 | F10: =BS!F10/BS!F$4 -> 0.089998105 | G10: =BS!G10/BS!G$4 -> 0.12631845 | H10: =BS!H10/BS!H$4 -> 0.11077502 | I10: =BS!I10/BS!I$4 -> 0.095436887 | J10: =BS!J10/BS!J$4 -> 0.086347826 | K10: =BS!K10/BS!K$4 -> 0.10301545 | ... V10: =BS!V10/BS!V$4 -> 0
B11: Vendor non-trade receivables | C11: =BS!C11/BS!$C$4 -> 0 | D11: =BS!D11/BS!D$4 -> 0 | E11: =BS!E11/BS!E$4 -> 0 | F11: =BS!F11/BS!F$4 -> 0.035704511 | G11: =BS!G11/BS!G$4 -> 0.058710081 | H11: =BS!H11/BS!H$4 -> 0.054549673 | I11: =BS!I11/BS!I$4 -> 0.044086241 | J11: =BS!J11/BS!J$4 -> 0.03642029 | K11: =BS!K11/BS!K$4 -> 0.042093867 | ... V11: =BS!V11/BS!V$4 -> 0.092361395
B12: Other current assets excluding vendor non-trade receivables | C12: =BS!C12/BS!$C$4 -> 0.16721883 | D12: =BS!D12/BS!D$4 -> 0.18096816 | E12: =BS!E12/BS!E$4 -> 0.18369049 | F12: =BS!F12/BS!F$4 -> 0.054293594 | G12: =BS!G12/BS!G$4 -> 0.067608369 | H12: =BS!H12/BS!H$4 -> 0.056225348 | I12: =BS!I12/BS!I$4 -> 0.051350645 | J12: =BS!J12/BS!J$4 -> 0.049927536 | K12: =BS!K12/BS!K$4 -> 0.060921588 | ... V12: =BS!V12/BS!V$4 -> 0
B13: Deferred tax assets | C13: =BS!C13/BS!$C$4 -> 0.035280442 | D13: =BS!D13/BS!D$4 -> 0.030851777 | E13: =BS!E13/BS!E$4 -> 0.036566259 | F13: =BS!F13/BS!F$4 -> 0.023894234 | G13: =BS!G13/BS!G$4 -> 0.021760238 | H13: =BS!H13/BS!H$4 -> 0.017306717 | I13: =BS!I13/BS!I$4 -> 0.014670802 | J13: =BS!J13/BS!J$4 -> 0.016681159 | K13: =BS!K13/BS!K$4 -> 0.018624994 | ... V13: =BS!V13/BS!V$4 -> 0
B14: Other current assets excluding deferred tax assets | C14: =BS!C14/BS!$C$4 -> 0.13193839 | D14: =BS!D14/BS!D$4 -> 0.15011638 | E14: =BS!E14/BS!E$4 -> 0.14712423 | F14: =BS!F14/BS!F$4 -> 0.03039936 | G14: =BS!G14/BS!G$4 -> 0.045848131 | H14: =BS!H14/BS!H$4 -> 0.038918631 | I14: =BS!I14/BS!I$4 -> 0.036679844 | J14: =BS!J14/BS!J$4 -> 0.033246377 | K14: =BS!K14/BS!K$4 -> 0.042296594 | ... V14: =BS!V14/BS!V$4 -> 0.040599486
B15: Long-term marketable securities | C15: =BS!C15/BS!$C$4 -> 0 | D15: =BS!D15/BS!D$4 -> 0 | E15: =BS!E15/BS!E$4 -> 0.060118265 | F15: =BS!F15/BS!F$4 -> 0.22163744 | G15: =BS!G15/BS!G$4 -> 0.33772262 | H15: =BS!H15/BS!H$4 -> 0.47793694 | I15: =BS!I15/BS!I$4 -> 0.52323019 | J15: =BS!J15/BS!J$4 -> 0.51311594 | K15: =BS!K15/BS!K$4 -> 0.56143272 | ... V15: =BS!V15/BS!V$4 -> 0.21635337
B16: Property, plant and equipment, net | C16: =BS!C16/BS!$C$4 -> 0.0744551 | D16: =BS!D16/BS!D$4 -> 0.072276798 | E16: =BS!E16/BS!E$4 -> 0.062038815 | F16: =BS!F16/BS!F$4 -> 0.062188164 | G16: =BS!G16/BS!G$4 -> 0.063418592 | H16: =BS!H16/BS!H$4 -> 0.066829365 | I16: =BS!I16/BS!I$4 -> 0.087763541 | J16: =BS!J16/BS!J$4 -> 0.080178744 | K16: =BS!K16/BS!K$4 -> 0.088958286 | ... V16: =BS!V16/BS!V$4 -> 0.13872025
B17: Goodwill | C17: =BS!C17/BS!$C$4 -> 0.0022086603 | D17: =BS!D17/BS!D$4 -> 0.0014991912 | E17: =BS!E17/BS!E$4 -> 0.0052309714 | F17: =BS!F17/BS!F$4 -> 0.0043367508 | G17: =BS!G17/BS!G$4 -> 0.0098559515 | H17: =BS!H17/BS!H$4 -> 0.0076995128 | I17: =BS!I17/BS!I$4 -> 0.0064465194 | J17: =BS!J17/BS!J$4 -> 0.0076183575 | K17: =BS!K17/BS!K$4 -> 0.019910369 | ... V17: =BS!V17/BS!V$4 -> 0
... B36: Accumulated other comprehensive income / loss | C36: =BS!C36/BS!$C$4 -> 0.0012786981 | D36: =BS!D36/BS!D$4 -> 0.0024855012 | E36: =BS!E36/BS!E$4 -> 0.00020216315 | F36: =BS!F36/BS!F$4 -> 0.0016210185 | G36: =BS!G36/BS!G$4 -> -0.00061184044 | H36: =BS!H36/BS!H$4 -> 0.0038067904 | I36: =BS!I36/BS!I$4 -> 0.0028341967 | J36: =BS!J36/BS!J$4 -> -0.0022753623 | K36: =BS!K36/BS!K$4 -> 0.0046670319 | ... V36: =BS!V36/BS!V$4 -> -0.015507695
B39: Calculations
B40: Cash + ST + LT investments | C40: =C6+C7+C15 -> 0.58761988 | D40: =D6+D7+D15 -> 0.60701464 | E40: =E6+E7+E15 -> 0.61887193 | F40: =F6+F7+F15 -> 0.71560599 | G40: =G6+G7+G15 -> 0.67849115 | H40: =H6+H7+H15 -> 0.70094783 | I40: =I6+I7+I15 -> 0.68867571 | J40: =J6+J7+J15 -> 0.70899034 | ... V40: =V6+V7+V15 -> 0.36861049
B41: Total AR | C41: =C8+C11 -> 0.072769544 | D41: =D8+D11 -> 0.06458358 | E41: =E8+E11 -> 0.061204892 | F41: =F8+F11 -> 0.10646092 | G41: =G8+G11 -> 0.13199793 | H41: =H8+H11 -> 0.1006866 | I41: =I8+I11 -> 0.10616594 | J41: =J8+J11 -> 0.099714976 | ... V41: =V8+V11 -> 0.20308651
B42: Total debt | C42: =C27+C28+C29 -> 0 | D42: =D27+D28+D29 -> 0 | E42: =E27+E28+E29 -> 0 | F42: =F27+F28+F29 -> 0 | G42: =G27+G28+G29 -> 0 | H42: =H27+H28+H29 -> 0 | I42: =I27+I28+I29 -> 0 | J42: =J27+J28+J29 -> 0.081932367 | ... V42: =V27+V28+V29 -> 0.27462623
B43: Goodwill and Intangible assets | C43: =C17+C18 -> 0.010287707 | D43: =D17+D18 -> 0.013295459 | E43: =E17+E18 -> 0.012433033 | F43: =F17+F18 -> 0.0095366413 | G43: =G17+G18 -> 0.014404852 | H43: =H17+H18 -> 0.03808509 | I43: =I17+I18 -> 0.030437795 | J43: =J17+J18 -> 0.027806763 | ... V43: =V17+V18 -> 0
B45: Inventory as % of COGS | C45: =-BS!C9/IS!C5 -> 0.019683604 | D45: =-BS!D9/IS!D5 -> 0.021826899 | E45: =-BS!E9/IS!E5 -> 0.020951675 | F45: =-BS!F9/IS!F5 -> 0.017715999 | G45: =-BS!G9/IS!G5 -> 0.026580006 | H45: =-BS!H9/IS!H5 -> 0.012043892 | I45: =-BS!I9/IS!I5 -> 0.0090043941 | J45: =-BS!J9/IS!J5 -> 0.016546911 | ... V45: =-BS!V9/IS!V5 -> 0.025877987
B46: AP as % of COGS | C46: =-BS!C23/IS!C5 -> 0.24713859 | D46: =-BS!D23/IS!D5 -> 0.31352511 | E46: =-BS!E23/IS!E5 -> 0.2272166 | F46: =-BS!F23/IS!F5 -> 0.218082 | G46: =-BS!G23/IS!G5 -> 0.30386181 | H46: =-BS!H23/IS!H5 -> 0.22709565 | I46: =-BS!I23/IS!I5 -> 0.24104683 | J46: =-BS!J23/IS!J5 -> 0.20980995 | ... V46: =-BS!V23/IS!V5 -> 0.31616582
B47: Accrued expenses as % of COGS | C47: =-BS!C24/IS!C5 -> 0.22257053 | D47: =-BS!D24/IS!D5 -> 0.27188998 | E47: =-BS!E24/IS!E5 -> 0.35284432 | F47: =-BS!F24/IS!F5 -> 0.22991862 | G47: =-BS!G24/IS!G5 -> 0.22020182 | H47: =-BS!H24/IS!H5 -> 0.20701215 | I47: =-BS!I24/IS!I5 -> 0.19769824 | J47: =-BS!J24/IS!J5 -> 0.19971671 | ... P47: =-BS!P24/IS!P5 -> 0.26728561 | Q47: =-(BS!Q24+BS!Q26)/IS!Q5 -> 0.29091349 | R47: =-(BS!R24+BS!R26)/IS!R5 -> 0.25867566 | S47: =-(BS!S24+BS!S26)/IS!S5 -> 0.30695089 | T47: =-(BS!T24+BS!T26)/IS!T5 -> 0.31308411 | U47: =-(BS!U24+BS!U26)/IS!U5 -> 0.40952381 | V47: =-(BS!V24+BS!V26)/IS!V5 -> 0.34142831
B48: AR as % of sales | C48: =BS!C8/IS!C4 -> 0.064820088 | D48: =BS!D8/IS!D4 -> 0.068191286 | E48: =BS!E8/IS!E4 -> 0.064602171 | F48: =BS!F8/IS!F4 -> 0.078335858 | G48: =BS!G8/IS!G4 -> 0.084476811 | H48: =BS!H8/IS!H4 -> 0.049598611 | I48: =BS!I8/IS!I4 -> 0.069836686 | J48: =BS!J8/IS!J4 -> 0.076660231 | ... V48: =BS!V8/IS!V4 -> 0.095580797
B49: Other current assets as % of sales | C49: =BS!C10/IS!C4 -> 0.14895159 | D49: =BS!D10/IS!D4 -> 0.19107723 | E49: =BS!E10/IS!E4 -> 0.19388653 | F49: =BS!F10/IS!F4 -> 0.099638737 | G49: =BS!G10/IS!G4 -> 0.14560368 | H49: =BS!H10/IS!H4 -> 0.11908655 | I49: =BS!I10/IS!I4 -> 0.10736192 | J49: =BS!J10/IS!J4 -> 0.10458136 | ... P49: =BS!P10/IS!P4 -> 0.13540938 | Q49: =(BS!Q10+BS!Q11)/IS!Q4 -> 0.11871482 | R49: =(BS!R10+BS!R11)/IS!R4 -> 0.10753738 | S49: =(BS!S10+BS!S11)/IS!S4 -> 0.13762183 | T49: =(BS!T10+BS!T11)/IS!T4 -> 0.1227154 | U49: =(BS!U10+BS!U11)/IS!U4 -> 0.1202046 | V49: =(BS!V10+BS!V11)/IS!V4 -> 0.079728759

Sheet BS graphs
B2: Balance sheet - common size - graphs
B4: Composition of Cash, ST and LT investments
B21: Liquid Assets, Debt and Total equity
B37: Liquid, Tangible and Intangible assets
B53: AR, Inventory, AP, Accrued expenses

Sheet CF
B2: Cash Flow - As Reported
C3: Sep '06 | D3: Sep '07 | E3: Sep '08 | F3: Sep '09 | G3: Sep '10 | H3: Sep '11 | I3: Sep '12 | J3: Sep '13 | K3: Sep '14 | L3: Sep '15 | M3: Sep '16 | N3: Sep '17 | O3: Sep '18 | P3: Sep '19 | Q3: Sep '20 | R3: Sep '21 | S3: Sep '22 | T3: Sep '23 | U3: Sep '24 | V3: Sep '25
B4: Cash generated by operating activities | C4: 2220 | D4: 5470 | E4: 9596 | F4: 10159 | G4: 18595 | H4: 37529 | I4: 50856 | J4: 53666 | K4: 59713 | L4: 81266 | M4: 65824 | N4: 63598 | O4: 77434 | P4: 69391 | Q4: 80674 | R4: 104038 | S4: 122151 | T4: 110543 | U4: 118254 | V4: 111482
B5: Net income | C5: 1989 | D5: 3496 | E5: 6119 | F5: 8235 | G5: 14013 | H5: 25922 | I5: 41733 | J5: 37037 | K5: 39510 | L5: 53394 | M5: 45687 | N5: 48351 | O5: 59531 | P5: 55256 | Q5: 57411 | R5: 94680 | S5: 99803 | T5: 96995 | U5: 93736 | V5: 112010
B6: Adjustments to reconcile net income to cash generated by operating activities | C6: 441 | D6: 637 | E6: 1410 | F6: 2484 | G6: 3346 | H6: 5850 | I6: 9422 | J6: 10151 | K6: 13156 | L6: 16225 | M6: 20137 | N6: 15247 | O6: 17903 | P6: 14135
B7: Depreciation and amortization | C7: 225 | D7: 317 | E7: 496 | F7: 734 | G7: 1027 | H7: 1814 | I7: 3277 | J7: 6757 | K7: 7946 | L7: 11257 | M7: 10505 | N7: 10157 | O7: 10903 | P7: 12547 | Q7: 11056 | R7: 11284 | S7: 11104 | T7: 11519 | U7: 11445 | V7: 11698
B8: Share-based compensation expense | C8: 163 | D8: 242 | E8: 516 | F8: 710 | G8: 879 | H8: 1168 | I8: 1740 | J8: 2253 | K8: 2863 | L8: 3586 | M8: 4210 | N8: 4840 | O8: 5340 | P8: 6068
B9: Deferred income tax expense / benefit | C9: 53 | D9: 78 | E9: 398 | F9: 1040 | G9: 1440 | H9: 2868 | I9: 4405 | J9: 1141 | K9: 2347 | L9: 1382 | M9: 4938 | N9: 5966 | O9: -32590 | P9: -340
B10: Excess tax benefits from stock options | C10: -- | D10: -- | E10: -- | F10: -- | G10: -- | H10: -- | I10: -- | J10: -- | K10: -- | L10: -- | M10: -- | N10: -- | P10: -
B11: Gain on sale of PowerSchool net assets | C11: -- | D11: -- | E11: -- | F11: -- | G11: -- | H11: -- | I11: -- | J11: -- | K11: -- | L11: -- | M11: -- | N11: -- | P11: -
B12: Changes in operating assets and liabilities | C12: -210 | D12: 1337 | E12: 2067 | F12: -560 | G12: 1236 | H12: 5757 | I12: -299 | J12: 6478 | K12: 7047 | L12: 11647 | M12: 484 | N12: -5550 | O12: 34694 | P12: -3488
B13: Accounts receivable, net | C13: -357 | D13: -385 | E13: -785 | F13: -939 | G13: -2142 | H13: 143 | I13: -5551 | J13: -2172 | K13: -4232 | L13: 611 | M13: 1095 | N13: -2093 | O13: -5322 | P13: 245
B14: Inventories | C14: -105 | D14: -76 | E14: -163 | F14: 54 | G14: -596 | H14: 275 | I14: -15 | J14: -973 | K14: -76 | L14: -238 | M14: 217 | N14: -2723 | O14: 828 | P14: -289
B15: Vendor non-trade receivables | C15: -- | D15: -- | E15: 110 | F15: 586 | G15: -2718 | H15: -1934 | I15: -1414 | J15: 223 | K15: -2220 | L15: -3735 | M15: -51 | N15: -4254 | O15: -8010 | P15: 2931
B16: Other current and non-current assets | C16: -2651 | D16: -1447 | E16: -73 | F16: -713 | G16: -1610 | H16: -1391 | I16: -3162 | J16: 1080 | K16: 167 | L16: -179 | M16: 1090 | N16: -5318 | O16: -423 | P16: 873
B17: Loss on disposition of property, plant and equipment | C17: 15 | D17: 12 | E17: 22 | F17: -- | G17: -- | H17: -- | I17: -- | J17: -- | K17: -- | L17: -- | M17: -- | O17: - | P17: 0
B18: Other current assets | C18: -1626 | D18: -1540 | E18: -384 | F18: -- | G18: -- | H18: -- | I18: -- | J18: -- | K18: -- | L18: -- | M18: -- | N18: -- | O18: - | P18: 0
B19: Other assets | C19: -1040 | D19: 81 | E19: 289 | F19: -- | G19: -- | H19: -- | I19: -- | J19: -- | K19: -- | L19: -- | M19: -- | N19: -- | O19: - | P19: 0
B20: Accounts payable | C20: 1611 | D20: 1494 | E20: 596 | F20: 92 | G20: 6307 | H20: 2515 | I20: 4467 | J20: 2340 | K20: 5938 | L20: 5400 | M20: 1791 | N20: 9618 | O20: 9175 | P20: -1923
B21: Other liabilities | C21: 1292 | D21: 1751 | E21: 2382 | F21: 360 | G21: 1995 | H21: 6149 | I21: 5376 | J21: 5980 | K21: 7470 | L21: 9788 | M21: -3658 | N21: -780 | O21: 38446 | P21: -5325
B22: Deferred revenue | C22: 319 | D22: 1139 | E22: 718 | F22: 521 | G22: 1217 | H22: 1654 | I22: 2824 | J22: 1459 | K22: 1460 | L22: 1042 | M22: -1554 | N22: -626 | O22: -44 | P22: -625
B23: Other current and non-current liabilities | C23: 973 | D23: 612 | E23: 1664 | F23: -161 | G23: 778 | H23: 4495 | I23: 2552 | J23: 4521 | K23: 6010 | L23: 8746 | M23: -2104 | N23: -154 | O23: 38490 | P23: -4700
B24: Cash used in / generated by investing activities | C24: 357 | D24: -3249 | E24: -8189 | F24: -17434 | G24: -13854 | H24: -40419 | I24: -48227 | J24: -33774 | K24: -22579 | L24: -56274 | M24: -45977 | N24: -46446 | O24: 16066 | P24: 45896 | Q24: -4289 | R24: -14545 | S24: -22354 | T24: 3705 | U24: 2935 | V24: 15195
B25: Purchases of marketable securities | C25: -7255 | D25: -11719 | E25: -22965 | F25: -46724 | G25: -57793 | H25: -102317 | I25: -151232 | J25: -148489 | K25: -217128 | L25: -166402 | M25: -142428 | N25: -159486 | O25: -71356 | P25: -39630
B26: Proceeds from maturities of marketable securities | C26: 7226 | D26: 6483 | E26: 11804 | F26: 19790 | G26: 24930 | H26: 20437 | I26: 13035 | J26: 20317 | K26: 18810 | L26: 14538 | M26: 21258 | N26: 31775 | O26: 55881 | P26: 40102
B27: Proceeds from sales of marketable securities | C27: 1086 | D27: 2941 | E27: 4439 | F27: 10888 | G27: 21788 | H27: 49416 | I27: 99770 | J27: 104130 | K27: 189301 | L27: 107447 | M27: 90536 | N27: 94564 | O27: 47838 | P27: 56988
B28: Proceeds from sale of PowerSchool net assets | C28: -- | D28: -- | E28: -- | F28: -- | G28: -- | H28: -- | I28: -- | J28: -- | K28: -- | L28: -- | M28: -- | N28: -- | O28: - | P28: 0
B29: Payments made in connection with business acquisitions, net | C29: 0 | D29: 0 | E29: -220 | F29: 0 | G29: -638 | H29: -244 | I29: -350 | J29: -496 | K29: -3765 | L29: -343 | M29: -297 | N29: -329 | O29: -721 | P29: -624
B30: Payments for acquisition of property, plant and equipment | C30: -657 | D30: -735 | E30: -1091 | F30: -1144 | G30: -2005 | H30: -4260 | I30: -8295 | J30: -8165 | K30: -9571 | L30: -11247 | M30: -12734 | N30: -12451 | O30: -13313 | P30: -10495 | Q30: -7309 | R30: -11085 | S30: -10708 | T30: -10959 | U30: -9447 | V30: -12715
B31: Payments for acquisition of intangible assets | C31: -28 | D31: -251 | E31: -108 | F31: -69 | G31: -116 | H31: -3192 | I31: -1107 | J31: -911 | K31: -242 | L31: -241 | M31: -814 | N31: -344 | P31: 0
B32: Other | C32: -15 | D32: 32 | E32: -48 | F32: -175 | G32: -20 | H32: -259 | I32: -48 | J32: -160 | K32: 16 | L32: -26 | M32: -1498 | N32: -175 | O32: -2263 | P32: 0
B33: Purchases of other long-term investments | C33: -25 | D33: -17 | E33: -38 | F33: -- | G33: -- | H33: -- | I33: -- | J33: -- | K33: -- | L33: -- | M33: -- | P33: 0
B34: Other excluding purchases of other long-term investments | C34: 10 | D34: 49 | E34: -10 | F34: -- | G34: -- | H34: -- | I34: -- | J34: -- | K34: -- | L34: -- | M34: -- | P34: 0
B35: Cash used in / generated by financing activities | C35: 324 | D35: 739 | E35: 1116 | F35: 663 | G35: 1257 | H35: 1444 | I35: -1698 | J35: -16379 | K35: -37549 | L35: -17716 | M35: -20483 | N35: -17347 | O35: -87876 | P35: -90976 | Q35: -86820 | R35: -93353 | S35: -110749 | T35: -108488 | U35: -121983 | V35: -120686
B36: Proceeds from issuance of common stock | C36: 318 | D36: 365 | E36: 483 | F36: 475 | G36: 912 | H36: 831 | I36: 665 | J36: 530 | K36: 730 | L36: 543 | M36: 495 | N36: 555 | O36: 669 | P36: 781
B37: Excess tax benefits from equity awards | C37: 361 | D37: 377 | E37: 757 | F37: 270 | G37: 751 | H37: 1133 | I37: 1351 | J37: 701 | K37: 739 | L37: 749 | M37: 407 | N37: 627 | O37: - | P37: 0
B38: Payments for taxes related to net share settlement of equity awards | C38: -355 | D38: -3 | E38: -124 | F38: -82 | G38: -406 | H38: -520 | I38: -1226 | J38: -1082 | K38: -1158 | L38: -1499 | M38: -1570 | N38: -1874 | O38: -2527 | P38: -2817
B39: Payments for dividends and dividend equivalents | C39: -- | D39: -- | E39: -- | F39: -- | G39: 0 | H39: 0 | I39: -2488 | J39: -10564 | K39: -11126 | L39: -11561 | M39: -12150 | N39: -12769 | O39: -13712 | P39: -14119 | Q39: -14081 | R39: -14467 | S39: -14841 | T39: -15025 | U39: -15234 | V39: -15421
B40: Repurchase of common stock | C40: -- | D40: -- | E40: -- | F40: -- | G40: -- | H40: 0 | I40: 0 | J40: -22860 | K40: -45000 | L40: -35253 | M40: -29722 | N40: -32900 | O40: -72738 | P40: -66897 | Q40: -72358 | R40: -85971 | S40: -89402 | T40: -77550 | U40: -94949 | V40: -90711
B41: Proceeds from issuance of term debt, net | C41: -- | D41: -- | E41: -- | F41: -- | G41: -- | H41: 0 | I41: 0 | J41: 16896 | K41: 11960 | L41: 27114 | M41: =24954-2500 -> 22454 | N41: 28662 | O41: 469 | P41: -1840
B42: Change in commercial paper, net | C42: -- | D42: -- | E42: -- | F42: -- | G42: -- | H42: -- | I42: 0 | J42: 0 | K42: 6306 | L42: 2191 | M42: -397 | N42: 3852 | O42: -37 | P42: -5977
B43: Increase / decrease in cash and cash equivalents | C43: 2901 | D43: 2960 | E43: 2523 | F43: -6612 | G43: 5998 | H43: -1446 | I43: 931 | J43: 3513 | K43: -415 | L43: 7276 | M43: -636 | N43: -195 | O43: 5624 | P43: 24311
B44: Cash and cash equivalents, beginning of the period | C44: 3491 | D44: 6392 | E44: 9352 | F44: 11875 | G44: 5263 | H44: 11261 | I44: 9815 | J44: 10746 | K44: 14259 | L44: 13844 | M44: 21120 | N44: 20484 | O44: 20289
B45: Cash and cash equivalents, end of the period | C45: 6392 | D45: 9352 | E45: 11875 | F45: 5263 | G45: 11261 | H45: 9815 | I45: 10746 | J45: 14259 | K45: 13844 | L45: 21120 | M45: 20484 | N45: 20289 | O45: 25913
B46: Supplemental disclosure | C46: -- | D46: -- | E46: -- | F46: -- | G46: -- | H46: -- | I46: -- | J46: -- | K46: -- | L46: -- | M46: --
B47: Cash paid for income taxes, net | C47: -194 | D47: -863 | E47: -1267 | F47: -2997 | G47: -2697 | H47: -3338 | I47: -7682 | J47: -9128 | K47: -10026 | L47: -13252 | M47: -10444 | N47: -11591 | O47: -10417
B48: Cash paid for interest | C48: -- | D48: -- | E48: -- | F48: -- | G48: -- | H48: -- | I48: 0 | J48: 0 | K48: -339 | L48: -514 | M48: -1316 | N48: -2092 | O48: -3022

Sheet WC days chart
B2: Inventory Days | D2: Accounts Receivable Days
B5: Accounts Payable Days | F5: Working capital Days

Sheet Efficiency ratios
B2: Efficiency ratios
C4: Sep '06 | D4: Sep '07 | E4: Sep '08 | F4: Sep '09 | G4: Sep '10 | H4: Sep '11 | I4: Sep '12 | J4: Sep '13 | K4: Sep '14 | L4: Sep '15 | M4: Sep '16 | N4: Sep '17 | O4: Sep '18 | P4: Sep '19 | Q4: Sep '20 | R4: Sep '21 | S4: Sep '22 | T4: Sep '23 | U4: Sep '24 | V4: Sep '25
B5: Sales | C5: =IS!C4 -> 19.315 | D5: =IS!D4 -> 24.006 | E5: =IS!E4 -> 37.491 | F5: =IS!F4 -> 42.905 | G5: =IS!G4 -> 65.225 | H5: =IS!H4 -> 108.249 | I5: =IS!I4 -> 156.508 | J5: =IS!J4 -> 170.91 | ... V5: =IS!V4 -> 416.161
B6: Cost of sales | C6: =-IS!C5 -> 13.717 | D6: =-IS!D5 -> 15.852 | E6: =-IS!E5 -> 24.294 | F6: =-IS!F5 -> 25.683 | G6: =-IS!G5 -> 39.541 | H6: =-IS!H5 -> 64.431 | I6: =-IS!I5 -> 87.846 | J6: =-IS!J5 -> 106.606 | ... V6: =-IS!V5 -> 220.96
B7: Total assets | C7: =BS!C4 -> 17.205 | D7: =BS!D4 -> 25.347 | E7: =BS!E4 -> 39.572 | F7: =BS!F4 -> 47.501 | G7: =BS!G4 -> 75.183 | H7: =BS!H4 -> 116.371 | I7: =BS!I4 -> 176.064 | J7: =BS!J4 -> 207 | ... V7: =BS!V4 -> 359.241
B8: AR | C8: =BS!C8+BS!C11 -> 1.252 | D8: =BS!D8+BS!D11 -> 1.637 | E8: =BS!E8+BS!E11 -> 2.422 | F8: =BS!F8+BS!F11 -> 5.057 | G8: =BS!G8+BS!G11 -> 9.924 | H8: =BS!H8+BS!H11 -> 11.717 | I8: =BS!I8+BS!I11 -> 18.692 | J8: =BS!J8+BS!J11 -> 20.641 | ... V8: =BS!V8+BS!V11 -> 72.957
B9: Inventory | C9: =BS!C9 -> 0.27 | D9: =BS!D9 -> 0.346 | E9: =BS!E9 -> 0.509 | F9: =BS!F9 -> 0.455 | G9: =BS!G9 -> 1.051 | H9: =BS!H9 -> 0.776 | I9: =BS!I9 -> 0.791 | J9: =BS!J9 -> 1.764 | ... V9: =BS!V9 -> 5.718
B10: AP | C10: =BS!C23 -> 3.39 | D10: =BS!D23 -> 4.97 | E10: =BS!E23 -> 5.52 | F10: =BS!F23 -> 5.601 | G10: =BS!G23 -> 12.015 | H10: =BS!H23 -> 14.632 | I10: =BS!I23 -> 21.175 | J10: =BS!J23 -> 22.367 | ... V10: =BS!V23 -> 69.86
B12: Analysis
B13: Total assets turnover | D13: =D5/((C7+D7)/2) -> 1.1283136 | E13: =E5/((D7+E7)/2) -> 1.1550085 | F13: =F5/((E7+F7)/2) -> 0.98549493 | G13: =G5/((F7+G7)/2) -> 1.0633008 | H13: =H5/((G7+H7)/2) -> 1.1302192 | I13: =I5/((H7+I7)/2) -> 1.070378 | J13: =J5/((I7+J7)/2) -> 0.89233131 | K13: =K5/((J7+K7)/2) -> 0.83308457 | ... V13: =V5/((U7+V7)/2) -> 1.1492335
B15: AR turnover | D15: =$D$5/((C8+D8)/2) -> 16.618899 | E15: =E5/((D8+E8)/2) -> 18.473023 | F15: =F5/((E8+F8)/2) -> 11.473459 | G15: =G5/((F8+G8)/2) -> 8.7076964 | H15: =H5/((G8+H8)/2) -> 10.004066 | I15: =I5/((H8+I8)/2) -> 10.293532 | J15: =J5/((I8+J8)/2) -> 8.6904126 | K15: =K5/((J8+K8)/2) -> 7.638738 | L15: =L5/((K8+L8)/2) -> 8.1204614 | ... V15: =V5/((U8+V8)/2) -> 5.989781
B16: Inventory turnover | D16: =D6/((C9+D9)/2) -> 51.467532 | E16: =E6/((D9+E9)/2) -> 56.82807 | F16: =F6/((E9+F9)/2) -> 53.284232 | G16: =G6/((F9+G9)/2) -> 52.511288 | H16: =H6/((G9+H9)/2) -> 70.53202 | I16: =I6/((H9+I9)/2) -> 112.11997 | J16: =J6/((I9+J9)/2) -> 83.448924 | K16: =K6/((J9+K9)/2) -> 57.939613 | ... V16: =V6/((U9+V9)/2) -> 34.747602
B17: AP turnover | D17: =(D6)/((C10+D10)/2) -> 3.7923445 | E17: =(E6)/((D10+E10)/2) -> 4.6318398 | F17: =(F6)/((E10+F10)/2) -> 4.6188292 | G17: =(G6)/((F10+G10)/2) -> 4.4892144 | H17: =(H6)/((G10+H10)/2) -> 4.8358915 | I17: =(I6)/((H10+I10)/2) -> 4.9066384 | J17: =(J6)/((I10+J10)/2) -> 4.8966974 | K17: =(K6)/((J10+K10)/2) -> 4.2713696 | ... V17: =(V6)/((U10+V10)/2) -> 3.182486
B19: Days AR | D19: =365/D15 -> 21.962947 | E19: =365/E15 -> 19.758542 | F19: =365/F15 -> 31.812551 | G19: =365/G15 -> 41.916941 | H19: =365/H15 -> 36.485164 | I19: =365/I15 -> 35.459162 | J19: =365/J15 -> 42.000307 | K19: =365/K15 -> 47.782762 | ... V19: =365/V15 -> 60.937119
B20: Days Inventory | D20: =365/D16 -> 7.0918496 | E20: =365/E16 -> 6.4228822 | F20: =365/F16 -> 6.8500565 | G20: =365/G16 -> 6.9508864 | H20: =365/H16 -> 5.1749546 | I20: =365/I16 -> 3.2554413 | J20: =365/J16 -> 4.373933 | K20: =365/K16 -> 6.2996624 | ... V20: =365/V16 -> 10.504322
B21: Days AP | D21: =365/D17 -> 96.24653 | E21: =365/E17 -> 78.802379 | F21: =365/F17 -> 79.024355 | G21: =365/G17 -> 81.305986 | H21: =365/H17 -> 75.477294 | I21: =365/I17 -> 74.389016 | J21: =365/J17 -> 74.540035 | K21: =365/K17 -> 85.452685 | ... V21: =365/V17 -> 114.69022
B23: Working capital days | D23: =D19+D20-D21 -> -67.191734 | E23: =E19+E20-E21 -> -52.620955 | F23: =F19+F20-F21 -> -40.361747 | G23: =G19+G20-G21 -> -32.438158 | H23: =H19+H20-H21 -> -33.817175 | I23: =I19+I20-I21 -> -35.674413 | J23: =J19+J20-J21 -> -28.165795 | K23: =K19+K20-K21 -> -31.37026 | ... V23: =V19+V20-V21 -> -43.248774
B24: (excl accrued expenses)

Sheet Liquidity
B2: Liquidity ratios
C4: Sep '06 | D4: Sep '07 | E4: Sep '08 | F4: Sep '09 | G4: Sep '10 | H4: Sep '11 | I4: Sep '12 | J4: Sep '13 | K4: Sep '14 | L4: Sep '15 | M4: Sep '16 | N4: Sep '17 | O4: Sep '18 | P4: Sep '19 | Q4: Sep '20 | R4: Sep '21 | S4: Sep '22 | T4: Sep '23 | U4: Sep '24 | V4: Sep '25
B5: Cash | C5: =BS!C6 -> 6.392 | D5: =BS!D6 -> 9.352 | E5: =BS!E6 -> 11.875 | F5: =BS!F6 -> 5.263 | G5: =BS!G6 -> 11.261 | H5: =BS!H6 -> 9.815 | I5: =BS!I6 -> 10.746 | J5: =BS!J6 -> 14.259 | ... V5: =BS!V6 -> 35.934
B6: ST marketable securities | C6: =BS!C7 -> 3.718 | D6: =BS!D7 -> 6.034 | E6: =BS!E7 -> 10.236 | F6: =BS!F7 -> 18.201 | G6: =BS!G7 -> 14.359 | H6: =BS!H7 -> 16.137 | I6: =BS!I7 -> 18.383 | J6: =BS!J7 -> 26.287 | ... V6: =BS!V7 -> 18.763
B7: Total AR | C7: =BS!C8+BS!C11 -> 1.252 | D7: =BS!D8+BS!D11 -> 1.637 | E7: =BS!E8+BS!E11 -> 2.422 | F7: =BS!F8+BS!F11 -> 5.057 | G7: =BS!G8+BS!G11 -> 9.924 | H7: =BS!H8+BS!H11 -> 11.717 | I7: =BS!I8+BS!I11 -> 18.692 | J7: =BS!J8+BS!J11 -> 20.641 | ... V7: =BS!V8+BS!V11 -> 72.957
B8: Inventory | C8: =BS!C9 -> 0.27 | D8: =BS!D9 -> 0.346 | E8: =BS!E9 -> 0.509 | F8: =BS!F9 -> 0.455 | G8: =BS!G9 -> 1.051 | H8: =BS!H9 -> 0.776 | I8: =BS!I9 -> 0.791 | J8: =BS!J9 -> 1.764 | ... V8: =BS!V9 -> 5.718
B9: Current assets | C9: =BS!C5 -> 14.509 | D9: =BS!D5 -> 21.956 | E9: =BS!E5 -> 32.311 | F9: =BS!F5 -> 31.555 | G9: =BS!G5 -> 41.678 | H9: =BS!H5 -> 44.988 | I9: =BS!I5 -> 57.653 | J9: =BS!J5 -> 73.286 | ... V9: =BS!V5 -> 147.957
B10: Current liabilities | C10: =BS!C22 -> 6.443 | D10: =BS!D22 -> 9.28 | E10: =BS!E22 -> 14.092 | F10: =BS!F22 -> 11.506 | G10: =BS!G22 -> 20.722 | H10: =BS!H22 -> 27.97 | I10: =BS!I22 -> 38.542 | J10: =BS!J22 -> 43.658 | ... V10: =BS!V22 -> 165.631
B11: Cash flow from operations | C11: =CF!C4/1000 -> 2.22 | D11: =CF!D4/1000 -> 5.47 | E11: =CF!E4/1000 -> 9.596 | F11: =CF!F4/1000 -> 10.159 | G11: =CF!G4/1000 -> 18.595 | H11: =CF!H4/1000 -> 37.529 | I11: =CF!I4/1000 -> 50.856 | J11: =CF!J4/1000 -> 53.666 | ... V11: =CF!V4/1000 -> 111.482
B13: Analysis
B14: Current ratio | C14: =C9/C10 -> 2.2519013 | D14: =D9/D10 -> 2.3659483 | E14: =E9/E10 -> 2.2928612 | F14: =F9/F10 -> 2.7424822 | G14: =G9/G10 -> 2.0112923 | H14: =H9/H10 -> 1.6084376 | I14: =I9/I10 -> 1.4958487 | J14: =J9/J10 -> 1.6786385 | ... V14: =V9/V10 -> 0.89329292
B15: Quick ratio | C15: =(C9-C8)/C10 -> 2.2099953 | D15: =(D9-D8)/D10 -> 2.3286638 | E15: =(E9-E8)/E10 -> 2.2567414 | F15: =(F9-F8)/F10 -> 2.7029376 | G15: =(G9-G8)/G10 -> 1.9605733 | H15: =(H9-H8)/H10 -> 1.5806936 | I15: =(I9-I8)/I10 -> 1.4753256 | J15: =(J9-J8)/J10 -> 1.6382335 | ... V15: =(V9-V8)/V10 -> 0.8587704
B16: Cash ratio | C16: =(C5+C6)/C10 -> 1.5691448 | D16: =(D5+D6)/D10 -> 1.6579741 | E16: =(E5+E6)/E10 -> 1.5690463 | F16: =(F5+F6)/F10 -> 2.0392839 | G16: =(G5+G6)/G10 -> 1.2363671 | H16: =(H5+H6)/H10 -> 0.92785127 | I16: =(I5+I6)/I10 -> 0.75577292 | J16: =(J5+J6)/J10 -> 0.92871868 | ... V16: =(V5+V6)/V10 -> 0.33023407
B17: CFO/Current liabilities | C17: =C11/C10 -> 0.34455999 | D17: =D11/D10 -> 0.58943966 | E17: =E11/E10 -> 0.68095373 | F17: =F11/F10 -> 0.88293064 | G17: =G11/G10 -> 0.89735547 | H17: =H11/H10 -> 1.341759 | I17: =I11/I10 -> 1.3194956 | J17: =J11/J10 -> 1.2292363 | ... V17: =V11/V10 -> 0.67307448

Sheet Leverage
B2: Leverage ratios
C4: Sep '06 | D4: Sep '07 | E4: Sep '08 | F4: Sep '09 | G4: Sep '10 | H4: Sep '11 | I4: Sep '12 | J4: Sep '13 | K4: Sep '14 | L4: Sep '15 | M4: Sep '16 | N4: Sep '17 | O4: Sep '18 | P4: Sep '19 | Q4: Sep '20 | R4: Sep '21 | S4: Sep '22 | T4: Sep '23 | U4: Sep '24 | V4: Sep '25
B5: ST debt | C5: =BS!C27+BS!C28 -> 0 | D5: =BS!D27+BS!D28 -> 0 | E5: =BS!E27+BS!E28 -> 0 | F5: =BS!F27+BS!F28 -> 0 | G5: =BS!G27+BS!G28 -> 0 | H5: =BS!H27+BS!H28 -> 0 | I5: =BS!I27+BS!I28 -> 0 | J5: =BS!J27+BS!J28 -> 0 | ... V5: =BS!V27+BS!V28 -> 20.329
B6: LT debt | C6: =BS!C29 -> 0 | D6: =BS!D29 -> 0 | E6: =BS!E29 -> 0 | F6: =BS!F29 -> 0 | G6: =BS!G29 -> 0 | H6: =BS!H29 -> 0 | I6: =BS!I29 -> 0 | J6: =BS!J29 -> 16.96 | ... V6: =BS!V29 -> 78.328
B7: Cash | C7: =BS!C6 -> 6.392 | D7: =BS!D6 -> 9.352 | E7: =BS!E6 -> 11.875 | F7: =BS!F6 -> 5.263 | G7: =BS!G6 -> 11.261 | H7: =BS!H6 -> 9.815 | I7: =BS!I6 -> 10.746 | J7: =BS!J6 -> 14.259 | ... V7: =BS!V6 -> 35.934
B8: ST marketable securities | C8: =BS!C7 -> 3.718 | D8: =BS!D7 -> 6.034 | E8: =BS!E7 -> 10.236 | F8: =BS!F7 -> 18.201 | G8: =BS!G7 -> 14.359 | H8: =BS!H7 -> 16.137 | I8: =BS!I7 -> 18.383 | J8: =BS!J7 -> 26.287 | ... V8: =BS!V7 -> 18.763
B9: LT marketable securities | C9: =BS!C15 -> 0 | D9: =BS!D15 -> 0 | E9: =BS!E15 -> 2.379 | F9: =BS!F15 -> 10.528 | G9: =BS!G15 -> 25.391 | H9: =BS!H15 -> 55.618 | I9: =BS!I15 -> 92.122 | J9: =BS!J15 -> 106.215 | ... V9: =BS!V15 -> 77.723
B10: Equity book value | C10: =BS!C33 -> 9.984 | D10: =BS!D33 -> 14.532 | E10: =BS!E33 -> 21.03 | F10: =BS!F33 -> 31.64 | G10: =BS!G33 -> 47.791 | H10: =BS!H33 -> 76.615 | I10: =BS!I33 -> 118.21 | J10: =BS!J33 -> 123.549 | ... V10: =BS!V33 -> 73.733
B11: Total assets | C11: =BS!C4 -> 17.205 | D11: =BS!D4 -> 25.347 | E11: =BS!E4 -> 39.572 | F11: =BS!F4 -> 47.501 | G11: =BS!G4 -> 75.183 | H11: =BS!H4 -> 116.371 | I11: =BS!I4 -> 176.064 | J11: =BS!J4 -> 207 | ... V11: =BS!V4 -> 359.241
B12: Operating income | C12: =IS!C10 -> 2.453 | D12: =IS!D10 -> 4.409 | E12: =IS!E10 -> 8.327 | F12: =IS!F10 -> 11.74 | G12: =IS!G10 -> 18.385 | H12: =IS!H10 -> 33.79 | I12: =IS!I10 -> 55.241 | J12: =IS!J10 -> 48.999 | ... V12: =IS!V10 -> 133.05
B13: Interest expense | C13: =IS!C16 -> 0 | D13: =IS!D16 -> 0 | E13: =IS!E16 -> 0 | F13: =IS!F16 -> 0 | G13: =IS!G16 -> 0 | H13: =IS!H16 -> 0 | I13: =IS!I16 -> 0 | J13: =IS!J16 -> 0.136 | ... V13: =IS!V16 -> 4
B14: Depreciation and amortization | C14: =CF!C7/1000 -> 0.225 | D14: =CF!D7/1000 -> 0.317 | E14: =CF!E7/1000 -> 0.496 | F14: =CF!F7/1000 -> 0.734 | G14: =CF!G7/1000 -> 1.027 | H14: =CF!H7/1000 -> 1.814 | I14: =CF!I7/1000 -> 3.277 | J14: =CF!J7/1000 -> 6.757 | ... V14: =CF!V7/1000 -> 11.698
B15: CapEx | C15: =-CF!C30/1000 -> 0.657 | D15: =-CF!D30/1000 -> 0.735 | E15: =-CF!E30/1000 -> 1.091 | F15: =-CF!F30/1000 -> 1.144 | G15: =-CF!G30/1000 -> 2.005 | H15: =-CF!H30/1000 -> 4.26 | I15: =-CF!I30/1000 -> 8.295 | J15: =-CF!J30/1000 -> 8.165 | ... V15: =-CF!V30/1000 -> 12.715
B16: CFO | C16: =CF!C4/1000 -> 2.22 | D16: =CF!D4/1000 -> 5.47 | E16: =CF!E4/1000 -> 9.596 | F16: =CF!F4/1000 -> 10.159 | G16: =CF!G4/1000 -> 18.595 | H16: =CF!H4/1000 -> 37.529 | I16: =CF!I4/1000 -> 50.856 | J16: =CF!J4/1000 -> 53.666 | ... V16: =CF!V4/1000 -> 111.482
B18: EBITDA (Ops income + D + A) | C18: =C12+C14 -> 2.678 | D18: =D12+D14 -> 4.726 | E18: =E12+E14 -> 8.823 | F18: =F12+F14 -> 12.474 | G18: =G12+G14 -> 19.412 | H18: =H12+H14 -> 35.604 | I18: =I12+I14 -> 58.518 | J18: =J12+J14 -> 55.756 | ... V18: =V12+V14 -> 144.748
B19: FCF (CFO - CapEx) | C19: =C16-C15 -> 1.563 | D19: =D16-D15 -> 4.735 | E19: =E16-E15 -> 8.505 | F19: =F16-F15 -> 9.015 | G19: =G16-G15 -> 16.59 | H19: =H16-H15 -> 33.269 | I19: =I16-I15 -> 42.561 | J19: =J16-J15 -> 45.501 | ... V19: =V16-V15 -> 98.767
B21: Analysis
B22: Net debt | C22: =(C5+C6)-C7 -> -6.392 | D22: =(D5+D6)-D7 -> -9.352 | E22: =(E5+E6)-E7 -> -11.875 | F22: =(F5+F6)-F7 -> -5.263 | G22: =(G5+G6)-G7 -> -11.261 | H22: =(H5+H6)-H7 -> -9.815 | I22: =(I5+I6)-I7 -> -10.746 | J22: =(J5+J6)-J7 -> 2.701 | ... V22: =(V5+V6)-V7 -> 62.723
B23: Debt/Assets | C23: =(C5+C6)/C11 -> 0 | D23: =(D5+D6)/D11 -> 0 | E23: =(E5+E6)/E11 -> 0 | F23: =(F5+F6)/F11 -> 0 | G23: =(G5+G6)/G11 -> 0 | H23: =(H5+H6)/H11 -> 0 | I23: =(I5+I6)/I11 -> 0 | J23: =(J5+J6)/J11 -> 0.081932367 | ... V23: =(V5+V6)/V11 -> 0.27462623
B24: Debt/Equity book value | C24: =(C5+C6)/C10 -> 0 | D24: =(D5+D6)/D10 -> 0 | E24: =(E5+E6)/E10 -> 0 | F24: =(F5+F6)/F10 -> 0 | G24: =(G5+G6)/G10 -> 0 | H24: =(H5+H6)/H10 -> 0 | I24: =(I5+I6)/I10 -> 0 | J24: =(J5+J6)/J10 -> 0.13727347 | ... V24: =(V5+V6)/V10 -> 1.3380305
B25: Interest coverage ratio (EBIT/interest) | J25: =J12/J13 -> 360.28676 | K25: =K12/K13 -> 136.72656 | L25: =L12/L13 -> 97.175989 | M25: =M12/M13 -> 41.112329 | N25: =N12/N13 -> 26.671304 | O25: =O12/O13 -> 21.882099 | P25: =P12/P13 -> 17.758333 | Q25: =Q12/Q13 -> 22.857931 | ... V25: =V12/V13 -> 33.2625
B26: EBITDA/interest | J26: =J18/J13 -> 409.97059 | K26: =K18/K13 -> 157.41927 | L26: =L18/L13 -> 112.53342 | M26: =M18/M13 -> 48.307534 | N26: =N18/N13 -> 31.087391 | O26: =O18/O13 -> 25.247222 | P26: =P18/P13 -> 21.243611 | Q26: =Q18/Q13 -> 26.670345 | ... V26: =V18/V13 -> 36.187
B27: CFO/interest | J27: =J16/J13 -> 394.60294 | K27: =K16/K13 -> 155.5026 | L27: =L16/L13 -> 110.86767 | M27: =M16/M13 -> 45.084932 | N27: =N16/N13 -> 27.651304 | O27: =O16/O13 -> 23.899383 | P27: =P16/P13 -> 19.275278 | Q27: =Q16/Q13 -> 27.818621 | ... V27: =V16/V13 -> 27.8705
B28: Debt/EBITDA | J28: =(J5+J6)/J18 -> 0.30418251 | K28: =(K5+K6)/K18 -> 0.58388063 | L28: =(L5+L6)/L18 -> 0.78148072 | M28: =(M5+M6)/M18 -> 1.2339889 | N28: =(N5+N6)/N18 -> 1.6178795 | O28: =(O5+O6)/O18 -> 1.3995306 | P28: =(P5+P6)/P18 -> 1.4128038 | Q28: =(Q5+Q6)/Q18 -> 1.4537133 | ... V28: =(V5+V6)/V18 -> 0.68157764
B29: Debt/CFO | J29: =(J5+J6)/J16 -> 0.31602877 | K29: =(K5+K6)/K16 -> 0.59107732 | L29: =(L5+L6)/L16 -> 0.79322226 | M29: =(M5+M6)/M16 -> 1.3221925 | N29: =(N5+N6)/N16 -> 1.8189251 | O29: =(O5+O6)/O16 -> 1.4784591 | P29: =(P5+P6)/P16 -> 1.5570751 | Q29: =(Q5+Q6)/Q16 -> 1.393708 | ... V29: =(V5+V6)/V16 -> 0.88495901
B30: Debt/FCF | J30: =(J5+J6)/J19 -> 0.37273906 | K30: =(K5+K6)/K19 -> 0.70390092 | L30: =(L5+L6)/L19 -> 0.92063583 | M30: =(M5+M6)/M19 -> 1.6393294 | N30: =(N5+N6)/N19 -> 2.2617162 | O30: =(O5+O6)/O19 -> 1.7854213 | P30: =(P5+P6)/P19 -> 1.8345388 | Q30: =(Q5+Q6)/Q19 -> 1.5325564 | ... V30: =(V5+V6)/V19 -> 0.99888627

Sheet Share price performance
B2: Share price performance
C4: Sep '06 | D4: Sep '07 | E4: Sep '08 | F4: Sep '09 | G4: Sep '10 | H4: Sep '11 | I4: Sep '12 | J4: Sep '13 | K4: Sep '14 | L4: Sep '15 | M4: Sep '16
B5: Share price | C5: 11 | D5: 25 | E5: 14 | F5: 25 | G5: 40 | H5: 54 | I5: 79 | J5: 71 | K5: 105 | L5: 118 | M5: 113
B6: Equity book value | C6: =BS!C33 -> 9.984 | D6: =BS!D33 -> 14.532 | E6: =BS!E33 -> 21.03 | F6: =BS!F33 -> 31.64 | G6: =BS!G33 -> 47.791 | H6: =BS!H33 -> 76.615 | I6: =BS!I33 -> 118.21 | J6: =BS!J33 -> 123.549 | ... M6: =BS!M33 -> 128.249
B7: Net income | C7: =IS!C14 -> 1.989 | D7: =IS!D14 -> 3.496 | E7: =IS!E14 -> 6.119 | F7: =IS!F14 -> 8.235 | G7: =IS!G14 -> 14.013 | H7: =IS!H14 -> 25.922 | I7: =IS!I14 -> 41.733 | J7: =IS!J14 -> 37.037 | ... M7: =IS!M14 -> 45.687
B8: EBITDA (EBIT+D+A) | C8: =Leverage!C18 -> 2.678 | D8: =Leverage!D18 -> 4.726 | E8: =Leverage!E18 -> 8.823 | F8: =Leverage!F18 -> 12.474 | G8: =Leverage!G18 -> 19.412 | H8: =Leverage!H18 -> 35.604 | I8: =Leverage!I18 -> 58.518 | J8: =Leverage!J18 -> 55.756 | ... M8: =Leverage!M18 -> 70.529
B9: Shares outstanding (basic) | C9: =IS!#REF! -> #REF! | D9: =IS!#REF! -> #REF! | E9: =IS!#REF! -> #REF! | F9: =IS!#REF! -> #REF! | G9: =IS!#REF! -> #REF! | H9: =IS!#REF! -> #REF! | I9: =IS!#REF! -> #REF! | J9: =IS!#REF! -> #REF! | ... M9: =IS!#REF! -> #REF!
B10: =IS!#REF! -> #REF! | C10: =IS!#REF! -> #REF! | D10: =IS!#REF! -> #REF! | E10: =IS!#REF! -> #REF! | F10: =IS!#REF! -> #REF! | G10: =IS!#REF! -> #REF! | H10: =IS!#REF! -> #REF! | I10: =IS!#REF! -> #REF! | ... M10: =IS!#REF! -> #REF!
B12: Analysis
B13: Earnings per share | C13: =C7/C10 -> #REF! | D13: =D7/D10 -> #REF! | E13: =E7/E10 -> #REF! | F13: =F7/F10 -> #REF! | G13: =G7/G10 -> #REF! | H13: =H7/H10 -> #REF! | I13: =I7/I10 -> #REF! | J13: =J7/J10 -> #REF! | ... M13: =M7/M10 -> #REF!
B14: P/E trailing | C14: =C5/C13 -> #REF! | D14: =D5/D13 -> #REF! | E14: =E5/E13 -> #REF! | F14: =F5/F13 -> #REF! | G14: =G5/G13 -> #REF! | H14: =H5/H13 -> #REF! | I14: =I5/I13 -> #REF! | J14: =J5/J13 -> #REF! | ... M14: =M5/M13 -> #REF!
B15: Market cap/EBITDA | C15: =C9*C5/C8 -> #REF! | D15: =D9*D5/D8 -> #REF! | E15: =E9*E5/E8 -> #REF! | F15: =F9*F5/F8 -> #REF! | G15: =G9*G5/G8 -> #REF! | H15: =H9*H5/H8 -> #REF! | I15: =I9*I5/I8 -> #REF! | J15: =J9*J5/J8 -> #REF! | ... M15: =M9*M5/M8 -> #REF!
B16: Market/book value per share | C16: =C5/(C6/C9) -> #REF! | D16: =D5/(D6/D9) -> #REF! | E16: =E5/(E6/E9) -> #REF! | F16: =F5/(F6/F9) -> #REF! | G16: =G5/(G6/G9) -> #REF! | H16: =H5/(H6/H9) -> #REF! | I16: =I5/(I6/I9) -> #REF! | J16: =J5/(J6/J9) -> #REF! | ... M16: =M5/(M6/M9) -> #REF!

Sheet ROE
B3: ROE | C3: = | D3: Net Income | E3: = | F3: Net Income | G3: X | H3: Assets | I3: X | J3: Sales
D4: Equity | F4: Equity | H4: Assets | J4: Sales
E6: = | F6: Net Profit Margin | H6: Assets Turnover | J6: Equity Multiplier

Sheet Profitability
B2: Profitability - basic DuPont analysis
C5: Sep '06 | D5: Sep '07 | E5: Sep '08 | F5: Sep '09 | G5: Sep '10 | H5: Sep '11 | I5: Sep '12 | J5: Sep '13 | K5: Sep '14 | L5: Sep '15 | M5: Sep '16 | N5: Sep '17 | O5: Sep '18 | P5: Sep '19 | Q5: Sep '20 | R5: Sep '21 | S5: Sep '22 | T5: Sep '23 | U5: Sep '24 | V5: Sep '25
B6: Sales | C6: =IS!C4 -> 19.315 | D6: =IS!D4 -> 24.006 | E6: =IS!E4 -> 37.491 | F6: =IS!F4 -> 42.905 | G6: =IS!G4 -> 65.225 | H6: =IS!H4 -> 108.249 | I6: =IS!I4 -> 156.508 | J6: =IS!J4 -> 170.91 | ... V6: =IS!V4 -> 416.161
B7: Net income | C7: =IS!C14 -> 1.989 | D7: =IS!D14 -> 3.496 | E7: =IS!E14 -> 6.119 | F7: =IS!F14 -> 8.235 | G7: =IS!G14 -> 14.013 | H7: =IS!H14 -> 25.922 | I7: =IS!I14 -> 41.733 | J7: =IS!J14 -> 37.037 | ... V7: =IS!V14 -> 112.01
B8: Equity book value | C8: =BS!C33 -> 9.984 | D8: =BS!D33 -> 14.532 | E8: =BS!E33 -> 21.03 | F8: =BS!F33 -> 31.64 | G8: =BS!G33 -> 47.791 | H8: =BS!H33 -> 76.615 | I8: =BS!I33 -> 118.21 | J8: =BS!J33 -> 123.549 | ... V8: =BS!V33 -> 73.733
B9: Total assets | C9: =BS!C4 -> 17.205 | D9: =BS!D4 -> 25.347 | E9: =BS!E4 -> 39.572 | F9: =BS!F4 -> 47.501 | G9: =BS!G4 -> 75.183 | H9: =BS!H4 -> 116.371 | I9: =BS!I4 -> 176.064 | J9: =BS!J4 -> 207 | ... V9: =BS!V4 -> 359.241
B11: Analysis
B12: Return on equity | D12: =D7/((D8+C8)/2) -> 0.2852015 | E12: =E7/((E8+D8)/2) -> 0.34413138 | F12: =F7/((F8+E8)/2) -> 0.31270173 | G12: =G7/((G8+F8)/2) -> 0.35283454 | H12: =H7/((H8+G8)/2) -> 0.41673231 | I12: =I7/((I8+H8)/2) -> 0.42841524 | J12: =J7/((J8+I8)/2) -> 0.30639604 | K12: =K7/((K8+J8)/2) -> 0.33611801 | ... V12: =V7/((V8+U8)/2) -> 1.7135689
B14: Net profit margin | D14: =D7/D6 -> 0.14563026 | E14: =E7/E6 -> 0.1632125 | F14: =F7/F6 -> 0.19193567 | G14: =G7/G6 -> 0.21484094 | H14: =H7/H6 -> 0.23946642 | I14: =I7/I6 -> 0.26665091 | J14: =J7/J6 -> 0.2167047 | K14: =K7/K6 -> 0.21614377 | ... V14: =V7/V6 -> 0.26915064
B15: Assets turnover | D15: =D6/((D9+C9)/2) -> 1.1283136 | E15: =E6/((E9+D9)/2) -> 1.1550085 | F15: =F6/((F9+E9)/2) -> 0.98549493 | G15: =G6/((G9+F9)/2) -> 1.0633008 | H15: =H6/((H9+G9)/2) -> 1.1302192 | I15: =I6/((I9+H9)/2) -> 1.070378 | J15: =J6/((J9+I9)/2) -> 0.89233131 | K15: =K6/((K9+J9)/2) -> 0.83308457 | ... V15: =V6/((V9+U9)/2) -> 1.1492335
B16: Equity multiplier (Assets/equity) | D16: =(D9+C9)/(D8+C8) -> 1.7356828 | E16: =(E9+D9)/(E8+D8) -> 1.825516 | F16: =(F9+E9)/(F8+E8) -> 1.6531802 | G16: =(G9+F9)/(G8+F8) -> 1.5445355 | H16: =(H9+G9)/(H8+G8) -> 1.5397489 | I16: =(I9+H9)/(I8+H8) -> 1.5010137 | J16: =(J9+I9)/(J8+I8) -> 1.584487 | K16: =(K9+J9)/(K8+J8) -> 1.8666375 | ... V16: =(V9+U9)/(V8+U8) -> 5.5398484
B17: Return on equity | D17: =D14*D15*D16 -> 0.2852015 | E17: =E14*E15*E16 -> 0.34413138 | F17: =F14*F15*F16 -> 0.31270173 | G17: =G14*G15*G16 -> 0.35283454 | H17: =H14*H15*H16 -> 0.41673231 | I17: =I14*I15*I16 -> 0.42841524 | J17: =J14*J15*J16 -> 0.30639604 | K17: =K14*K15*K16 -> 0.33611801 | ... V17: =V14*V15*V16 -> 1.7135689
