Workbook

Sheet Balance sheet
B2: Balance sheet
B4: Cash | C4: ='CF statement'!C15 -> 2000
B5: AR | C5: 1500
B6: Inventory | C6: 2000
B7: Prepaid expenses | C7: 1200
B8: Total current assets | C8: =SUM(C4:C7) -> 6700
B10: PPE net | C10: 10000
B11: Long-term investments | C11: =C12-C10 -> 8283.3333
B12: Total long-term assets | C12: =C13-C8 -> 18283.333
B13: Total assets | C13: =C22 -> 24983.333
B15: Accounts payable | C15: =C17-C16 -> 1983.3333
B16: Short-term debt | C16: ='CF statement'!C6*2 -> 3600
B17: Total current liabilities | C17: =C8/1.2 -> 5583.3333
B18: Long-term debt | C18: =C20-C16 -> 6400
B19: Total liabilities | C19: =C17+C18 -> 11983.333
B20: Common stock | C20: 10000
B21: RE | C21: 3000
B22: Total liabilities and equity | C22: =C21+C19+C20 -> 24983.333
B24: Check BS | C24: =C13-C22 -> 0

Sheet Income Statement
B2: Income statement
B4: Revenue | C4: 15000
B5: Cost of revenue | C5: =5*'Balance sheet'!C15 -> 9916.6667
B6: Gross profit | C6: =C4-C5 -> 5083.3333
B8: Operating expenses | C8: =C6-C9 -> 2833.3333
B9: Operating income | C9: =0.15*C4 -> 2250
B11: Non-operating expenses | C11: =C9-C12 -> 351.26582
B12: Pre-tax income | C12: =C15/(1-0.21) -> 1898.7342
B14: Income taxes | C14: =C12-C15 -> 398.73418
B15: Net income | C15: ='Balance sheet'!C21-2000+500 -> 1500

Sheet CF statement
B2: Cash flow statement
B4: Net Income | C4: ='Income Statement'!C15 -> 1500
B5: Adjustments to the net income | C5: 300
B6: Cash flow from operations | C6: =SUM(C4:C5) -> 1800
B8: Cash flow from investing | C8: 0
B10: Cash flow from financing | C10: -500
B12: Net change in cash | C12: =SUM(C6:C10) -> 1300
B14: Beginning cash | C14: 700
B15: Ending cash | C15: =C12+C14 -> 2000
